Workbook
Name Slicer_Product_Category: #REF!
Name Slicer_store_region: #REF!

Sheet Dashboard
D2: Sales Performance Dashboard
D4: Oct 2023 – Oct 2025 | Source: Sales_Fact
D6: Total Revenue | F6: Total Orders | H6: Avg Order Value | J6: Unique Customers | L6: Top Region | N6: Top Category
D7: =SUM(Sales_Fact!$O$2:$O$2001) -> 2170969.8 | F7: =COUNTA(Sales_Fact!$A$2:$A$2001) -> 2000 | H7: =AVERAGE(Sales_Fact!$O$2:$O$2001) -> 1085.4849 | J7: =SUMPRODUCT(1/COUNTIF(Sales_Fact!$C$2:$C$2001,Sales_Fact!$C$2:$C$2001)) -> 492 | L7: =INDEX('Pivot and Visualizations '!$A$4:$A$7,MATCH(MAX('Pivot and Visualizations '!$B$4:$B$7),'Pivot and Visualizations '!$B$4:$B$7,0)) -> North | N7: =INDEX('Pivot and Visualizations '!$A$12:$A$16,MATCH(MAX('Pivot and Visualizations '!$B$12:$B$16),'Pivot and Visualizations '!$B$12:$B$16,0)) -> Sports
D10: Key Visualizations

Sheet Customer_Dim
A1: Customer_ID | B1: Name | C1: Age | D1: Gender | E1: City | F1: State | G1: Country | H1: Loyalty_Level | I1: Clean name | J1: Clean city | K1: Clean Country | L1: Clean Customer ID | M1: Clean Loyalty | N1: Age Validation
A2: CUST1000 | B2: sheena bonilla | C2: 55 | D2: Male | E2: Donaldton | F2: North Carolina | G2: USA | I2: =PROPER(TRIM(B2)) -> Sheena Bonilla | J2: =PROPER(TRIM(E2)) -> Donaldton | K2: =IF(OR(G2="USA",G2="usa"),"USA",K5 IF(G2="United States of America","USA","USA")) -> USA | L2: =IF(LEFT(A2,1)="C","CUST"&RIGHT(A2,4),A2) -> CUST1000 | M2: =IF(H2="","Standard",H2) -> Standard | N2: =IF(OR(C2<18,C2>70),"Check Age","Ok") -> Ok
A3: CUST1001 | B3: Eugene Nelson | C3: 26 | D3: Female | E3: Phillipsmouth | F3: North Dakota | G3: USA | H3: Platinum | I3: =PROPER(TRIM(B3)) -> Eugene Nelson | J3: =PROPER(TRIM(E3)) -> Phillipsmouth | K3: =IF(OR(G3="USA",G3="usa"),"USA",K6 IF(G3="United States of America","USA","USA")) -> USA | L3: =IF(LEFT(A3,1)="C","CUST"&RIGHT(A3,4),A3) -> CUST1001 | M3: =IF(H3="","Standard",H3) -> Platinum | N3: =IF(OR(C3<18,C3>70),"Check Age","Ok") -> Ok
A4: CUST1002 | B4: dr. Benjamin Price | C4: 29 | D4: Female | E4: Kylebury | F4: Alabama | G4: USA | H4: Platinum | I4: =PROPER(TRIM(B4)) -> Dr. Benjamin Price | J4: =PROPER(TRIM(E4)) -> Kylebury | K4: =IF(OR(G4="USA",G4="usa"),"USA",K7 IF(G4="United States of America","USA","USA")) -> USA | L4: =IF(LEFT(A4,1)="C","CUST"&RIGHT(A4,4),A4) -> CUST1002 | M4: =IF(H4="","Standard",H4) -> Platinum | N4: =IF(OR(C4<18,C4>70),"Check Age","Ok") -> Ok | P4: Count | Q4: =COUNTA(A:A) -> 501
A5: CUST1003 | B5: jeremy harris | C5: 59 | D5: Female | E5: Thomastown | F5: Ohio | G5: USA | H5: Bronze | I5: =PROPER(TRIM(B5)) -> Jeremy Harris | J5: =PROPER(TRIM(E5)) -> Thomastown | K5: =IF(OR(G5="USA",G5="usa"),"USA",K8 IF(G5="United States of America","USA","USA")) -> USA | L5: =IF(LEFT(A5,1)="C","CUST"&RIGHT(A5,4),A5) -> CUST1003 | M5: =IF(H5="","Standard",H5) -> Bronze | N5: =IF(OR(C5<18,C5>70),"Check Age","Ok") -> Ok | P5: Average | Q5: =ROUNDUP(AVERAGE(C:C),2) -> 41.57
A6: CUST1004 | B6: Caroline Collins | C6: 64 | D6: Female | E6: Nicholasshire | F6: California | G6: USA | H6: Silver | I6: =PROPER(TRIM(B6)) -> Caroline Collins | J6: =PROPER(TRIM(E6)) -> Nicholasshire | K6: =IF(OR(G6="USA",G6="usa"),"USA",K9 IF(G6="United States of America","USA","USA")) -> USA | L6: =IF(LEFT(A6,1)="C","CUST"&RIGHT(A6,4),A6) -> CUST1004 | M6: =IF(H6="","Standard",H6) -> Silver | N6: =IF(OR(C6<18,C6>70),"Check Age","Ok") -> Ok | P6: Male | Q6: =COUNTIF(D:D,"Male") -> 238
A7: CUST1005 | B7: Christine Vaughn | C7: 24 | D7: Male | E7: East Amandamouth | F7: Oregon | G7: USA | H7: Bronze | I7: =PROPER(TRIM(B7)) -> Christine Vaughn | J7: =PROPER(TRIM(E7)) -> East Amandamouth | K7: =IF(OR(G7="USA",G7="usa"),"USA",K10 IF(G7="United States of America","USA","USA")) -> USA | L7: =IF(LEFT(A7,1)="C","CUST"&RIGHT(A7,4),A7) -> CUST1005 | M7: =IF(H7="","Standard",H7) -> Bronze | N7: =IF(OR(C7<18,C7>70),"Check Age","Ok") -> Ok | P7: Female | Q7: =COUNTIF(D:D,"Female") -> 262
A8: CUST1006 | B8: Amber Jackson | C8: 29 | D8: Female | E8: Deborahborough | F8: South Dakota | G8: USA | H8: Platinum | I8: =PROPER(TRIM(B8)) -> Amber Jackson | J8: =PROPER(TRIM(E8)) -> Deborahborough | K8: =IF(OR(G8="USA",G8="usa"),"USA",K11 IF(G8="United States of America","USA","USA")) -> USA | L8: =IF(LEFT(A8,1)="C","CUST"&RIGHT(A8,4),A8) -> CUST1006 | M8: =IF(H8="","Standard",H8) -> Platinum | N8: =IF(OR(C8<18,C8>70),"Check Age","Ok") -> Ok
A9: CUST1007 | B9: Daniel Boyd | C9: 29 | D9: Female | E9: West Pamelafurt | F9: West Virginia | G9: USA | H9: Bronze | I9: =PROPER(TRIM(B9)) -> Daniel Boyd | J9: =PROPER(TRIM(E9)) -> West Pamelafurt | K9: =IF(OR(G9="USA",G9="usa"),"USA",K12 IF(G9="United States of America","USA","USA")) -> USA | L9: =IF(LEFT(A9,1)="C","CUST"&RIGHT(A9,4),A9) -> CUST1007 | M9: =IF(H9="","Standard",H9) -> Bronze | N9: =IF(OR(C9<18,C9>70),"Check Age","Ok") -> Ok
A10: CUST1008 | B10: Melissa Howard | C10: 53 | D10: Female | E10: Maynardton | F10: New Hampshire | G10: USA | H10: Gold | I10: =PROPER(TRIM(B10)) -> Melissa Howard | J10: =PROPER(TRIM(E10)) -> Maynardton | K10: =IF(OR(G10="USA",G10="usa"),"USA",K13 IF(G10="United States of America","USA","USA")) -> USA | L10: =IF(LEFT(A10,1)="C","CUST"&RIGHT(A10,4),A10) -> CUST1008 | M10: =IF(H10="","Standard",H10) -> Gold | N10: =IF(OR(C10<18,C10>70),"Check Age","Ok") -> Ok
A11: CUST1009 | B11: Ms. Maria Leach | C11: 64 | D11: Male | E11: Melissashire | F11: Pennsylvania | G11: USA | H11: Platinum | I11: =PROPER(TRIM(B11)) -> Ms. Maria Leach | J11: =PROPER(TRIM(E11)) -> Melissashire | K11: =IF(OR(G11="USA",G11="usa"),"USA",K14 IF(G11="United States of America","USA","USA")) -> USA | L11: =IF(LEFT(A11,1)="C","CUST"&RIGHT(A11,4),A11) -> CUST1009 | M11: =IF(H11="","Standard",H11) -> Platinum | N11: =IF(OR(C11<18,C11>70),"Check Age","Ok") -> Ok
A12: CUST1010 | B12: Dominic Page | C12: 53 | D12: Male | E12: Port Michaelburgh | F12: Pennsylvania | G12: USA | H12: Bronze | I12: =PROPER(TRIM(B12)) -> Dominic Page | J12: =PROPER(TRIM(E12)) -> Port Michaelburgh | K12: =IF(OR(G12="USA",G12="usa"),"USA",K15 IF(G12="United States of America","USA","USA")) -> USA | L12: =IF(LEFT(A12,1)="C","CUST"&RIGHT(A12,4),A12) -> CUST1010 | M12: =IF(H12="","Standard",H12) -> Bronze | N12: =IF(OR(C12<18,C12>70),"Check Age","Ok") -> Ok
A13: CUST1011 | B13: Brian Lopez | C13: 28 | D13: Female | E13: East Krista | F13: New York | G13: USA | H13: Gold | I13: =PROPER(TRIM(B13)) -> Brian Lopez | J13: =PROPER(TRIM(E13)) -> East Krista | K13: =IF(OR(G13="USA",G13="usa"),"USA",K16 IF(G13="United States of America","USA","USA")) -> USA | L13: =IF(LEFT(A13,1)="C","CUST"&RIGHT(A13,4),A13) -> CUST1011 | M13: =IF(H13="","Standard",H13) -> Gold | N13: =IF(OR(C13<18,C13>70),"Check Age","Ok") -> Ok
A14: CUST1012 | B14: Kenneth Lambert | C14: 55 | D14: Female | E14: North Kathryn | F14: Kansas | G14: USA | H14: Platinum | I14: =PROPER(TRIM(B14)) -> Kenneth Lambert | J14: =PROPER(TRIM(E14)) -> North Kathryn | K14: =IF(OR(G14="USA",G14="usa"),"USA",K17 IF(G14="United States of America","USA","USA")) -> USA | L14: =IF(LEFT(A14,1)="C","CUST"&RIGHT(A14,4),A14) -> CUST1012 | M14: =IF(H14="","Standard",H14) -> Platinum | N14: =IF(OR(C14<18,C14>70),"Check Age","Ok") -> Ok
A15: CUST1013 | B15: Nathan Hernandez | C15: 32 | D15: Female | E15: New Becky | F15: Montana | G15: USA | H15: Silver | I15: =PROPER(TRIM(B15)) -> Nathan Hernandez | J15: =PROPER(TRIM(E15)) -> New Becky | K15: =IF(OR(G15="USA",G15="usa"),"USA",K18 IF(G15="United States of America","USA","USA")) -> USA | L15: =IF(LEFT(A15,1)="C","CUST"&RIGHT(A15,4),A15) -> CUST1013 | M15: =IF(H15="","Standard",H15) -> Silver | N15: =IF(OR(C15<18,C15>70),"Check Age","Ok") -> Ok
A16: CUST1014 | B16: Ashley Cohen | C16: 53 | D16: Female | E16: Lake Kristamouth | F16: Nebraska | G16: USA | H16: Silver | I16: =PROPER(TRIM(B16)) -> Ashley Cohen | J16: =PROPER(TRIM(E16)) -> Lake Kristamouth | K16: =IF(OR(G16="USA",G16="usa"),"USA",K19 IF(G16="United States of America","USA","USA")) -> USA | L16: =IF(LEFT(A16,1)="C","CUST"&RIGHT(A16,4),A16) -> CUST1014 | M16: =IF(H16="","Standard",H16) -> Silver | N16: =IF(OR(C16<18,C16>70),"Check Age","Ok") -> Ok
A17: CUST1015 | B17: Laura Alvarez | C17: 49 | D17: Female | E17: Lawsonhaven | F17: Washington | G17: USA | H17: Platinum | I17: =PROPER(TRIM(B17)) -> Laura Alvarez | J17: =PROPER(TRIM(E17)) -> Lawsonhaven | K17: =IF(OR(G17="USA",G17="usa"),"USA",K20 IF(G17="United States of America","USA","USA")) -> USA | L17: =IF(LEFT(A17,1)="C","CUST"&RIGHT(A17,4),A17) -> CUST1015 | M17: =IF(H17="","Standard",H17) -> Platinum | N17: =IF(OR(C17<18,C17>70),"Check Age","Ok") -> Ok
A18: CUST1016 | B18: John Scott | C18: 24 | D18: Female | E18: South Christopher | F18: Pennsylvania | G18: USA | H18: Bronze | I18: =PROPER(TRIM(B18)) -> John Scott | J18: =PROPER(TRIM(E18)) -> South Christopher | K18: =IF(OR(G18="USA",G18="usa"),"USA",K21 IF(G18="United States of America","USA","USA")) -> USA | L18: =IF(LEFT(A18,1)="C","CUST"&RIGHT(A18,4),A18) -> CUST1016 | M18: =IF(H18="","Standard",H18) -> Bronze | N18: =IF(OR(C18<18,C18>70),"Check Age","Ok") -> Ok
A19: CUST1017 | B19: Adam Cruz | C19: 60 | D19: Female | E19: Brandonville | F19: Georgia | G19: USA | H19: Platinum | I19: =PROPER(TRIM(B19)) -> Adam Cruz | J19: =PROPER(TRIM(E19)) -> Brandonville | K19: =IF(OR(G19="USA",G19="usa"),"USA",K22 IF(G19="United States of America","USA","USA")) -> USA | L19: =IF(LEFT(A19,1)="C","CUST"&RIGHT(A19,4),A19) -> CUST1017 | M19: =IF(H19="","Standard",H19) -> Platinum | N19: =IF(OR(C19<18,C19>70),"Check Age","Ok") -> Ok
A20: CUST1018 | B20: Rhonda Moss | C20: 43 | D20: Male | E20: South William | F20: Kansas | G20: USA | I20: =PROPER(TRIM(B20)) -> Rhonda Moss | J20: =PROPER(TRIM(E20)) -> South William | K20: =IF(OR(G20="USA",G20="usa"),"USA",K23 IF(G20="United States of America","USA","USA")) -> USA | L20: =IF(LEFT(A20,1)="C","CUST"&RIGHT(A20,4),A20) -> CUST1018 | M20: =IF(H20="","Standard",H20) -> Standard | N20: =IF(OR(C20<18,C20>70),"Check Age","Ok") -> Ok
A21: CUST1019 | B21: Michael Torres | C21: 46 | D21: Female | E21: Gonzalezfort | F21: New Jersey | G21: USA | H21: Platinum | I21: =PROPER(TRIM(B21)) -> Michael Torres | J21: =PROPER(TRIM(E21)) -> Gonzalezfort | K21: =IF(OR(G21="USA",G21="usa"),"USA",K24 IF(G21="United States of America","USA","USA")) -> USA | L21: =IF(LEFT(A21,1)="C","CUST"&RIGHT(A21,4),A21) -> CUST1019 | M21: =IF(H21="","Standard",H21) -> Platinum | N21: =IF(OR(C21<18,C21>70),"Check Age","Ok") -> Ok
A22: CUST1020 | B22: Bridget Allen | C22: 59 | D22: Male | E22: Lake Shaneburgh | F22: Delaware | G22: USA | H22: Silver | I22: =PROPER(TRIM(B22)) -> Bridget Allen | J22: =PROPER(TRIM(E22)) -> Lake Shaneburgh | K22: =IF(OR(G22="USA",G22="usa"),"USA",K25 IF(G22="United States of America","USA","USA")) -> USA | L22: =IF(LEFT(A22,1)="C","CUST"&RIGHT(A22,4),A22) -> CUST1020 | M22: =IF(H22="","Standard",H22) -> Silver | N22: =IF(OR(C22<18,C22>70),"Check Age","Ok") -> Ok
A23: CUST1021 | B23: Jeff Martinez | C23: 36 | D23: Female | E23: Smithburgh | F23: Oklahoma | G23: USA | H23: Gold | I23: =PROPER(TRIM(B23)) -> Jeff Martinez | J23: =PROPER(TRIM(E23)) -> Smithburgh | K23: =IF(OR(G23="USA",G23="usa"),"USA",K26 IF(G23="United States of America","USA","USA")) -> USA | L23: =IF(LEFT(A23,1)="C","CUST"&RIGHT(A23,4),A23) -> CUST1021 | M23: =IF(H23="","Standard",H23) -> Gold | N23: =IF(OR(C23<18,C23>70),"Check Age","Ok") -> Ok
A24: CUST1022 | B24: paul fox | C24: 33 | D24: Female | E24: Michaelton | F24: Hawaii | G24: USA | H24: Silver | I24: =PROPER(TRIM(B24)) -> Paul Fox | J24: =PROPER(TRIM(E24)) -> Michaelton | K24: =IF(OR(G24="USA",G24="usa"),"USA",K27 IF(G24="United States of America","USA","USA")) -> USA | L24: =IF(LEFT(A24,1)="C","CUST"&RIGHT(A24,4),A24) -> CUST1022 | M24: =IF(H24="","Standard",H24) -> Silver | N24: =IF(OR(C24<18,C24>70),"Check Age","Ok") -> Ok
A25: CUST1023 | B25: Jonathan Steele | C25: 52 | D25: Female | E25: Molinabury | F25: Oregon | G25: USA | H25: Silver | I25: =PROPER(TRIM(B25)) -> Jonathan Steele | J25: =PROPER(TRIM(E25)) -> Molinabury | K25: =IF(OR(G25="USA",G25="usa"),"USA",K28 IF(G25="United States of America","USA","USA")) -> USA | L25: =IF(LEFT(A25,1)="C","CUST"&RIGHT(A25,4),A25) -> CUST1023 | M25: =IF(H25="","Standard",H25) -> Silver | N25: =IF(OR(C25<18,C25>70),"Check Age","Ok") -> Ok
A26: CUST1024 | B26: Heather Collins | C26: 40 | D26: Male | E26: Rogerschester | F26: Idaho | G26: USA | H26: Platinum | I26: =PROPER(TRIM(B26)) -> Heather Collins | J26: =PROPER(TRIM(E26)) -> Rogerschester | K26: =IF(OR(G26="USA",G26="usa"),"USA",K29 IF(G26="United States of America","USA","USA")) -> USA | L26: =IF(LEFT(A26,1)="C","CUST"&RIGHT(A26,4),A26) -> CUST1024 | M26: =IF(H26="","Standard",H26) -> Platinum | N26: =IF(OR(C26<18,C26>70),"Check Age","Ok") -> Ok
A27: CUST1025 | B27: Diana Taylor | C27: 59 | D27: Female | E27: Vasqueztown | F27: California | G27: USA | H27: Bronze | I27: =PROPER(TRIM(B27)) -> Diana Taylor | J27: =PROPER(TRIM(E27)) -> Vasqueztown | K27: =IF(OR(G27="USA",G27="usa"),"USA",K30 IF(G27="United States of America","USA","USA")) -> USA | L27: =IF(LEFT(A27,1)="C","CUST"&RIGHT(A27,4),A27) -> CUST1025 | M27: =IF(H27="","Standard",H27) -> Bronze | N27: =IF(OR(C27<18,C27>70),"Check Age","Ok") -> Ok
A28: CUST1026 | B28: Amber Carlson | C28: 18 | D28: Female | E28: East Michellemouth | F28: Missouri | G28: USA | H28: Gold | I28: =PROPER(TRIM(B28)) -> Amber Carlson | J28: =PROPER(TRIM(E28)) -> East Michellemouth | K28: =IF(OR(G28="USA",G28="usa"),"USA",K31 IF(G28="United States of America","USA","USA")) -> USA | L28: =IF(LEFT(A28,1)="C","CUST"&RIGHT(A28,4),A28) -> CUST1026 | M28: =IF(H28="","Standard",H28) -> Gold | N28: =IF(OR(C28<18,C28>70),"Check Age","Ok") -> Ok
A29: CUST1027 | B29: Leslie Johnson | C29: 31 | D29: Male | E29: Mollyshire | F29: Utah | G29: USA | I29: =PROPER(TRIM(B29)) -> Leslie Johnson | J29: =PROPER(TRIM(E29)) -> Mollyshire | K29: =IF(OR(G29="USA",G29="usa"),"USA",K32 IF(G29="United States of America","USA","USA")) -> USA | L29: =IF(LEFT(A29,1)="C","CUST"&RIGHT(A29,4),A29) -> CUST1027 | M29: =IF(H29="","Standard",H29) -> Standard | N29: =IF(OR(C29<18,C29>70),"Check Age","Ok") -> Ok
A30: CUST1028 | B30: Joshua Ryan | C30: 27 | D30: Female | E30: New David | F30: New Jersey | G30: USA | H30: Platinum | I30: =PROPER(TRIM(B30)) -> Joshua Ryan | J30: =PROPER(TRIM(E30)) -> New David | K30: =IF(OR(G30="USA",G30="usa"),"USA",K33 IF(G30="United States of America","USA","USA")) -> USA | L30: =IF(LEFT(A30,1)="C","CUST"&RIGHT(A30,4),A30) -> CUST1028 | M30: =IF(H30="","Standard",H30) -> Platinum | N30: =IF(OR(C30<18,C30>70),"Check Age","Ok") -> Ok
A31: CUST1029 | B31: David Arnold | C31: 54 | D31: Female | E31: East Jennifer | F31: California | G31: USA | H31: Silver | I31: =PROPER(TRIM(B31)) -> David Arnold | J31: =PROPER(TRIM(E31)) -> East Jennifer | K31: =IF(OR(G31="USA",G31="usa"),"USA",K34 IF(G31="United States of America","USA","USA")) -> USA | L31: =IF(LEFT(A31,1)="C","CUST"&RIGHT(A31,4),A31) -> CUST1029 | M31: =IF(H31="","Standard",H31) -> Silver | N31: =IF(OR(C31<18,C31>70),"Check Age","Ok") -> Ok
A32: CUST1030 | B32: Jessica Acevedo | C32: 64 | D32: Female | E32: Amybury | F32: Pennsylvania | G32: USA | H32: Bronze | I32: =PROPER(TRIM(B32)) -> Jessica Acevedo | J32: =PROPER(TRIM(E32)) -> Amybury | K32: =IF(OR(G32="USA",G32="usa"),"USA",K35 IF(G32="United States of America","USA","USA")) -> USA | L32: =IF(LEFT(A32,1)="C","CUST"&RIGHT(A32,4),A32) -> CUST1030 | M32: =IF(H32="","Standard",H32) -> Bronze | N32: =IF(OR(C32<18,C32>70),"Check Age","Ok") -> Ok
A33: CUST1031 | B33: Sarah Vance | C33: 41 | D33: Male | E33: Johnsonville | F33: Oregon | G33: USA | H33: Silver | I33: =PROPER(TRIM(B33)) -> Sarah Vance | J33: =PROPER(TRIM(E33)) -> Johnsonville | K33: =IF(OR(G33="USA",G33="usa"),"USA",K36 IF(G33="United States of America","USA","USA")) -> USA | L33: =IF(LEFT(A33,1)="C","CUST"&RIGHT(A33,4),A33) -> CUST1031 | M33: =IF(H33="","Standard",H33) -> Silver | N33: =IF(OR(C33<18,C33>70),"Check Age","Ok") -> Ok
A34: CUST1032 | B34: Mike Jennings | C34: 48 | D34: Female | E34: Fostermouth | F34: Arizona | G34: USA | H34: Gold | I34: =PROPER(TRIM(B34)) -> Mike Jennings | J34: =PROPER(TRIM(E34)) -> Fostermouth | K34: =IF(OR(G34="USA",G34="usa"),"USA",K37 IF(G34="United States of America","USA","USA")) -> USA | L34: =IF(LEFT(A34,1)="C","CUST"&RIGHT(A34,4),A34) -> CUST1032 | M34: =IF(H34="","Standard",H34) -> Gold | N34: =IF(OR(C34<18,C34>70),"Check Age","Ok") -> Ok
A35: CUST1033 | B35: Robert Jones DDS | C35: 25 | D35: Male | E35: Tristanton | F35: Oklahoma | G35: USA | H35: Platinum | I35: =PROPER(TRIM(B35)) -> Robert Jones Dds | J35: =PROPER(TRIM(E35)) -> Tristanton | K35: =IF(OR(G35="USA",G35="usa"),"USA",K38 IF(G35="United States of America","USA","USA")) -> USA | L35: =IF(LEFT(A35,1)="C","CUST"&RIGHT(A35,4),A35) -> CUST1033 | M35: =IF(H35="","Standard",H35) -> Platinum | N35: =IF(OR(C35<18,C35>70),"Check Age","Ok") -> Ok
A36: CUST1034 | B36: Christopher Olson | C36: 27 | D36: Female | E36: West Richard | F36: Maryland | G36: USA | H36: Platinum | I36: =PROPER(TRIM(B36)) -> Christopher Olson | J36: =PROPER(TRIM(E36)) -> West Richard | K36: =IF(OR(G36="USA",G36="usa"),"USA",K39 IF(G36="United States of America","USA","USA")) -> USA | L36: =IF(LEFT(A36,1)="C","CUST"&RIGHT(A36,4),A36) -> CUST1034 | M36: =IF(H36="","Standard",H36) -> Platinum | N36: =IF(OR(C36<18,C36>70),"Check Age","Ok") -> Ok
A37: CUST1035 | B37: Rachel Myers | C37: 52 | D37: Male | E37: Robertberg | F37: North Dakota | G37: USA | H37: Silver | I37: =PROPER(TRIM(B37)) -> Rachel Myers | J37: =PROPER(TRIM(E37)) -> Robertberg | K37: =IF(OR(G37="USA",G37="usa"),"USA",K40 IF(G37="United States of America","USA","USA")) -> USA | L37: =IF(LEFT(A37,1)="C","CUST"&RIGHT(A37,4),A37) -> CUST1035 | M37: =IF(H37="","Standard",H37) -> Silver | N37: =IF(OR(C37<18,C37>70),"Check Age","Ok") -> Ok
A38: CUST1036 | B38: Thomas Phillips | C38: 20 | D38: Female | E38: Luisfurt | F38: Georgia | G38: USA | H38: Gold | I38: =PROPER(TRIM(B38)) -> Thomas Phillips | J38: =PROPER(TRIM(E38)) -> Luisfurt | K38: =IF(OR(G38="USA",G38="usa"),"USA",K41 IF(G38="United States of America","USA","USA")) -> USA | L38: =IF(LEFT(A38,1)="C","CUST"&RIGHT(A38,4),A38) -> CUST1036 | M38: =IF(H38="","Standard",H38) -> Gold | N38: =IF(OR(C38<18,C38>70),"Check Age","Ok") -> Ok
A39: CUST1037 | B39: Christopher Carter | C39: 27 | D39: Female | E39: Brendastad | F39: South Dakota | G39: USA | I39: =PROPER(TRIM(B39)) -> Christopher Carter | J39: =PROPER(TRIM(E39)) -> Brendastad | K39: =IF(OR(G39="USA",G39="usa"),"USA",K42 IF(G39="United States of America","USA","USA")) -> USA | L39: =IF(LEFT(A39,1)="C","CUST"&RIGHT(A39,4),A39) -> CUST1037 | M39: =IF(H39="","Standard",H39) -> Standard | N39: =IF(OR(C39<18,C39>70),"Check Age","Ok") -> Ok
A40: CUST1038 | B40: Deanna Simpson | C40: 35 | D40: Female | E40: Brownport | F40: North Dakota | G40: USA | H40: Bronze | I40: =PROPER(TRIM(B40)) -> Deanna Simpson | J40: =PROPER(TRIM(E40)) -> Brownport | K40: =IF(OR(G40="USA",G40="usa"),"USA",K43 IF(G40="United States of America","USA","USA")) -> USA | L40: =IF(LEFT(A40,1)="C","CUST"&RIGHT(A40,4),A40) -> CUST1038 | M40: =IF(H40="","Standard",H40) -> Bronze | N40: =IF(OR(C40<18,C40>70),"Check Age","Ok") -> Ok
A41: CUST1039 | B41: Tonya Reynolds | C41: 55 | D41: Female | E41: Darleneton | F41: Michigan | G41: USA | H41: Gold | I41: =PROPER(TRIM(B41)) -> Tonya Reynolds | J41: =PROPER(TRIM(E41)) -> Darleneton | K41: =IF(OR(G41="USA",G41="usa"),"USA",K44 IF(G41="United States of America","USA","USA")) -> USA | L41: =IF(LEFT(A41,1)="C","CUST"&RIGHT(A41,4),A41) -> CUST1039 | M41: =IF(H41="","Standard",H41) -> Gold | N41: =IF(OR(C41<18,C41>70),"Check Age","Ok") -> Ok
A42: CUST1040 | B42: Eric Vega | C42: 50 | D42: Male | E42: Williamsonland | F42: Kansas | G42: USA | H42: Gold | I42: =PROPER(TRIM(B42)) -> Eric Vega | J42: =PROPER(TRIM(E42)) -> Williamsonland | K42: =IF(OR(G42="USA",G42="usa"),"USA",K45 IF(G42="United States of America","USA","USA")) -> USA | L42: =IF(LEFT(A42,1)="C","CUST"&RIGHT(A42,4),A42) -> CUST1040 | M42: =IF(H42="","Standard",H42) -> Gold | N42: =IF(OR(C42<18,C42>70),"Check Age","Ok") -> Ok
A43: CUST1041 | B43: James Gibbs | C43: 21 | D43: Male | E43: Mooneyshire | F43: Alaska | G43: USA | H43: Platinum | I43: =PROPER(TRIM(B43)) -> James Gibbs | J43: =PROPER(TRIM(E43)) -> Mooneyshire | K43: =IF(OR(G43="USA",G43="usa"),"USA",K46 IF(G43="United States of America","USA","USA")) -> USA | L43: =IF(LEFT(A43,1)="C","CUST"&RIGHT(A43,4),A43) -> CUST1041 | M43: =IF(H43="","Standard",H43) -> Platinum | N43: =IF(OR(C43<18,C43>70),"Check Age","Ok") -> Ok
A44: CUST1042 | B44: William Martin | C44: 19 | D44: Male | E44: Ryanburgh | F44: Connecticut | G44: USA | H44: Platinum | I44: =PROPER(TRIM(B44)) -> William Martin | J44: =PROPER(TRIM(E44)) -> Ryanburgh | K44: =IF(OR(G44="USA",G44="usa"),"USA",K47 IF(G44="United States of America","USA","USA")) -> USA | L44: =IF(LEFT(A44,1)="C","CUST"&RIGHT(A44,4),A44) -> CUST1042 | M44: =IF(H44="","Standard",H44) -> Platinum | N44: =IF(OR(C44<18,C44>70),"Check Age","Ok") -> Ok
A45: CUST1043 | B45: Joseph Snow | C45: 45 | D45: Male | E45: South Michaelfort | F45: Vermont | G45: USA | H45: Gold | I45: =PROPER(TRIM(B45)) -> Joseph Snow | J45: =PROPER(TRIM(E45)) -> South Michaelfort | K45: =IF(OR(G45="USA",G45="usa"),"USA",K48 IF(G45="United States of America","USA","USA")) -> USA | L45: =IF(LEFT(A45,1)="C","CUST"&RIGHT(A45,4),A45) -> CUST1043 | M45: =IF(H45="","Standard",H45) -> Gold | N45: =IF(OR(C45<18,C45>70),"Check Age","Ok") -> Ok
A46: CUST1044 | B46: Denise Williams | C46: 34 | D46: Male | E46: Christianstad | F46: Hawaii | G46: USA | H46: Bronze | I46: =PROPER(TRIM(B46)) -> Denise Williams | J46: =PROPER(TRIM(E46)) -> Christianstad | K46: =IF(OR(G46="USA",G46="usa"),"USA",K49 IF(G46="United States of America","USA","USA")) -> USA | L46: =IF(LEFT(A46,1)="C","CUST"&RIGHT(A46,4),A46) -> CUST1044 | M46: =IF(H46="","Standard",H46) -> Bronze | N46: =IF(OR(C46<18,C46>70),"Check Age","Ok") -> Ok
A47: CUST1045 | B47: Jordan Jackson DDS | C47: 54 | D47: Male | E47: North Johnview | F47: Arizona | G47: USA | H47: Gold | I47: =PROPER(TRIM(B47)) -> Jordan Jackson Dds | J47: =PROPER(TRIM(E47)) -> North Johnview | K47: =IF(OR(G47="USA",G47="usa"),"USA",K50 IF(G47="United States of America","USA","USA")) -> USA | L47: =IF(LEFT(A47,1)="C","CUST"&RIGHT(A47,4),A47) -> CUST1045 | M47: =IF(H47="","Standard",H47) -> Gold | N47: =IF(OR(C47<18,C47>70),"Check Age","Ok") -> Ok
A48: CUST1046 | B48: Michelle Garcia DDS | C48: 55 | D48: Female | E48: Perezbury | F48: Ohio | G48: USA | H48: Platinum | I48: =PROPER(TRIM(B48)) -> Michelle Garcia Dds | J48: =PROPER(TRIM(E48)) -> Perezbury | K48: =IF(OR(G48="USA",G48="usa"),"USA",K51 IF(G48="United States of America","USA","USA")) -> USA | L48: =IF(LEFT(A48,1)="C","CUST"&RIGHT(A48,4),A48) -> CUST1046 | M48: =IF(H48="","Standard",H48) -> Platinum | N48: =IF(OR(C48<18,C48>70),"Check Age","Ok") -> Ok
A49: CUST1047 | B49: Gina Knight | C49: 54 | D49: Female | E49: Lake Roberthaven | F49: Nevada | G49: USA | H49: Silver | I49: =PROPER(TRIM(B49)) -> Gina Knight | J49: =PROPER(TRIM(E49)) -> Lake Roberthaven | K49: =IF(OR(G49="USA",G49="usa"),"USA",K52 IF(G49="United States of America","USA","USA")) -> USA | L49: =IF(LEFT(A49,1)="C","CUST"&RIGHT(A49,4),A49) -> CUST1047 | M49: =IF(H49="","Standard",H49) -> Silver | N49: =IF(OR(C49<18,C49>70),"Check Age","Ok") -> Ok
A50: CUST1048 | B50: April Mullins | C50: 54 | D50: Male | E50: Dawsonbury | F50: North Carolina | G50: USA | H50: Platinum | I50: =PROPER(TRIM(B50)) -> April Mullins | J50: =PROPER(TRIM(E50)) -> Dawsonbury | K50: =IF(OR(G50="USA",G50="usa"),"USA",K53 IF(G50="United States of America","USA","USA")) -> USA | L50: =IF(LEFT(A50,1)="C","CUST"&RIGHT(A50,4),A50) -> CUST1048 | M50: =IF(H50="","Standard",H50) -> Platinum | N50: =IF(OR(C50<18,C50>70),"Check Age","Ok") -> Ok
A51: CUST1049 | B51: Timothy Weaver | C51: 45 | D51: Female | E51: New Amy | F51: Ohio | G51: USA | H51: Gold | I51: =PROPER(TRIM(B51)) -> Timothy Weaver | J51: =PROPER(TRIM(E51)) -> New Amy | K51: =IF(OR(G51="USA",G51="usa"),"USA",K54 IF(G51="United States of America","USA","USA")) -> USA | L51: =IF(LEFT(A51,1)="C","CUST"&RIGHT(A51,4),A51) -> CUST1049 | M51: =IF(H51="","Standard",H51) -> Gold | N51: =IF(OR(C51<18,C51>70),"Check Age","Ok") -> Ok
... A501: CUST1499 | B501: Philip Pennington | C501: 27 | D501: Female | E501: East Valerieview | F501: Oregon | G501: USA | H501: Platinum | I501: =PROPER(TRIM(B501)) -> Philip Pennington | J501: =PROPER(TRIM(E501)) -> East Valerieview | K501: =IF(OR(G501="USA",G501="usa"),"USA",K504 IF(G501="United States of America","USA","USA")) -> USA | L501: =IF(LEFT(A501,1)="C","CUST"&RIGHT(A501,4),A501) -> CUST1499 | M501: =IF(H501="","Standard",H501) -> Platinum | N501: =IF(OR(C501<18,C501>70),"Check Age","Ok") -> Ok

Sheet Product_Dim
A1: Product_ID | B1: Product_Name | C1: Category | D1: Sub_Category | E1: Brand | F1: Cost | G1: Stock | H1: Clean Product ID | I1: Clean category | J1: Clean Product Names | K1: Clean cost | L1: Clean stock | M1: Overall Pricing
A2: PROD0 | B2: Brother Laser Printer | C2: Electronics | D2: Computer | E2: Hunt Inc | F2: 112.42 | G2: 416 | H2: =IF(LEFT(A2,2)="PROD16","PROD"&TEXT(MID(A2,3,2),"000"),"PROD"&TEXT(MID(A2,5,2),"000")) -> PROD000 | I2: Electronics | J2: =PROPER(TRIM(B2)) -> Brother Laser Printer | K2: =ROUNDUP(IF(ISBLANK(F2),AVERAGEIF(C:C,C2,F:F),F2),2) -> 112.42 | L2: =ROUNDUP(IF(ISBLANK(G2),AVERAGE(C:C,C2,G:G),G2),0) -> 416 | M2: =K2*L2 -> 46766.72
A3: PROD1 | B3: Men's Graphic T-Shirt | C3: Clothing | D3: Tops | E3: Terry-Moore | F3: 342.56 | G3: 181 | H3: =IF(LEFT(A3,2)="PROD16","PROD"&TEXT(MID(A3,3,2),"000"),"PROD"&TEXT(MID(A3,5,2),"000")) -> PROD001 | I3: Clothing | J3: =PROPER(TRIM(B3)) -> Men'S Graphic T-Shirt | K3: =ROUNDUP(IF(ISBLANK(F3),AVERAGEIF(C:C,C3,F:F),F3),2) -> 342.56 | L3: =ROUNDUP(IF(ISBLANK(G3),AVERAGE(C:C,C3,G:G),G3),0) -> 181 | M3: =K3*L3 -> 62003.36
A4: PROD2 | B4: Women's Casual Hoodie | C4: Clothing | D4: Outerwear | E4: Sims Inc | G4: 352 | H4: =IF(LEFT(A4,2)="PROD16","PROD"&TEXT(MID(A4,3,2),"000"),"PROD"&TEXT(MID(A4,5,2),"000")) -> PROD002 | I4: Clothing | J4: =PROPER(TRIM(B4)) -> Women'S Casual Hoodie | K4: =ROUNDUP(IF(ISBLANK(F4),AVERAGEIF(C:C,C4,F:F),F4),2) -> 265.74 | L4: =ROUNDUP(IF(ISBLANK(G4),AVERAGE(C:C,C4,G:G),G4),0) -> 352 | M4: =K4*L4 -> 93540.48
A5: PROD3 | B5: Men's Running Jacket | C5: Clothing | D5: Outerwear | E5: Pineda Ltd | F5: 364.67 | G5: 452 | H5: =IF(LEFT(A5,2)="PROD16","PROD"&TEXT(MID(A5,3,2),"000"),"PROD"&TEXT(MID(A5,5,2),"000")) -> PROD003 | I5: Clothing | J5: =PROPER(TRIM(B5)) -> Men'S Running Jacket | K5: =ROUNDUP(IF(ISBLANK(F5),AVERAGEIF(C:C,C5,F:F),F5),2) -> 364.67 | L5: =ROUNDUP(IF(ISBLANK(G5),AVERAGE(C:C,C5,G:G),G5),0) -> 452 | M5: =K5*L5 -> 164830.84
A6: PROD4 | B6: Women's Yoga Pants | C6: Clothing | D6: Bottoms | E6: Gonzales-Davis | F6: 306.46 | G6: 487 | H6: =IF(LEFT(A6,2)="PROD16","PROD"&TEXT(MID(A6,3,2),"000"),"PROD"&TEXT(MID(A6,5,2),"000")) -> PROD004 | I6: Clothing | J6: =PROPER(TRIM(B6)) -> Women'S Yoga Pants | K6: =ROUNDUP(IF(ISBLANK(F6),AVERAGEIF(C:C,C6,F:F),F6),2) -> 306.46 | L6: =ROUNDUP(IF(ISBLANK(G6),AVERAGE(C:C,C6,G:G),G6),0) -> 487 | M6: =K6*L6 -> 149246.02
A7: PROD5 | B7: Men's Leather Belt | C7: Clothing | D7: Accessories | E7: Baldwin, Garza and Gonzalez | F7: 261 | G7: 59 | H7: =IF(LEFT(A7,2)="PROD16","PROD"&TEXT(MID(A7,3,2),"000"),"PROD"&TEXT(MID(A7,5,2),"000")) -> PROD005 | I7: Clothing | J7: =PROPER(TRIM(B7)) -> Men'S Leather Belt | K7: =ROUNDUP(IF(ISBLANK(F7),AVERAGEIF(C:C,C7,F:F),F7),2) -> 261 | L7: =ROUNDUP(IF(ISBLANK(G7),AVERAGE(C:C,C7,G:G),G7),0) -> 59 | M7: =K7*L7 -> 15399
A8: PROD6 | B8: Herbal Face Moisturizer | C8: Beauty | D8: Skincare | E8: Davidson PLC | F8: 312.8 | G8: 350 | H8: =IF(LEFT(A8,2)="PROD16","PROD"&TEXT(MID(A8,3,2),"000"),"PROD"&TEXT(MID(A8,5,2),"000")) -> PROD006 | I8: Beauty | J8: =PROPER(TRIM(B8)) -> Herbal Face Moisturizer | K8: =ROUNDUP(IF(ISBLANK(F8),AVERAGEIF(C:C,C8,F:F),F8),2) -> 312.8 | L8: =ROUNDUP(IF(ISBLANK(G8),AVERAGE(C:C,C8,G:G),G8),0) -> 350 | M8: =K8*L8 -> 109480
A9: PROD7 | B9: LED Table Lamp | C9: Home | D9: Lighting | E9: Harrell LLC | F9: 218.86 | G9: 170 | H9: =IF(LEFT(A9,2)="PROD16","PROD"&TEXT(MID(A9,3,2),"000"),"PROD"&TEXT(MID(A9,5,2),"000")) -> PROD007 | I9: Home | J9: =PROPER(TRIM(B9)) -> Led Table Lamp | K9: =ROUNDUP(IF(ISBLANK(F9),AVERAGEIF(C:C,C9,F:F),F9),2) -> 218.86 | L9: =ROUNDUP(IF(ISBLANK(G9),AVERAGE(C:C,C9,G:G),G9),0) -> 170 | M9: =K9*L9 -> 37206.2
A10: PROD8 | B10: Wireless Bluetooth Earbuds | C10: Electronics | D10: Audio | E10: Perez-Johnston | F10: 439.07 | G10: 142 | H10: =IF(LEFT(A10,2)="PROD16","PROD"&TEXT(MID(A10,3,2),"000"),"PROD"&TEXT(MID(A10,5,2),"000")) -> PROD008 | I10: Electronics | J10: =PROPER(TRIM(B10)) -> Wireless Bluetooth Earbuds | K10: =ROUNDUP(IF(ISBLANK(F10),AVERAGEIF(C:C,C10,F:F),F10),2) -> 439.07 | L10: =ROUNDUP(IF(ISBLANK(G10),AVERAGE(C:C,C10,G:G),G10),0) -> 142 | M10: =K10*L10 -> 62347.94
A11: PROD9 | B11: Adjustable Dumbbell Set | C11: Sports | D11: Fitness | E11: Hill PLC | F11: 495.72 | G11: 323 | H11: =IF(LEFT(A11,2)="PROD16","PROD"&TEXT(MID(A11,3,2),"000"),"PROD"&TEXT(MID(A11,5,2),"000")) -> PROD009 | I11: Sports | J11: =PROPER(TRIM(B11)) -> Adjustable Dumbbell Set | K11: =ROUNDUP(IF(ISBLANK(F11),AVERAGEIF(C:C,C11,F:F),F11),2) -> 495.72 | L11: =ROUNDUP(IF(ISBLANK(G11),AVERAGE(C:C,C11,G:G),G11),0) -> 323 | M11: =K11*L11 -> 160117.56
A12: PROD10 | B12: Ceramic Kitchen Bowl Set | C12: Home | D12: Kitchen | E12: Hamilton Group | F12: 298.86 | G12: 308 | H12: =IF(LEFT(A12,2)="PROD16","PROD"&TEXT(MID(A12,3,2),"000"),"PROD"&TEXT(MID(A12,5,2),"000")) -> PROD010 | I12: Home | J12: =PROPER(TRIM(B12)) -> Ceramic Kitchen Bowl Set | K12: =ROUNDUP(IF(ISBLANK(F12),AVERAGEIF(C:C,C12,F:F),F12),2) -> 298.86 | L12: =ROUNDUP(IF(ISBLANK(G12),AVERAGE(C:C,C12,G:G),G12),0) -> 308 | M12: =K12*L12 -> 92048.88
A13: PROD11 | B13: HD Smart TV Stick | C13: Electronics | D13: Accessories | E13: Gibson, Hobbs and Weaver | F13: 449.4 | H13: =IF(LEFT(A13,2)="PROD16","PROD"&TEXT(MID(A13,3,2),"000"),"PROD"&TEXT(MID(A13,5,2),"000")) -> PROD011 | I13: Electronics | J13: =PROPER(TRIM(B13)) -> Hd Smart Tv Stick | K13: =ROUNDUP(IF(ISBLANK(F13),AVERAGEIF(C:C,C13,F:F),F13),2) -> 449.4 | L13: =ROUNDUP(IF(ISBLANK(G13),AVERAGE(C:C,C13,G:G),G13),0) -> 274 | M13: =K13*L13 -> 123135.6
A14: PROD12 | B14: Hair Strengthening Shampoo | C14: Beauty | D14: Haircare | E14: Rice LLC | F14: 115.82 | G14: 460 | H14: =IF(LEFT(A14,2)="PROD16","PROD"&TEXT(MID(A14,3,2),"000"),"PROD"&TEXT(MID(A14,5,2),"000")) -> PROD012 | I14: Beauty | J14: =PROPER(TRIM(B14)) -> Hair Strengthening Shampoo | K14: =ROUNDUP(IF(ISBLANK(F14),AVERAGEIF(C:C,C14,F:F),F14),2) -> 115.82 | L14: =ROUNDUP(IF(ISBLANK(G14),AVERAGE(C:C,C14,G:G),G14),0) -> 460 | M14: =K14*L14 -> 53277.2
A15: PROD13 | B15: USB-C Fast Charger | C15: Electronics | D15: Accessories | E15: Dawson-Perkins | F15: 242.23 | G15: 453 | H15: =IF(LEFT(A15,2)="PROD16","PROD"&TEXT(MID(A15,3,2),"000"),"PROD"&TEXT(MID(A15,5,2),"000")) -> PROD013 | I15: Electronics | J15: =PROPER(TRIM(B15)) -> Usb-C Fast Charger | K15: =ROUNDUP(IF(ISBLANK(F15),AVERAGEIF(C:C,C15,F:F),F15),2) -> 242.23 | L15: =ROUNDUP(IF(ISBLANK(G15),AVERAGE(C:C,C15,G:G),G15),0) -> 453 | M15: =K15*L15 -> 109730.19
A16: PROD14 | B16: Decorative Wall Mirror | C16: Home | D16: Decor | E16: Luna, Anderson and Bowman | F16: 48.01 | G16: 439 | H16: =IF(LEFT(A16,2)="PROD16","PROD"&TEXT(MID(A16,3,2),"000"),"PROD"&TEXT(MID(A16,5,2),"000")) -> PROD014 | I16: Home | J16: =PROPER(TRIM(B16)) -> Decorative Wall Mirror | K16: =ROUNDUP(IF(ISBLANK(F16),AVERAGEIF(C:C,C16,F:F),F16),2) -> 48.01 | L16: =ROUNDUP(IF(ISBLANK(G16),AVERAGE(C:C,C16,G:G),G16),0) -> 439 | M16: =K16*L16 -> 21076.39
A17: PROD15 | B17: 4K Home Projector | C17: Electronics | D17: Appliances | E17: Thomas LLC | F17: 465.34 | G17: 301 | H17: =IF(LEFT(A17,2)="PROD16","PROD"&TEXT(MID(A17,3,2),"000"),"PROD"&TEXT(MID(A17,5,2),"000")) -> PROD015 | I17: Electronics | J17: =PROPER(TRIM(B17)) -> 4K Home Projector | K17: =ROUNDUP(IF(ISBLANK(F17),AVERAGEIF(C:C,C17,F:F),F17),2) -> 465.34 | L17: =ROUNDUP(IF(ISBLANK(G17),AVERAGE(C:C,C17,G:G),G17),0) -> 301 | M17: =K17*L17 -> 140067.34
A18: PROD16 | B18: Beard Grooming Kit | C18: Beauty | D18: Grooming | E18: Erickson-Green | F18: 337.42 | G18: 256 | H18: =IF(LEFT(A18,2)="PROD16","PROD"&TEXT(MID(A18,3,2),"000"),"PROD"&TEXT(MID(A18,5,2),"000")) -> PROD016 | I18: Beauty | J18: =PROPER(TRIM(B18)) -> Beard Grooming Kit | K18: =ROUNDUP(IF(ISBLANK(F18),AVERAGEIF(C:C,C18,F:F),F18),2) -> 337.42 | L18: =ROUNDUP(IF(ISBLANK(G18),AVERAGE(C:C,C18,G:G),G18),0) -> 256 | M18: =K18*L18 -> 86379.52
A19: PROD17 | B19: Soccer Training Cone Set | C19: Sports | D19: Accessories | E19: Ford, Murphy and Wilson | F19: 144.53 | G19: 367 | H19: =IF(LEFT(A19,2)="PROD16","PROD"&TEXT(MID(A19,3,2),"000"),"PROD"&TEXT(MID(A19,5,2),"000")) -> PROD017 | I19: Sports | J19: =PROPER(TRIM(B19)) -> Soccer Training Cone Set | K19: =ROUNDUP(IF(ISBLANK(F19),AVERAGEIF(C:C,C19,F:F),F19),2) -> 144.53 | L19: =ROUNDUP(IF(ISBLANK(G19),AVERAGE(C:C,C19,G:G),G19),0) -> 367 | M19: =K19*L19 -> 53042.51
A20: PROD18 | B20: Women's Denim Jeans | C20: Clothing | D20: Bottoms | E20: Guerra-Hendrix | G20: 343 | H20: =IF(LEFT(A20,2)="PROD16","PROD"&TEXT(MID(A20,3,2),"000"),"PROD"&TEXT(MID(A20,5,2),"000")) -> PROD018 | I20: Clothing | J20: =PROPER(TRIM(B20)) -> Women'S Denim Jeans | K20: =ROUNDUP(IF(ISBLANK(F20),AVERAGEIF(C:C,C20,F:F),F20),2) -> 265.74 | L20: =ROUNDUP(IF(ISBLANK(G20),AVERAGE(C:C,C20,G:G),G20),0) -> 343 | M20: =K20*L20 -> 91148.82
A21: PROD19 | B21: Knee Support Brace | C21: Sports | D21: Equipment | E21: May-Reese | F21: 21.34 | G21: 65 | H21: =IF(LEFT(A21,2)="PROD16","PROD"&TEXT(MID(A21,3,2),"000"),"PROD"&TEXT(MID(A21,5,2),"000")) -> PROD019 | I21: Sports | J21: =PROPER(TRIM(B21)) -> Knee Support Brace | K21: =ROUNDUP(IF(ISBLANK(F21),AVERAGEIF(C:C,C21,F:F),F21),2) -> 21.34 | L21: =ROUNDUP(IF(ISBLANK(G21),AVERAGE(C:C,C21,G:G),G21),0) -> 65 | M21: =K21*L21 -> 1387.1
A22: PROD20 | B22: Outdoor Sports Water Bottle | C22: Sports | D22: Accessories | E22: Soto-Ellis | F22: 131.51 | H22: =IF(LEFT(A22,2)="PROD16","PROD"&TEXT(MID(A22,3,2),"000"),"PROD"&TEXT(MID(A22,5,2),"000")) -> PROD020 | I22: Sports | J22: =PROPER(TRIM(B22)) -> Outdoor Sports Water Bottle | K22: =ROUNDUP(IF(ISBLANK(F22),AVERAGEIF(C:C,C22,F:F),F22),2) -> 131.51 | L22: =ROUNDUP(IF(ISBLANK(G22),AVERAGE(C:C,C22,G:G),G22),0) -> 274 | M22: =K22*L22 -> 36033.74
A23: PROD21 | B23: Multi-Purpose Storage Box | C23: Home | D23: Storage | E23: Gardner-Montes | F23: 123.46 | G23: 76 | H23: =IF(LEFT(A23,2)="PROD16","PROD"&TEXT(MID(A23,3,2),"000"),"PROD"&TEXT(MID(A23,5,2),"000")) -> PROD021 | I23: Home | J23: =PROPER(TRIM(B23)) -> Multi-Purpose Storage Box | K23: =ROUNDUP(IF(ISBLANK(F23),AVERAGEIF(C:C,C23,F:F),F23),2) -> 123.46 | L23: =ROUNDUP(IF(ISBLANK(G23),AVERAGE(C:C,C23,G:G),G23),0) -> 76 | M23: =K23*L23 -> 9382.96
A24: PROD22 | B24: Carbon Fiber Tennis Racket | C24: Sports | D24: Equipment | E24: Flores, Pineda and Rodriguez | F24: 484.62 | G24: 432 | H24: =IF(LEFT(A24,2)="PROD16","PROD"&TEXT(MID(A24,3,2),"000"),"PROD"&TEXT(MID(A24,5,2),"000")) -> PROD022 | I24: Sports | J24: =PROPER(TRIM(B24)) -> Carbon Fiber Tennis Racket | K24: =ROUNDUP(IF(ISBLANK(F24),AVERAGEIF(C:C,C24,F:F),F24),2) -> 484.62 | L24: =ROUNDUP(IF(ISBLANK(G24),AVERAGE(C:C,C24,G:G),G24),0) -> 432 | M24: =K24*L24 -> 209355.84
A25: PROD23 | B25: Men's Formal Shirt | C25: Clothing | D25: Tops | E25: Moon, Mora and Santos | G25: 360 | H25: =IF(LEFT(A25,2)="PROD16","PROD"&TEXT(MID(A25,3,2),"000"),"PROD"&TEXT(MID(A25,5,2),"000")) -> PROD023 | I25: Clothing | J25: =PROPER(TRIM(B25)) -> Men'S Formal Shirt | K25: =ROUNDUP(IF(ISBLANK(F25),AVERAGEIF(C:C,C25,F:F),F25),2) -> 265.74 | L25: =ROUNDUP(IF(ISBLANK(G25),AVERAGE(C:C,C25,G:G),G25),0) -> 360 | M25: =K25*L25 -> 95666.4
A26: PROD24 | B26: Foldable Camping Chair | C26: Sports | D26: Outdoor | E26: Cook Ltd | F26: 166.06 | G26: 340 | H26: =IF(LEFT(A26,2)="PROD16","PROD"&TEXT(MID(A26,3,2),"000"),"PROD"&TEXT(MID(A26,5,2),"000")) -> PROD024 | I26: Sports | J26: =PROPER(TRIM(B26)) -> Foldable Camping Chair | K26: =ROUNDUP(IF(ISBLANK(F26),AVERAGEIF(C:C,C26,F:F),F26),2) -> 166.06 | L26: =ROUNDUP(IF(ISBLANK(G26),AVERAGE(C:C,C26,G:G),G26),0) -> 340 | M26: =K26*L26 -> 56460.4
A27: PROD25 | B27: Women's Scarf Set | C27: Clothing | D27: Accessories | E27: Brown and Sons | F27: 174.02 | G27: 268 | H27: =IF(LEFT(A27,2)="PROD16","PROD"&TEXT(MID(A27,3,2),"000"),"PROD"&TEXT(MID(A27,5,2),"000")) -> PROD025 | I27: Clothing | J27: =PROPER(TRIM(B27)) -> Women'S Scarf Set | K27: =ROUNDUP(IF(ISBLANK(F27),AVERAGEIF(C:C,C27,F:F),F27),2) -> 174.02 | L27: =ROUNDUP(IF(ISBLANK(G27),AVERAGE(C:C,C27,G:G),G27),0) -> 268 | M27: =K27*L27 -> 46637.36
A28: PROD26 | B28: Wireless Bluetooth Speaker | C28: Electronics | D28: Audio | E28: Reed-Schmidt | F28: 322.41 | G28: 213 | H28: =IF(LEFT(A28,2)="PROD16","PROD"&TEXT(MID(A28,3,2),"000"),"PROD"&TEXT(MID(A28,5,2),"000")) -> PROD026 | I28: Electronics | J28: =PROPER(TRIM(B28)) -> Wireless Bluetooth Speaker | K28: =ROUNDUP(IF(ISBLANK(F28),AVERAGEIF(C:C,C28,F:F),F28),2) -> 322.41 | L28: =ROUNDUP(IF(ISBLANK(G28),AVERAGE(C:C,C28,G:G),G28),0) -> 213 | M28: =K28*L28 -> 68673.33
A29: PROD27 | B29: Decorative Floor Vase | C29: Home | D29: Decor | E29: Khan, Jones and Paul | G29: 378 | H29: =IF(LEFT(A29,2)="PROD16","PROD"&TEXT(MID(A29,3,2),"000"),"PROD"&TEXT(MID(A29,5,2),"000")) -> PROD027 | I29: Home | J29: =PROPER(TRIM(B29)) -> Decorative Floor Vase | K29: =ROUNDUP(IF(ISBLANK(F29),AVERAGEIF(C:C,C29,F:F),F29),2) -> 234.81 | L29: =ROUNDUP(IF(ISBLANK(G29),AVERAGE(C:C,C29,G:G),G29),0) -> 378 | M29: =K29*L29 -> 88758.18
A30: PROD28 | B30: Sports Stopwatch Timer | C30: Sports | D30: Accessories | E30: Burns-Hansen | F30: 38.76 | G30: 137 | H30: =IF(LEFT(A30,2)="PROD16","PROD"&TEXT(MID(A30,3,2),"000"),"PROD"&TEXT(MID(A30,5,2),"000")) -> PROD028 | I30: Sports | J30: =PROPER(TRIM(B30)) -> Sports Stopwatch Timer | K30: =ROUNDUP(IF(ISBLANK(F30),AVERAGEIF(C:C,C30,F:F),F30),2) -> 38.76 | L30: =ROUNDUP(IF(ISBLANK(G30),AVERAGE(C:C,C30,G:G),G30),0) -> 137 | M30: =K30*L30 -> 5310.12
A31: PROD29 | B31: Fabric Sofa Throw Blanket | C31: Home | D31: Decor | E31: Hoffman Group | F31: 218.48 | G31: 276 | H31: =IF(LEFT(A31,2)="PROD16","PROD"&TEXT(MID(A31,3,2),"000"),"PROD"&TEXT(MID(A31,5,2),"000")) -> PROD029 | I31: Home | J31: =PROPER(TRIM(B31)) -> Fabric Sofa Throw Blanket | K31: =ROUNDUP(IF(ISBLANK(F31),AVERAGEIF(C:C,C31,F:F),F31),2) -> 218.48 | L31: =ROUNDUP(IF(ISBLANK(G31),AVERAGE(C:C,C31,G:G),G31),0) -> 276 | M31: =K31*L31 -> 60300.48
A32: PROD30 | B32: Stainless Steel Cutlery Set | C32: Home | D32: Kitchen | E32: Stevens, Fernandez and Martin | F32: 19.52 | G32: 57 | H32: =IF(LEFT(A32,2)="PROD16","PROD"&TEXT(MID(A32,3,2),"000"),"PROD"&TEXT(MID(A32,5,2),"000")) -> PROD030 | I32: Home | J32: =PROPER(TRIM(B32)) -> Stainless Steel Cutlery Set | K32: =ROUNDUP(IF(ISBLANK(F32),AVERAGEIF(C:C,C32,F:F),F32),2) -> 19.52 | L32: =ROUNDUP(IF(ISBLANK(G32),AVERAGE(C:C,C32,G:G),G32),0) -> 57 | M32: =K32*L32 -> 1112.64
A33: PROD31 | B33: Basketball | C33: Sports | D33: Team Sports | E33: Nolan-Snow | F33: 204.39 | G33: 281 | H33: =IF(LEFT(A33,2)="PROD16","PROD"&TEXT(MID(A33,3,2),"000"),"PROD"&TEXT(MID(A33,5,2),"000")) -> PROD031 | I33: Sports | J33: =PROPER(TRIM(B33)) -> Basketball | K33: =ROUNDUP(IF(ISBLANK(F33),AVERAGEIF(C:C,C33,F:F),F33),2) -> 204.39 | L33: =ROUNDUP(IF(ISBLANK(G33),AVERAGE(C:C,C33,G:G),G33),0) -> 281 | M33: =K33*L33 -> 57433.59
A34: PROD32 | B34: Vitamin C Face Serum | C34: Beauty | D34: Skincare | E34: Griffin Ltd | F34: 283.83 | G34: 244 | H34: =IF(LEFT(A34,2)="PROD16","PROD"&TEXT(MID(A34,3,2),"000"),"PROD"&TEXT(MID(A34,5,2),"000")) -> PROD032 | I34: Beauty | J34: =PROPER(TRIM(B34)) -> Vitamin C Face Serum | K34: =ROUNDUP(IF(ISBLANK(F34),AVERAGEIF(C:C,C34,F:F),F34),2) -> 283.83 | L34: =ROUNDUP(IF(ISBLANK(G34),AVERAGE(C:C,C34,G:G),G34),0) -> 244 | M34: =K34*L34 -> 69254.52
A35: PROD33 | B35: Modern Wall Clock | C35: Home | D35: Decor | E35: Weiss-Watson | F35: 179.77 | G35: 305 | H35: =IF(LEFT(A35,2)="PROD16","PROD"&TEXT(MID(A35,3,2),"000"),"PROD"&TEXT(MID(A35,5,2),"000")) -> PROD033 | I35: Home | J35: =PROPER(TRIM(B35)) -> Modern Wall Clock | K35: =ROUNDUP(IF(ISBLANK(F35),AVERAGEIF(C:C,C35,F:F),F35),2) -> 179.77 | L35: =ROUNDUP(IF(ISBLANK(G35),AVERAGE(C:C,C35,G:G),G35),0) -> 305 | M35: =K35*L35 -> 54829.85
A36: PROD34 | B36: Gaming Mechanical Keyboard | C36: Electronics | D36: Computer | E36: Lucero LLC | F36: 419.28 | G36: 86 | H36: =IF(LEFT(A36,2)="PROD16","PROD"&TEXT(MID(A36,3,2),"000"),"PROD"&TEXT(MID(A36,5,2),"000")) -> PROD034 | I36: Electronics | J36: =PROPER(TRIM(B36)) -> Gaming Mechanical Keyboard | K36: =ROUNDUP(IF(ISBLANK(F36),AVERAGEIF(C:C,C36,F:F),F36),2) -> 419.28 | L36: =ROUNDUP(IF(ISBLANK(G36),AVERAGE(C:C,C36,G:G),G36),0) -> 86 | M36: =K36*L36 -> 36058.08
A37: PROD35 | B37: Bedroom Table Lamp | C37: Home | D37: Lighting | E37: Jones LLC | F37: 382.22 | G37: 329 | H37: =IF(LEFT(A37,2)="PROD16","PROD"&TEXT(MID(A37,3,2),"000"),"PROD"&TEXT(MID(A37,5,2),"000")) -> PROD035 | I37: Home | J37: =PROPER(TRIM(B37)) -> Bedroom Table Lamp | K37: =ROUNDUP(IF(ISBLANK(F37),AVERAGEIF(C:C,C37,F:F),F37),2) -> 382.22 | L37: =ROUNDUP(IF(ISBLANK(G37),AVERAGE(C:C,C37,G:G),G37),0) -> 329 | M37: =K37*L37 -> 125750.38
A38: PROD36 | B38: Women's Summer Dress | C38: Clothing | D38: Tops | E38: Smith-Mills | F38: 223.43 | G38: 154 | H38: =IF(LEFT(A38,2)="PROD16","PROD"&TEXT(MID(A38,3,2),"000"),"PROD"&TEXT(MID(A38,5,2),"000")) -> PROD036 | I38: Clothing | J38: =PROPER(TRIM(B38)) -> Women'S Summer Dress | K38: =ROUNDUP(IF(ISBLANK(F38),AVERAGEIF(C:C,C38,F:F),F38),2) -> 223.43 | L38: =ROUNDUP(IF(ISBLANK(G38),AVERAGE(C:C,C38,G:G),G38),0) -> 154 | M38: =K38*L38 -> 34408.22
A39: PROD37 | B39: Men's Casual Sneakers | C39: Clothing | D39: Footwear | E39: Hogan-Lee | F39: 353.47 | G39: 214 | H39: =IF(LEFT(A39,2)="PROD16","PROD"&TEXT(MID(A39,3,2),"000"),"PROD"&TEXT(MID(A39,5,2),"000")) -> PROD037 | I39: Clothing | J39: =PROPER(TRIM(B39)) -> Men'S Casual Sneakers | K39: =ROUNDUP(IF(ISBLANK(F39),AVERAGEIF(C:C,C39,F:F),F39),2) -> 353.47 | L39: =ROUNDUP(IF(ISBLANK(G39),AVERAGE(C:C,C39,G:G),G39),0) -> 214 | M39: =K39*L39 -> 75642.58
A40: PROD38 | B40: Sports Water Hydration Pack | C40: Sports | D40: Outdoor | E40: Sims-Smith | F40: 135.61 | G40: 394 | H40: =IF(LEFT(A40,2)="PROD16","PROD"&TEXT(MID(A40,3,2),"000"),"PROD"&TEXT(MID(A40,5,2),"000")) -> PROD038 | I40: Sports | J40: =PROPER(TRIM(B40)) -> Sports Water Hydration Pack | K40: =ROUNDUP(IF(ISBLANK(F40),AVERAGEIF(C:C,C40,F:F),F40),2) -> 135.61 | L40: =ROUNDUP(IF(ISBLANK(G40),AVERAGE(C:C,C40,G:G),G40),0) -> 394 | M40: =K40*L40 -> 53430.34
A41: PROD39 | B41: Portable Power Bank | C41: Electronics | D41: Mobile | E41: Cummings and Sons | F41: 326.06 | G41: 301 | H41: =IF(LEFT(A41,2)="PROD16","PROD"&TEXT(MID(A41,3,2),"000"),"PROD"&TEXT(MID(A41,5,2),"000")) -> PROD039 | I41: Electronics | J41: =PROPER(TRIM(B41)) -> Portable Power Bank | K41: =ROUNDUP(IF(ISBLANK(F41),AVERAGEIF(C:C,C41,F:F),F41),2) -> 326.06 | L41: =ROUNDUP(IF(ISBLANK(G41),AVERAGE(C:C,C41,G:G),G41),0) -> 301 | M41: =K41*L41 -> 98144.06
... A48: PROD46 | B48: Men's Winter Jacket | C48: Clothing | D48: Outerwear | E48: Kelly, Smith and Perez | F48: 167.34 | G48: 296 | H48: =IF(LEFT(A48,2)="PROD16","PROD"&TEXT(MID(A48,3,2),"000"),"PROD"&TEXT(MID(A48,5,2),"000")) -> PROD046 | I48: Clothing | J48: =PROPER(TRIM(B48)) -> Men'S Winter Jacket | K48: =ROUNDUP(IF(ISBLANK(F48),AVERAGEIF(C:C,C48,F:F),F48),2) -> 167.34 | L48: =ROUNDUP(IF(ISBLANK(G48),AVERAGE(C:C,C48,G:G),G48),0) -> 296 | M48: =K48*L48 -> 49532.64
A49: PROD47 | B49: Makeup Brush Set | C49: Beauty | D49: Makeup | E49: Cook Inc | G49: 431 | H49: =IF(LEFT(A49,2)="PROD16","PROD"&TEXT(MID(A49,3,2),"000"),"PROD"&TEXT(MID(A49,5,2),"000")) -> PROD047 | I49: Beauty | J49: =PROPER(TRIM(B49)) -> Makeup Brush Set | K49: =ROUNDUP(IF(ISBLANK(F49),AVERAGEIF(C:C,C49,F:F),F49),2) -> 250.42 | L49: =ROUNDUP(IF(ISBLANK(G49),AVERAGE(C:C,C49,G:G),G49),0) -> 431 | M49: =K49*L49 -> 107931.02
A50: PROD48 | B50: Car Dashboard Phone Holder | C50: Electronics | D50: Accessories | E50: Byrd, Stewart and Valdez | F50: 177.98 | G50: 103 | H50: =IF(LEFT(A50,2)="PROD16","PROD"&TEXT(MID(A50,3,2),"000"),"PROD"&TEXT(MID(A50,5,2),"000")) -> PROD048 | I50: Electronics | J50: =PROPER(TRIM(B50)) -> Car Dashboard Phone Holder | K50: =ROUNDUP(IF(ISBLANK(F50),AVERAGEIF(C:C,C50,F:F),F50),2) -> 177.98 | L50: =ROUNDUP(IF(ISBLANK(G50),AVERAGE(C:C,C50,G:G),G50),0) -> 103 | M50: =K50*L50 -> 18331.94
A51: PROD49 | B51: Men's Roll-On Perfume | C51: Beauty | D51: Fragrance | E51: Sullivan and Sons | F51: 43.29 | G51: 267 | H51: =IF(LEFT(A51,2)="PROD16","PROD"&TEXT(MID(A51,3,2),"000"),"PROD"&TEXT(MID(A51,5,2),"000")) -> PROD049 | I51: Beauty | J51: =PROPER(TRIM(B51)) -> Men'S Roll-On Perfume | K51: =ROUNDUP(IF(ISBLANK(F51),AVERAGEIF(C:C,C51,F:F),F51),2) -> 43.29 | L51: =ROUNDUP(IF(ISBLANK(G51),AVERAGE(C:C,C51,G:G),G51),0) -> 267 | M51: =K51*L51 -> 11558.43
A52: PROD50 | B52: Boxing Hand Wraps | C52: Sports | D52: Fitness | E52: Smith-King | F52: 190.29 | G52: 260 | H52: =IF(LEFT(A52,2)="PROD16","PROD"&TEXT(MID(A52,3,2),"000"),"PROD"&TEXT(MID(A52,5,2),"000")) -> PROD050 | I52: Sports | J52: =PROPER(TRIM(B52)) -> Boxing Hand Wraps | K52: =ROUNDUP(IF(ISBLANK(F52),AVERAGEIF(C:C,C52,F:F),F52),2) -> 190.29 | L52: =ROUNDUP(IF(ISBLANK(G52),AVERAGE(C:C,C52,G:G),G52),0) -> 260 | M52: =K52*L52 -> 49475.4
A53: PROD51 | B53: HDMI Cable – 2m | C53: Electronics | D53: Accessories | E53: Bautista, Green and Hale | F53: 88.49 | G53: 246 | H53: =IF(LEFT(A53,2)="PROD16","PROD"&TEXT(MID(A53,3,2),"000"),"PROD"&TEXT(MID(A53,5,2),"000")) -> PROD051 | I53: Electronics | J53: =PROPER(TRIM(B53)) -> Hdmi Cable – 2M | K53: =ROUNDUP(IF(ISBLANK(F53),AVERAGEIF(C:C,C53,F:F),F53),2) -> 88.49 | L53: =ROUNDUP(IF(ISBLANK(G53),AVERAGE(C:C,C53,G:G),G53),0) -> 246 | M53: =K53*L53 -> 21768.54
A54: PROD52 | B54: Rugby Ball | C54: Sports | D54: Team Sports | E54: Harris Inc | F54: 212.26 | G54: 82 | H54: =IF(LEFT(A54,2)="PROD16","PROD"&TEXT(MID(A54,3,2),"000"),"PROD"&TEXT(MID(A54,5,2),"000")) -> PROD052 | I54: Sports | J54: =PROPER(TRIM(B54)) -> Rugby Ball | K54: =ROUNDUP(IF(ISBLANK(F54),AVERAGEIF(C:C,C54,F:F),F54),2) -> 212.26 | L54: =ROUNDUP(IF(ISBLANK(G54),AVERAGE(C:C,C54,G:G),G54),0) -> 82 | M54: =K54*L54 -> 17405.32
A55: PROD53 | B55: Men's Track Pants | C55: Clothing | D55: Bottoms | E55: Hamilton, Woods and Walker | F55: 386.56 | G55: 125 | H55: =IF(LEFT(A55,2)="PROD16","PROD"&TEXT(MID(A55,3,2),"000"),"PROD"&TEXT(MID(A55,5,2),"000")) -> PROD053 | I55: Clothing | J55: =PROPER(TRIM(B55)) -> Men'S Track Pants | K55: =ROUNDUP(IF(ISBLANK(F55),AVERAGEIF(C:C,C55,F:F),F55),2) -> 386.56 | L55: =ROUNDUP(IF(ISBLANK(G55),AVERAGE(C:C,C55,G:G),G55),0) -> 125 | M55: =K55*L55 -> 48320
A56: PROD54 | B56: Sports Stopwatch Pro | C56: Sports | D56: Accessories | E56: Thompson-French | F56: 434.84 | G56: 185 | H56: =IF(LEFT(A56,2)="PROD16","PROD"&TEXT(MID(A56,3,2),"000"),"PROD"&TEXT(MID(A56,5,2),"000")) -> PROD054 | I56: Sports | J56: =PROPER(TRIM(B56)) -> Sports Stopwatch Pro | K56: =ROUNDUP(IF(ISBLANK(F56),AVERAGEIF(C:C,C56,F:F),F56),2) -> 434.84 | L56: =ROUNDUP(IF(ISBLANK(G56),AVERAGE(C:C,C56,G:G),G56),0) -> 185 | M56: =K56*L56 -> 80445.4
A57: PROD55 | B57: Ceramic Plant Pot | C57: Home | D57: Decor | E57: Hatfield, Baird and Torres | F57: 81.75 | H57: =IF(LEFT(A57,2)="PROD16","PROD"&TEXT(MID(A57,3,2),"000"),"PROD"&TEXT(MID(A57,5,2),"000")) -> PROD055 | I57: Home | J57: =PROPER(TRIM(B57)) -> Ceramic Plant Pot | K57: =ROUNDUP(IF(ISBLANK(F57),AVERAGEIF(C:C,C57,F:F),F57),2) -> 81.75 | L57: =ROUNDUP(IF(ISBLANK(G57),AVERAGE(C:C,C57,G:G),G57),0) -> 274 | M57: =K57*L57 -> 22399.5
A58: PROD56 | B58: Premium Blanket Throw | C58: Home | D58: Decor | E58: Hernandez, Kennedy and Porter | F58: 461.47 | G58: 190 | H58: =IF(LEFT(A58,2)="PROD16","PROD"&TEXT(MID(A58,3,2),"000"),"PROD"&TEXT(MID(A58,5,2),"000")) -> PROD056 | I58: Home | J58: =PROPER(TRIM(B58)) -> Premium Blanket Throw | K58: =ROUNDUP(IF(ISBLANK(F58),AVERAGEIF(C:C,C58,F:F),F58),2) -> 461.47 | L58: =ROUNDUP(IF(ISBLANK(G58),AVERAGE(C:C,C58,G:G),G58),0) -> 190 | M58: =K58*L58 -> 87679.3
A59: PROD57 | B59: Foam Roller | C59: Sports | D59: Fitness | E59: Atkinson, Camacho and Oliver | F59: 30.62 | G59: 138 | H59: =IF(LEFT(A59,2)="PROD16","PROD"&TEXT(MID(A59,3,2),"000"),"PROD"&TEXT(MID(A59,5,2),"000")) -> PROD057 | I59: Sports | J59: =PROPER(TRIM(B59)) -> Foam Roller | K59: =ROUNDUP(IF(ISBLANK(F59),AVERAGEIF(C:C,C59,F:F),F59),2) -> 30.62 | L59: =ROUNDUP(IF(ISBLANK(G59),AVERAGE(C:C,C59,G:G),G59),0) -> 138 | M59: =K59*L59 -> 4225.56
A60: PROD58 | B60: Womens Cotton Scarf | C60: Clothing | D60: Accessories | E60: Shepherd-Gould | F60: 113.83 | G60: 485 | H60: =IF(LEFT(A60,2)="PROD16","PROD"&TEXT(MID(A60,3,2),"000"),"PROD"&TEXT(MID(A60,5,2),"000")) -> PROD058 | I60: Clothing | J60: =PROPER(TRIM(B60)) -> Womens Cotton Scarf | K60: =ROUNDUP(IF(ISBLANK(F60),AVERAGEIF(C:C,C60,F:F),F60),2) -> 113.83 | L60: =ROUNDUP(IF(ISBLANK(G60),AVERAGE(C:C,C60,G:G),G60),0) -> 485 | M60: =K60*L60 -> 55207.55
A61: PROD59 | B61: Men's Hair Styling Gel | C61: Beauty | D61: Haircare | E61: Cline-Mccarthy | F61: 17.31 | G61: 399 | H61: =IF(LEFT(A61,2)="PROD16","PROD"&TEXT(MID(A61,3,2),"000"),"PROD"&TEXT(MID(A61,5,2),"000")) -> PROD059 | I61: Beauty | J61: =PROPER(TRIM(B61)) -> Men'S Hair Styling Gel | K61: =ROUNDUP(IF(ISBLANK(F61),AVERAGEIF(C:C,C61,F:F),F61),2) -> 17.31 | L61: =ROUNDUP(IF(ISBLANK(G61),AVERAGE(C:C,C61,G:G),G61),0) -> 399 | M61: =K61*L61 -> 6906.69
A62: PROD60 | B62: Luxury Perfume Spray | C62: Beauty | D62: Fragrance | E62: Gibson, Green and Lopez | F62: 482.75 | G62: 444 | H62: =IF(LEFT(A62,2)="PROD16","PROD"&TEXT(MID(A62,3,2),"000"),"PROD"&TEXT(MID(A62,5,2),"000")) -> PROD060 | I62: Beauty | J62: =PROPER(TRIM(B62)) -> Luxury Perfume Spray | K62: =ROUNDUP(IF(ISBLANK(F62),AVERAGEIF(C:C,C62,F:F),F62),2) -> 482.75 | L62: =ROUNDUP(IF(ISBLANK(G62),AVERAGE(C:C,C62,G:G),G62),0) -> 444 | M62: =K62*L62 -> 214341
A63: PROD61 | B63: Tennis Ball 3-Pack | C63: Sports | D63: Equipment | E63: Lopez LLC | F63: 103.45 | G63: 465 | H63: =IF(LEFT(A63,2)="PROD16","PROD"&TEXT(MID(A63,3,2),"000"),"PROD"&TEXT(MID(A63,5,2),"000")) -> PROD061 | I63: Sports | J63: =PROPER(TRIM(B63)) -> Tennis Ball 3-Pack | K63: =ROUNDUP(IF(ISBLANK(F63),AVERAGEIF(C:C,C63,F:F),F63),2) -> 103.45 | L63: =ROUNDUP(IF(ISBLANK(G63),AVERAGE(C:C,C63,G:G),G63),0) -> 465 | M63: =K63*L63 -> 48104.25
A64: PROD62 | B64: Laptop Cooling Pad | C64: Electronics | D64: Computer | E64: Murray, Gould and Ware | F64: 86.42 | G64: 222 | H64: =IF(LEFT(A64,2)="PROD16","PROD"&TEXT(MID(A64,3,2),"000"),"PROD"&TEXT(MID(A64,5,2),"000")) -> PROD062 | I64: Electronics | J64: =PROPER(TRIM(B64)) -> Laptop Cooling Pad | K64: =ROUNDUP(IF(ISBLANK(F64),AVERAGEIF(C:C,C64,F:F),F64),2) -> 86.42 | L64: =ROUNDUP(IF(ISBLANK(G64),AVERAGE(C:C,C64,G:G),G64),0) -> 222 | M64: =K64*L64 -> 19185.24
A65: PROD63 | B65: Organic Sunscreen Lotion | C65: Beauty | D65: Skincare | E65: Anderson-Riley | F65: 266.86 | G65: 458 | H65: =IF(LEFT(A65,2)="PROD16","PROD"&TEXT(MID(A65,3,2),"000"),"PROD"&TEXT(MID(A65,5,2),"000")) -> PROD063 | I65: Beauty | J65: =PROPER(TRIM(B65)) -> Organic Sunscreen Lotion | K65: =ROUNDUP(IF(ISBLANK(F65),AVERAGEIF(C:C,C65,F:F),F65),2) -> 266.86 | L65: =ROUNDUP(IF(ISBLANK(G65),AVERAGE(C:C,C65,G:G),G65),0) -> 458 | M65: =K65*L65 -> 122221.88
A66: PROD64 | B66: Matte Lipstick Set | C66: Beauty | D66: Makeup | E66: Zhang Inc | F66: 299.11 | G66: 118 | H66: =IF(LEFT(A66,2)="PROD16","PROD"&TEXT(MID(A66,3,2),"000"),"PROD"&TEXT(MID(A66,5,2),"000")) -> PROD064 | I66: Beauty | J66: =PROPER(TRIM(B66)) -> Matte Lipstick Set | K66: =ROUNDUP(IF(ISBLANK(F66),AVERAGEIF(C:C,C66,F:F),F66),2) -> 299.11 | L66: =ROUNDUP(IF(ISBLANK(G66),AVERAGE(C:C,C66,G:G),G66),0) -> 118 | M66: =K66*L66 -> 35294.98
A67: PROD65 | B67: Adjustable Dumbbells 20kg | C67: Sports | D67: Fitness | E67: Montgomery, Benton and Miller | F67: 240.63 | G67: 423 | H67: =IF(LEFT(A67,2)="PROD16","PROD"&TEXT(MID(A67,3,2),"000"),"PROD"&TEXT(MID(A67,5,2),"000")) -> PROD065 | I67: Sports | J67: =PROPER(TRIM(B67)) -> Adjustable Dumbbells 20Kg | K67: =ROUNDUP(IF(ISBLANK(F67),AVERAGEIF(C:C,C67,F:F),F67),2) -> 240.63 | L67: =ROUNDUP(IF(ISBLANK(G67),AVERAGE(C:C,C67,G:G),G67),0) -> 423 | M67: =K67*L67 -> 101786.49
A68: PROD66 | B68: Women's Hair Dryer Brush | C68: Beauty | D68: Haircare | E68: Torres, Spencer and Potter | F68: 340.39 | G68: 177 | H68: =IF(LEFT(A68,2)="PROD16","PROD"&TEXT(MID(A68,3,2),"000"),"PROD"&TEXT(MID(A68,5,2),"000")) -> PROD066 | I68: Beauty | J68: =PROPER(TRIM(B68)) -> Women'S Hair Dryer Brush | K68: =ROUNDUP(IF(ISBLANK(F68),AVERAGEIF(C:C,C68,F:F),F68),2) -> 340.39 | L68: =ROUNDUP(IF(ISBLANK(G68),AVERAGE(C:C,C68,G:G),G68),0) -> 177 | M68: =K68*L68 -> 60249.03
A69: PROD67 | B69: Smart LED Light Strip | C69: Electronics | D69: Accessories | E69: Flores-Davis | F69: 349.17 | G69: 476 | H69: =IF(LEFT(A69,2)="PROD16","PROD"&TEXT(MID(A69,3,2),"000"),"PROD"&TEXT(MID(A69,5,2),"000")) -> PROD067 | I69: Electronics | J69: =PROPER(TRIM(B69)) -> Smart Led Light Strip | K69: =ROUNDUP(IF(ISBLANK(F69),AVERAGEIF(C:C,C69,F:F),F69),2) -> 349.17 | L69: =ROUNDUP(IF(ISBLANK(G69),AVERAGE(C:C,C69,G:G),G69),0) -> 476 | M69: =K69*L69 -> 166204.92
... A84: PROD82 | B84: Fitness Resistance Bands | C84: Sports | D84: Fitness | E84: Reese-Watson | F84: 152.92 | G84: 281 | H84: =IF(LEFT(A84,2)="PROD16","PROD"&TEXT(MID(A84,3,2),"000"),"PROD"&TEXT(MID(A84,5,2),"000")) -> PROD082 | I84: Sports | J84: =PROPER(TRIM(B84)) -> Fitness Resistance Bands | K84: =ROUNDUP(IF(ISBLANK(F84),AVERAGEIF(C:C,C84,F:F),F84),2) -> 152.92 | L84: =ROUNDUP(IF(ISBLANK(G84),AVERAGE(C:C,C84,G:G),G84),0) -> 281 | M84: =K84*L84 -> 42970.52
A85: PROD83 | B85: Hydrating Face Cleanser | C85: Beauty | D85: Skincare | E85: Butler Group | G85: 159 | H85: =IF(LEFT(A85,2)="PROD16","PROD"&TEXT(MID(A85,3,2),"000"),"PROD"&TEXT(MID(A85,5,2),"000")) -> PROD083 | I85: Beauty | J85: =PROPER(TRIM(B85)) -> Hydrating Face Cleanser | K85: =ROUNDUP(IF(ISBLANK(F85),AVERAGEIF(C:C,C85,F:F),F85),2) -> 250.42 | L85: =ROUNDUP(IF(ISBLANK(G85),AVERAGE(C:C,C85,G:G),G85),0) -> 159 | M85: =K85*L85 -> 39816.78
A86: PROD84 | B86: Wooden Bookshelf | C86: Home | D86: Furniture | E86: Collins-Stephenson | F86: 388.46 | G86: 208 | H86: =IF(LEFT(A86,2)="PROD16","PROD"&TEXT(MID(A86,3,2),"000"),"PROD"&TEXT(MID(A86,5,2),"000")) -> PROD084 | I86: Home | J86: =PROPER(TRIM(B86)) -> Wooden Bookshelf | K86: =ROUNDUP(IF(ISBLANK(F86),AVERAGEIF(C:C,C86,F:F),F86),2) -> 388.46 | L86: =ROUNDUP(IF(ISBLANK(G86),AVERAGE(C:C,C86,G:G),G86),0) -> 208 | M86: =K86*L86 -> 80799.68
A87: PROD85 | B87: Women's Beanie Hat | C87: Clothing | D87: Accessories | E87: Richardson-Carrillo | F87: 119.57 | G87: 210 | H87: =IF(LEFT(A87,2)="PROD16","PROD"&TEXT(MID(A87,3,2),"000"),"PROD"&TEXT(MID(A87,5,2),"000")) -> PROD085 | I87: Clothing | J87: =PROPER(TRIM(B87)) -> Women'S Beanie Hat | K87: =ROUNDUP(IF(ISBLANK(F87),AVERAGEIF(C:C,C87,F:F),F87),2) -> 119.57 | L87: =ROUNDUP(IF(ISBLANK(G87),AVERAGE(C:C,C87,G:G),G87),0) -> 210 | M87: =K87*L87 -> 25109.7
A88: PROD86 | B88: Kitchen Cutting Board | C88: Home | D88: Kitchen | E88: Taylor, Dodson and Johnston | F88: 176.07 | G88: 82 | H88: =IF(LEFT(A88,2)="PROD16","PROD"&TEXT(MID(A88,3,2),"000"),"PROD"&TEXT(MID(A88,5,2),"000")) -> PROD086 | I88: Home | J88: =PROPER(TRIM(B88)) -> Kitchen Cutting Board | K88: =ROUNDUP(IF(ISBLANK(F88),AVERAGEIF(C:C,C88,F:F),F88),2) -> 176.07 | L88: =ROUNDUP(IF(ISBLANK(G88),AVERAGE(C:C,C88,G:G),G88),0) -> 82 | M88: =K88*L88 -> 14437.74
A89: PROD87 | B89: LED Bedside Lamp | C89: Home | D89: Lighting | E89: Aguilar, Horton and Lewis | F89: 371.38 | G89: 220 | H89: =IF(LEFT(A89,2)="PROD16","PROD"&TEXT(MID(A89,3,2),"000"),"PROD"&TEXT(MID(A89,5,2),"000")) -> PROD087 | I89: Home | J89: =PROPER(TRIM(B89)) -> Led Bedside Lamp | K89: =ROUNDUP(IF(ISBLANK(F89),AVERAGEIF(C:C,C89,F:F),F89),2) -> 371.38 | L89: =ROUNDUP(IF(ISBLANK(G89),AVERAGE(C:C,C89,G:G),G89),0) -> 220 | M89: =K89*L89 -> 81703.6
A90: PROD88 | B90: Sports Wrist Sweatbands | C90: Sports | D90: Accessories | E90: Olsen-Daniels | F90: 131.24 | G90: 232 | H90: =IF(LEFT(A90,2)="PROD16","PROD"&TEXT(MID(A90,3,2),"000"),"PROD"&TEXT(MID(A90,5,2),"000")) -> PROD088 | I90: Sports | J90: =PROPER(TRIM(B90)) -> Sports Wrist Sweatbands | K90: =ROUNDUP(IF(ISBLANK(F90),AVERAGEIF(C:C,C90,F:F),F90),2) -> 131.24 | L90: =ROUNDUP(IF(ISBLANK(G90),AVERAGE(C:C,C90,G:G),G90),0) -> 232 | M90: =K90*L90 -> 30447.68
A91: PROD89 | B91: Face Foundation Kit | C91: Beauty | D91: Makeup | E91: Taylor-Elliott | F91: 183.04 | G91: 457 | H91: =IF(LEFT(A91,2)="PROD16","PROD"&TEXT(MID(A91,3,2),"000"),"PROD"&TEXT(MID(A91,5,2),"000")) -> PROD089 | I91: Beauty | J91: =PROPER(TRIM(B91)) -> Face Foundation Kit | K91: =ROUNDUP(IF(ISBLANK(F91),AVERAGEIF(C:C,C91,F:F),F91),2) -> 183.04 | L91: =ROUNDUP(IF(ISBLANK(G91),AVERAGE(C:C,C91,G:G),G91),0) -> 457 | M91: =K91*L91 -> 83649.28
A92: PROD90 | B92: Gaming Mouse Pad XL | C92: Electronics | D92: Accessories | E92: Sharp, Taylor and Rodriguez | F92: 340.14 | G92: 361 | H92: =IF(LEFT(A92,2)="PROD16","PROD"&TEXT(MID(A92,3,2),"000"),"PROD"&TEXT(MID(A92,5,2),"000")) -> PROD090 | I92: Electronics | J92: =PROPER(TRIM(B92)) -> Gaming Mouse Pad Xl | K92: =ROUNDUP(IF(ISBLANK(F92),AVERAGEIF(C:C,C92,F:F),F92),2) -> 340.14 | L92: =ROUNDUP(IF(ISBLANK(G92),AVERAGE(C:C,C92,G:G),G92),0) -> 361 | M92: =K92*L92 -> 122790.54
A93: PROD91 | B93: Women's High Heels | C93: Clothing | D93: Footwear | E93: Smith-Charles | F93: 438.25 | G93: 496 | H93: =IF(LEFT(A93,2)="PROD16","PROD"&TEXT(MID(A93,3,2),"000"),"PROD"&TEXT(MID(A93,5,2),"000")) -> PROD091 | I93: Clothing | J93: =PROPER(TRIM(B93)) -> Women'S High Heels | K93: =ROUNDUP(IF(ISBLANK(F93),AVERAGEIF(C:C,C93,F:F),F93),2) -> 438.25 | L93: =ROUNDUP(IF(ISBLANK(G93),AVERAGE(C:C,C93,G:G),G93),0) -> 496 | M93: =K93*L93 -> 217372
A94: PROD92 | B94: Microwave Oven | C94: Home | D94: Appliances | E94: Green, Powell and Palmer | F94: 447.43 | G94: 191 | H94: =IF(LEFT(A94,2)="PROD16","PROD"&TEXT(MID(A94,3,2),"000"),"PROD"&TEXT(MID(A94,5,2),"000")) -> PROD092 | I94: Home | J94: =PROPER(TRIM(B94)) -> Microwave Oven | K94: =ROUNDUP(IF(ISBLANK(F94),AVERAGEIF(C:C,C94,F:F),F94),2) -> 447.43 | L94: =ROUNDUP(IF(ISBLANK(G94),AVERAGE(C:C,C94,G:G),G94),0) -> 191 | M94: =K94*L94 -> 85459.13
A95: PROD93 | B95: USB-C Laptop Charger | C95: Electronics | D95: Computer | E95: Martin LLC | F95: 377.52 | G95: 485 | H95: =IF(LEFT(A95,2)="PROD16","PROD"&TEXT(MID(A95,3,2),"000"),"PROD"&TEXT(MID(A95,5,2),"000")) -> PROD093 | I95: Electronics | J95: =PROPER(TRIM(B95)) -> Usb-C Laptop Charger | K95: =ROUNDUP(IF(ISBLANK(F95),AVERAGEIF(C:C,C95,F:F),F95),2) -> 377.52 | L95: =ROUNDUP(IF(ISBLANK(G95),AVERAGE(C:C,C95,G:G),G95),0) -> 485 | M95: =K95*L95 -> 183097.2
A96: PROD94 | B96: Vitamin E Body Lotion | C96: Beauty | D96: Skincare | E96: Hoffman-Williams | F96: 358.47 | G96: 213 | H96: =IF(LEFT(A96,2)="PROD16","PROD"&TEXT(MID(A96,3,2),"000"),"PROD"&TEXT(MID(A96,5,2),"000")) -> PROD094 | I96: Beauty | J96: =PROPER(TRIM(B96)) -> Vitamin E Body Lotion | K96: =ROUNDUP(IF(ISBLANK(F96),AVERAGEIF(C:C,C96,F:F),F96),2) -> 358.47 | L96: =ROUNDUP(IF(ISBLANK(G96),AVERAGE(C:C,C96,G:G),G96),0) -> 213 | M96: =K96*L96 -> 76354.11
A97: PROD95 | B97: Sports Stopwatch Basic | C97: Sports | D97: Accessories | E97: Wilson Group | F97: 60.65 | G97: 75 | H97: =IF(LEFT(A97,2)="PROD16","PROD"&TEXT(MID(A97,3,2),"000"),"PROD"&TEXT(MID(A97,5,2),"000")) -> PROD095 | I97: Sports | J97: =PROPER(TRIM(B97)) -> Sports Stopwatch Basic | K97: =ROUNDUP(IF(ISBLANK(F97),AVERAGEIF(C:C,C97,F:F),F97),2) -> 60.65 | L97: =ROUNDUP(IF(ISBLANK(G97),AVERAGE(C:C,C97,G:G),G97),0) -> 75 | M97: =K97*L97 -> 4548.75
... A101: PROD99 | B101: Stainless Steel Cookware Set | C101: Home | D101: Kitchen | E101: Campbell Ltd | F101: 201.41 | G101: 146 | H101: =IF(LEFT(A101,2)="PROD16","PROD"&TEXT(MID(A101,3,2),"000"),"PROD"&TEXT(MID(A101,5,2),"000")) -> PROD099 | I101: Home | J101: =PROPER(TRIM(B101)) -> Stainless Steel Cookware Set | K101: =ROUNDUP(IF(ISBLANK(F101),AVERAGEIF(C:C,C101,F:F),F101),2) -> 201.41 | L101: =ROUNDUP(IF(ISBLANK(G101),AVERAGE(C:C,C101,G:G),G101),0) -> 146 | M101: =K101*L101 -> 29405.86

Sheet Store_Dim
A1: Store_ID | B1: Store_Name | C1: Region | D1: City | E1: Store_Type
A2: STORE0 | B2: Rivera-Warner | C2: East | D2: Washingtonfurt | E2: Flagship
A3: STORE1 | B3: Martinez, Adkins and Johnson | C3: North | D3: Danielmouth | E3: Flagship
A4: STORE2 | B4: Black-Horn | C4: South | D4: North Nancyview | E4: Outlet
A5: STORE3 | B5: Johnson-Wright | C5: North | D5: Hoodberg | E5: Outlet
A6: STORE4 | B6: Alexander Group | C6: South | D6: Port Sharon | E6: Online
A7: STORE5 | B7: Gray Ltd | C7: North | D7: New Michaelchester | E7: Outlet
A8: STORE6 | B8: Benson-Elliott | C8: East | D8: Port Josephberg | E8: Online
A9: STORE7 | B9: Martinez-Mullins | C9: South | D9: Williamsfurt | E9: Online
A10: STORE8 | B10: Bean, Jones and Park | C10: West | D10: Thompsonborough | E10: Online
A11: STORE9 | B11: Moore, Padilla and Butler | C11: South | D11: East Johnstad | E11: Flagship
A12: STORE10 | B12: Hill, Wagner and Ballard | C12: East | D12: East Davidville | E12: Online
... A21: STORE19 | B21: Mann-Austin | C21: East | D21: Vasquezborough | E21: Online

Sheet Sales_Fact
A1: Sales_ID | B1: Order_Date | C1: Customer_ID | D1: Product_ID | E1: Store_ID | F1: Quantity | G1: Unit_Price | H1: Discount | I1: Payment_Type | J1: Total_Amount | K1: Clean Order Date | L1: Month | M1: Clean Quantity | N1: Clean Unit Price | O1: Clean Total Amount | P1: Overall Pice | Q1: Discount price | R1: Sales Perfomance | S1: Customer Name | T1: Product Category | U1: Product Name | V1: store region | W1: Loyalty Check | X1: Order range
A2: SALE0 | B2: 45480 | C2: CUST1409 | D2: PROD97 | E2: STORE3 | F2: 1 | G2: 218.04 | H2: 0.09 | I2: Credit Card | J2: 198.4164 | K2: =TEXT(B2,"dd-mm-yyyy") -> 07-07-2024 | L2: =TEXT(Sales_Fact!$B2,"mmm") -> Jul | M2: =IF(ISBLANK(F2),1,F2) -> 1 | N2: =ROUNDUP(IF(ISBLANK(G2),AVERAGE(C:C,G2,G:G),G2),2) -> 218.04 | O2: =M2*N2*(1-H2) -> 198.4164 | P2: =M2*N2 -> 218.04 | Q2: =(P2-O2)/P2 -> 0.09 | R2: =IF(Sales_Fact!$O2>1000,"High","Low") -> Low | S2: =VLOOKUP(C2,Customer_Dim!$A:$N,9,FALSE()) -> Sarah Smith | T2: =VLOOKUP(D2,Product_Dim!$A:$M,3,FALSE()) -> Sports | U2: =VLOOKUP(D2,Product_Dim!$A:$M,2,FALSE()) -> Cricket Bat | V2: =VLOOKUP(E2,Store_Dim!$A:$E,3,FALSE()) -> North | W2: =VLOOKUP(C2,Customer_Dim!$A:$N,13,FALSE()) -> Gold | X2: =IF(F2>3,"High","Low") -> Low
A3: SALE1 | B3: 45285 | C3: CUST1467 | D3: PROD74 | E3: STORE17 | F3: 3 | G3: 104.47 | H3: 0.27 | I3: PayPal | J3: 228.7893 | K3: =TEXT(B3,"dd-mm-yyyy") -> 25-12-2023 | L3: =TEXT(Sales_Fact!$B3,"mmm") -> Dec | M3: =IF(ISBLANK(F3),1,F3) -> 3 | N3: =ROUNDUP(IF(ISBLANK(G3),AVERAGE(C:C,G3,G:G),G3),2) -> 104.47 | O3: =M3*N3*(1-H3) -> 228.7893 | P3: =M3*N3 -> 313.41 | Q3: =(P3-O3)/P3 -> 0.27 | R3: =IF(Sales_Fact!$O3>1000,"High","Low") -> Low | S3: =VLOOKUP(C3,Customer_Dim!$A:$N,9,FALSE()) -> Michael Foley | T3: =VLOOKUP(D3,Product_Dim!$A:$M,3,FALSE()) -> Electronics | U3: =VLOOKUP(D3,Product_Dim!$A:$M,2,FALSE()) -> Bluetooth Car Audio System | V3: =VLOOKUP(E3,Store_Dim!$A:$E,3,FALSE()) -> North | W3: =VLOOKUP(C3,Customer_Dim!$A:$N,13,FALSE()) -> Gold | X3: =IF(F3>3,"High","Low") -> Low
A4: SALE10 | B4: 45335 | C4: CUST1065 | D4: PROD24 | E4: STORE14 | F4: 1 | G4: 278.63 | H4: 0.07 | I4: Credit Card | J4: 259.1259 | K4: =TEXT(B4,"dd-mm-yyyy") -> 13-02-2024 | L4: =TEXT(Sales_Fact!$B4,"mmm") -> Feb | M4: =IF(ISBLANK(F4),1,F4) -> 1 | N4: =ROUNDUP(IF(ISBLANK(G4),AVERAGE(C:C,G4,G:G),G4),2) -> 278.63 | O4: =M4*N4*(1-H4) -> 259.1259 | P4: =M4*N4 -> 278.63 | Q4: =(P4-O4)/P4 -> 0.07 | R4: =IF(Sales_Fact!$O4>1000,"High","Low") -> Low | S4: =VLOOKUP(C4,Customer_Dim!$A:$N,9,FALSE()) -> Michael Thomas | T4: =VLOOKUP(D4,Product_Dim!$A:$M,3,FALSE()) -> Sports | U4: =VLOOKUP(D4,Product_Dim!$A:$M,2,FALSE()) -> Foldable Camping Chair | V4: =VLOOKUP(E4,Store_Dim!$A:$E,3,FALSE()) -> South | W4: =VLOOKUP(C4,Customer_Dim!$A:$N,13,FALSE()) -> Silver | X4: =IF(F4>3,"High","Low") -> Low
A5: SALE100 | B5: 45677 | C5: CUST1369 | D5: PROD33 | E5: STORE5 | F5: 2 | G5: 401.5 | H5: 0.18 | I5: Credit Card | J5: 658.46 | K5: =TEXT(B5,"dd-mm-yyyy") -> 20-01-2025 | L5: =TEXT(Sales_Fact!$B5,"mmm") -> Jan | M5: =IF(ISBLANK(F5),1,F5) -> 2 | N5: =ROUNDUP(IF(ISBLANK(G5),AVERAGE(C:C,G5,G:G),G5),2) -> 401.5 | O5: =M5*N5*(1-H5) -> 658.46 | P5: =M5*N5 -> 803 | Q5: =(P5-O5)/P5 -> 0.18 | R5: =IF(Sales_Fact!$O5>1000,"High","Low") -> Low | S5: =VLOOKUP(C5,Customer_Dim!$A:$N,9,FALSE()) -> Gregory Allen | T5: =VLOOKUP(D5,Product_Dim!$A:$M,3,FALSE()) -> Home | U5: =VLOOKUP(D5,Product_Dim!$A:$M,2,FALSE()) -> Modern Wall Clock | V5: =VLOOKUP(E5,Store_Dim!$A:$E,3,FALSE()) -> North | W5: =VLOOKUP(C5,Customer_Dim!$A:$N,13,FALSE()) -> Platinum | X5: =IF(F5>3,"High","Low") -> Low
A6: SALE1000 | B6: 45456 | C6: CUST1190 | D6: PROD59 | E6: STORE2 | F6: 2 | G6: 909.51 | H6: 0.27 | I6: Credit Card | J6: 1327.8846 | K6: =TEXT(B6,"dd-mm-yyyy") -> 13-06-2024 | L6: =TEXT(Sales_Fact!$B6,"mmm") -> Jun | M6: =IF(ISBLANK(F6),1,F6) -> 2 | N6: =ROUNDUP(IF(ISBLANK(G6),AVERAGE(C:C,G6,G:G),G6),2) -> 909.51 | O6: =M6*N6*(1-H6) -> 1327.8846 | P6: =M6*N6 -> 1819.02 | Q6: =(P6-O6)/P6 -> 0.27 | R6: =IF(Sales_Fact!$O6>1000,"High","Low") -> High | S6: =VLOOKUP(C6,Customer_Dim!$A:$N,9,FALSE()) -> Christopher Stewart | T6: =VLOOKUP(D6,Product_Dim!$A:$M,3,FALSE()) -> Beauty | U6: =VLOOKUP(D6,Product_Dim!$A:$M,2,FALSE()) -> Men's Hair Styling Gel | V6: =VLOOKUP(E6,Store_Dim!$A:$E,3,FALSE()) -> South | W6: =VLOOKUP(C6,Customer_Dim!$A:$N,13,FALSE()) -> Bronze | X6: =IF(F6>3,"High","Low") -> Low
A7: SALE1001 | B7: 45776 | C7: CUST1052 | D7: PROD69 | E7: STORE14 | F7: 4 | G7: 593.84 | H7: 0.24 | I7: PayPal | J7: 1805.2736 | K7: =TEXT(B7,"dd-mm-yyyy") -> 29-04-2025 | L7: =TEXT(Sales_Fact!$B7,"mmm") -> Apr | M7: =IF(ISBLANK(F7),1,F7) -> 4 | N7: =ROUNDUP(IF(ISBLANK(G7),AVERAGE(C:C,G7,G:G),G7),2) -> 593.84 | O7: =M7*N7*(1-H7) -> 1805.2736 | P7: =M7*N7 -> 2375.36 | Q7: =(P7-O7)/P7 -> 0.24 | R7: =IF(Sales_Fact!$O7>1000,"High","Low") -> High | S7: =VLOOKUP(C7,Customer_Dim!$A:$N,9,FALSE()) -> Debra Liu | T7: =VLOOKUP(D7,Product_Dim!$A:$M,3,FALSE()) -> Clothing | U7: =VLOOKUP(D7,Product_Dim!$A:$M,2,FALSE()) -> Men's Sports Shorts | V7: =VLOOKUP(E7,Store_Dim!$A:$E,3,FALSE()) -> South | W7: =VLOOKUP(C7,Customer_Dim!$A:$N,13,FALSE()) -> Bronze | X7: =IF(F7>3,"High","Low") -> High
A8: SALE1002 | B8: 45566 | C8: CUST1109 | D8: PROD73 | E8: STORE10 | F8: 3 | G8: 909.11 | H8: 0.23 | I8: COD | J8: 2100.0441 | K8: =TEXT(B8,"dd-mm-yyyy") -> 01-10-2024 | L8: =TEXT(Sales_Fact!$B8,"mmm") -> Oct | M8: =IF(ISBLANK(F8),1,F8) -> 3 | N8: =ROUNDUP(IF(ISBLANK(G8),AVERAGE(C:C,G8,G:G),G8),2) -> 909.11 | O8: =M8*N8*(1-H8) -> 2100.0441 | P8: =M8*N8 -> 2727.33 | Q8: =(P8-O8)/P8 -> 0.23 | R8: =IF(Sales_Fact!$O8>1000,"High","Low") -> High | S8: =VLOOKUP(C8,Customer_Dim!$A:$N,9,FALSE()) -> Amy Walker | T8: =VLOOKUP(D8,Product_Dim!$A:$M,3,FALSE()) -> Sports | U8: =VLOOKUP(D8,Product_Dim!$A:$M,2,FALSE()) -> Shin Guards – Adult | V8: =VLOOKUP(E8,Store_Dim!$A:$E,3,FALSE()) -> East | W8: =VLOOKUP(C8,Customer_Dim!$A:$N,13,FALSE()) -> Silver | X8: =IF(F8>3,"High","Low") -> Low
A9: SALE1003 | B9: 45542 | C9: CUST1399 | D9: PROD24 | E9: STORE1 | F9: 4 | G9: 996.85 | H9: 0.24 | I9: PayPal | J9: 3030.424 | K9: =TEXT(B9,"dd-mm-yyyy") -> 07-09-2024 | L9: =TEXT(Sales_Fact!$B9,"mmm") -> Sep | M9: =IF(ISBLANK(F9),1,F9) -> 4 | N9: =ROUNDUP(IF(ISBLANK(G9),AVERAGE(C:C,G9,G:G),G9),2) -> 996.85 | O9: =M9*N9*(1-H9) -> 3030.424 | P9: =M9*N9 -> 3987.4 | Q9: =(P9-O9)/P9 -> 0.24 | R9: =IF(Sales_Fact!$O9>1000,"High","Low") -> High | S9: =VLOOKUP(C9,Customer_Dim!$A:$N,9,FALSE()) -> John Donaldson | T9: =VLOOKUP(D9,Product_Dim!$A:$M,3,FALSE()) -> Sports | U9: =VLOOKUP(D9,Product_Dim!$A:$M,2,FALSE()) -> Foldable Camping Chair | V9: =VLOOKUP(E9,Store_Dim!$A:$E,3,FALSE()) -> North | W9: =VLOOKUP(C9,Customer_Dim!$A:$N,13,FALSE()) -> Bronze | X9: =IF(F9>3,"High","Low") -> High
A10: SALE1004 | B10: 45834 | C10: CUST1300 | D10: PROD0 | E10: STORE17 | F10: 1 | G10: 522.69 | H10: 0.06 | I10: COD | J10: 491.3286 | K10: =TEXT(B10,"dd-mm-yyyy") -> 26-06-2025 | L10: =TEXT(Sales_Fact!$B10,"mmm") -> Jun | M10: =IF(ISBLANK(F10),1,F10) -> 1 | N10: =ROUNDUP(IF(ISBLANK(G10),AVERAGE(C:C,G10,G:G),G10),2) -> 522.69 | O10: =M10*N10*(1-H10) -> 491.3286 | P10: =M10*N10 -> 522.69 | Q10: =(P10-O10)/P10 -> 0.06 | R10: =IF(Sales_Fact!$O10>1000,"High","Low") -> Low | S10: =VLOOKUP(C10,Customer_Dim!$A:$N,9,FALSE()) -> Matthew Avery | T10: =VLOOKUP(D10,Product_Dim!$A:$M,3,FALSE()) -> Electronics | U10: =VLOOKUP(D10,Product_Dim!$A:$M,2,FALSE()) -> Brother Laser Printer | V10: =VLOOKUP(E10,Store_Dim!$A:$E,3,FALSE()) -> North | W10: =VLOOKUP(C10,Customer_Dim!$A:$N,13,FALSE()) -> Silver | X10: =IF(F10>3,"High","Low") -> Low
A11: SALE1005 | B11: 45405 | C11: CUST1194 | D11: PROD54 | E11: STORE3 | F11: 3 | G11: 261.05 | H11: 0.12 | I11: PayPal | J11: 689.172 | K11: =TEXT(B11,"dd-mm-yyyy") -> 23-04-2024 | L11: =TEXT(Sales_Fact!$B11,"mmm") -> Apr | M11: =IF(ISBLANK(F11),1,F11) -> 3 | N11: =ROUNDUP(IF(ISBLANK(G11),AVERAGE(C:C,G11,G:G),G11),2) -> 261.05 | O11: =M11*N11*(1-H11) -> 689.172 | P11: =M11*N11 -> 783.15 | Q11: =(P11-O11)/P11 -> 0.12 | R11: =IF(Sales_Fact!$O11>1000,"High","Low") -> Low | S11: =VLOOKUP(C11,Customer_Dim!$A:$N,9,FALSE()) -> Ashley Ferguson | T11: =VLOOKUP(D11,Product_Dim!$A:$M,3,FALSE()) -> Sports | U11: =VLOOKUP(D11,Product_Dim!$A:$M,2,FALSE()) -> Sports Stopwatch Pro | V11: =VLOOKUP(E11,Store_Dim!$A:$E,3,FALSE()) -> North | W11: =VLOOKUP(C11,Customer_Dim!$A:$N,13,FALSE()) -> Gold | X11: =IF(F11>3,"High","Low") -> Low
A12: SALE1006 | B12: 45918 | C12: CUST1087 | D12: PROD23 | E12: STORE17 | F12: 3 | G12: 644.73 | H12: 0.01 | I12: COD | J12: 1914.8481 | K12: =TEXT(B12,"dd-mm-yyyy") -> 18-09-2025 | L12: =TEXT(Sales_Fact!$B12,"mmm") -> Sep | M12: =IF(ISBLANK(F12),1,F12) -> 3 | N12: =ROUNDUP(IF(ISBLANK(G12),AVERAGE(C:C,G12,G:G),G12),2) -> 644.73 | O12: =M12*N12*(1-H12) -> 1914.8481 | P12: =M12*N12 -> 1934.19 | Q12: =(P12-O12)/P12 -> 0.01 | R12: =IF(Sales_Fact!$O12>1000,"High","Low") -> High | S12: =VLOOKUP(C12,Customer_Dim!$A:$N,9,FALSE()) -> Melissa Duffy Md | T12: =VLOOKUP(D12,Product_Dim!$A:$M,3,FALSE()) -> Clothing | U12: =VLOOKUP(D12,Product_Dim!$A:$M,2,FALSE()) -> Men's Formal Shirt | V12: =VLOOKUP(E12,Store_Dim!$A:$E,3,FALSE()) -> North | W12: =VLOOKUP(C12,Customer_Dim!$A:$N,13,FALSE()) -> Bronze | X12: =IF(F12>3,"High","Low") -> Low
A13: SALE1007 | B13: 45217 | C13: CUST1198 | D13: PROD75 | E13: STORE2 | F13: 2 | G13: 541.52 | H13: 0.26 | I13: PayPal | J13: 801.4496 | K13: =TEXT(B13,"dd-mm-yyyy") -> 18-10-2023 | L13: =TEXT(Sales_Fact!$B13,"mmm") -> Oct | M13: =IF(ISBLANK(F13),1,F13) -> 2 | N13: =ROUNDUP(IF(ISBLANK(G13),AVERAGE(C:C,G13,G:G),G13),2) -> 541.52 | O13: =M13*N13*(1-H13) -> 801.4496 | P13: =M13*N13 -> 1083.04 | Q13: =(P13-O13)/P13 -> 0.26 | R13: =IF(Sales_Fact!$O13>1000,"High","Low") -> Low | S13: =VLOOKUP(C13,Customer_Dim!$A:$N,9,FALSE()) -> Wanda Snyder | T13: =VLOOKUP(D13,Product_Dim!$A:$M,3,FALSE()) -> Clothing | U13: =VLOOKUP(D13,Product_Dim!$A:$M,2,FALSE()) -> Women's Ankle Boots | V13: =VLOOKUP(E13,Store_Dim!$A:$E,3,FALSE()) -> South | W13: =VLOOKUP(C13,Customer_Dim!$A:$N,13,FALSE()) -> Bronze | X13: =IF(F13>3,"High","Low") -> Low
... A558: SALE1499 | B558: 45590 | C558: CUST1464 | D558: PROD41 | E558: STORE12 | F558: 2 | G558: 581.19 | H558: 0.07 | I558: COD | J558: 1081.0134 | K558: =TEXT(B558,"dd-mm-yyyy") -> 25-10-2024 | L558: =TEXT(Sales_Fact!$B558,"mmm") -> Oct | M558: =IF(ISBLANK(F558),1,F558) -> 2 | N558: =ROUNDUP(IF(ISBLANK(G558),AVERAGE(C:C,G558,G:G),G558),2) -> 581.19 | O558: =M558*N558*(1-H558) -> 1081.0134 | P558: =M558*N558 -> 1162.38 | Q558: =(P558-O558)/P558 -> 0.07 | R558: =IF(Sales_Fact!$O558>1000,"High","Low") -> High | S558: =VLOOKUP(C558,Customer_Dim!$A:$N,9,FALSE()) -> David Pierce | T558: =VLOOKUP(D558,Product_Dim!$A:$M,3,FALSE()) -> Sports | U558: =VLOOKUP(D558,Product_Dim!$A:$M,2,FALSE()) -> Yoga Exercise Mat | V558: =VLOOKUP(E558,Store_Dim!$A:$E,3,FALSE()) -> North | W558: =VLOOKUP(C558,Customer_Dim!$A:$N,13,FALSE()) -> Platinum | X558: =IF(F558>3,"High","Low") -> Low
A559: SALE15 | B559: 45636 | C559: CUST1435 | D559: PROD36 | E559: STORE9 | G559: 871.34 | H559: 0.04 | I559: COD | J559: 2509.4592 | K559: =TEXT(B559,"dd-mm-yyyy") -> 10-12-2024 | L559: =TEXT(Sales_Fact!$B559,"mmm") -> Dec | M559: =IF(ISBLANK(F559),1,F559) -> 1 | N559: =ROUNDUP(IF(ISBLANK(G559),AVERAGE(C:C,G559,G:G),G559),2) -> 871.34 | O559: =M559*N559*(1-H559) -> 836.4864 | P559: =M559*N559 -> 871.34 | Q559: =(P559-O559)/P559 -> 0.04 | R559: =IF(Sales_Fact!$O559>1000,"High","Low") -> Low | S559: =VLOOKUP(C559,Customer_Dim!$A:$N,9,FALSE()) -> Lindsay Beasley | T559: =VLOOKUP(D559,Product_Dim!$A:$M,3,FALSE()) -> Clothing | U559: =VLOOKUP(D559,Product_Dim!$A:$M,2,FALSE()) -> Women's Summer Dress | V559: =VLOOKUP(E559,Store_Dim!$A:$E,3,FALSE()) -> South | W559: =VLOOKUP(C559,Customer_Dim!$A:$N,13,FALSE()) -> Silver | X559: =IF(F559>3,"High","Low") -> Low
A560: SALE150 | B560: 45433 | C560: CUST1068 | D560: PROD52 | E560: STORE5 | F560: 4 | G560: 355.64 | H560: 0.16 | I560: COD | J560: 1194.9504 | K560: =TEXT(B560,"dd-mm-yyyy") -> 21-05-2024 | L560: =TEXT(Sales_Fact!$B560,"mmm") -> May | M560: =IF(ISBLANK(F560),1,F560) -> 4 | N560: =ROUNDUP(IF(ISBLANK(G560),AVERAGE(C:C,G560,G:G),G560),2) -> 355.64 | O560: =M560*N560*(1-H560) -> 1194.9504 | P560: =M560*N560 -> 1422.56 | Q560: =(P560-O560)/P560 -> 0.16 | R560: =IF(Sales_Fact!$O560>1000,"High","Low") -> High | S560: =VLOOKUP(C560,Customer_Dim!$A:$N,9,FALSE()) -> Mr. Mark Beasley | T560: =VLOOKUP(D560,Product_Dim!$A:$M,3,FALSE()) -> Sports | U560: =VLOOKUP(D560,Product_Dim!$A:$M,2,FALSE()) -> Rugby Ball | V560: =VLOOKUP(E560,Store_Dim!$A:$E,3,FALSE()) -> North | W560: =VLOOKUP(C560,Customer_Dim!$A:$N,13,FALSE()) -> Silver | X560: =IF(F560>3,"High","Low") -> High
A561: SALE1500 | B561: 45618 | C561: CUST1112 | D561: PROD99 | E561: STORE11 | F561: 1 | G561: 736.54 | H561: 0.16 | I561: PayPal | J561: 618.6936 | K561: =TEXT(B561,"dd-mm-yyyy") -> 22-11-2024 | L561: =TEXT(Sales_Fact!$B561,"mmm") -> Nov | M561: =IF(ISBLANK(F561),1,F561) -> 1 | N561: =ROUNDUP(IF(ISBLANK(G561),AVERAGE(C:C,G561,G:G),G561),2) -> 736.54 | O561: =M561*N561*(1-H561) -> 618.6936 | P561: =M561*N561 -> 736.54 | Q561: =(P561-O561)/P561 -> 0.16 | R561: =IF(Sales_Fact!$O561>1000,"High","Low") -> Low | S561: =VLOOKUP(C561,Customer_Dim!$A:$N,9,FALSE()) -> David Cole | T561: =VLOOKUP(D561,Product_Dim!$A:$M,3,FALSE()) -> Home | U561: =VLOOKUP(D561,Product_Dim!$A:$M,2,FALSE()) -> Stainless Steel Cookware Set | V561: =VLOOKUP(E561,Store_Dim!$A:$E,3,FALSE()) -> South | W561: =VLOOKUP(C561,Customer_Dim!$A:$N,13,FALSE()) -> Silver | X561: =IF(F561>3,"High","Low") -> Low
A562: SALE1501 | B562: 45586 | C562: CUST1401 | D562: PROD65 | E562: STORE15 | F562: 1 | G562: 524 | H562: 0.28 | I562: Credit Card | J562: 377.28 | K562: =TEXT(B562,"dd-mm-yyyy") -> 21-10-2024 | L562: =TEXT(Sales_Fact!$B562,"mmm") -> Oct | M562: =IF(ISBLANK(F562),1,F562) -> 1 | N562: =ROUNDUP(IF(ISBLANK(G562),AVERAGE(C:C,G562,G:G),G562),2) -> 524 | O562: =M562*N562*(1-H562) -> 377.28 | P562: =M562*N562 -> 524 | Q562: =(P562-O562)/P562 -> 0.28 | R562: =IF(Sales_Fact!$O562>1000,"High","Low") -> Low | S562: =VLOOKUP(C562,Customer_Dim!$A:$N,9,FALSE()) -> Terry Moses | T562: =VLOOKUP(D562,Product_Dim!$A:$M,3,FALSE()) -> Sports | U562: =VLOOKUP(D562,Product_Dim!$A:$M,2,FALSE()) -> Adjustable Dumbbells 20kg | V562: =VLOOKUP(E562,Store_Dim!$A:$E,3,FALSE()) -> North | W562: =VLOOKUP(C562,Customer_Dim!$A:$N,13,FALSE()) -> Platinum | X562: =IF(F562>3,"High","Low") -> Low
A563: SALE1502 | B563: 45548 | C563: CUST1046 | D563: PROD28 | E563: STORE3 | F563: 4 | G563: 566.09 | H563: 0.28 | I563: COD | J563: 1630.3392 | K563: =TEXT(B563,"dd-mm-yyyy") -> 13-09-2024 | L563: =TEXT(Sales_Fact!$B563,"mmm") -> Sep | M563: =IF(ISBLANK(F563),1,F563) -> 4 | N563: =ROUNDUP(IF(ISBLANK(G563),AVERAGE(C:C,G563,G:G),G563),2) -> 566.09 | O563: =M563*N563*(1-H563) -> 1630.3392 | P563: =M563*N563 -> 2264.36 | Q563: =(P563-O563)/P563 -> 0.28 | R563: =IF(Sales_Fact!$O563>1000,"High","Low") -> High | S563: =VLOOKUP(C563,Customer_Dim!$A:$N,9,FALSE()) -> Michelle Garcia Dds | T563: =VLOOKUP(D563,Product_Dim!$A:$M,3,FALSE()) -> Sports | U563: =VLOOKUP(D563,Product_Dim!$A:$M,2,FALSE()) -> Sports Stopwatch Timer | V563: =VLOOKUP(E563,Store_Dim!$A:$E,3,FALSE()) -> North | W563: =VLOOKUP(C563,Customer_Dim!$A:$N,13,FALSE()) -> Platinum | X563: =IF(F563>3,"High","Low") -> High
A564: SALE1503 | B564: 45772 | C564: CUST1259 | D564: PROD21 | E564: STORE10 | F564: 1 | G564: 251.99 | H564: 0.09 | I564: Credit Card | J564: 229.3109 | K564: =TEXT(B564,"dd-mm-yyyy") -> 25-04-2025 | L564: =TEXT(Sales_Fact!$B564,"mmm") -> Apr | M564: =IF(ISBLANK(F564),1,F564) -> 1 | N564: =ROUNDUP(IF(ISBLANK(G564),AVERAGE(C:C,G564,G:G),G564),2) -> 251.99 | O564: =M564*N564*(1-H564) -> 229.3109 | P564: =M564*N564 -> 251.99 | Q564: =(P564-O564)/P564 -> 0.09 | R564: =IF(Sales_Fact!$O564>1000,"High","Low") -> Low | S564: =VLOOKUP(C564,Customer_Dim!$A:$N,9,FALSE()) -> Beth Allen | T564: =VLOOKUP(D564,Product_Dim!$A:$M,3,FALSE()) -> Home | U564: =VLOOKUP(D564,Product_Dim!$A:$M,2,FALSE()) -> Multi-Purpose Storage Box | V564: =VLOOKUP(E564,Store_Dim!$A:$E,3,FALSE()) -> East | W564: =VLOOKUP(C564,Customer_Dim!$A:$N,13,FALSE()) -> Silver | X564: =IF(F564>3,"High","Low") -> Low
A565: SALE1504 | B565: 45361 | C565: CUST1221 | D565: PROD17 | E565: STORE19 | F565: 1 | G565: 259.2 | H565: 0.27 | I565: COD | J565: 189.216 | K565: =TEXT(B565,"dd-mm-yyyy") -> 10-03-2024 | L565: =TEXT(Sales_Fact!$B565,"mmm") -> Mar | M565: =IF(ISBLANK(F565),1,F565) -> 1 | N565: =ROUNDUP(IF(ISBLANK(G565),AVERAGE(C:C,G565,G:G),G565),2) -> 259.2 | O565: =M565*N565*(1-H565) -> 189.216 | P565: =M565*N565 -> 259.2 | Q565: =(P565-O565)/P565 -> 0.27 | R565: =IF(Sales_Fact!$O565>1000,"High","Low") -> Low | S565: =VLOOKUP(C565,Customer_Dim!$A:$N,9,FALSE()) -> Lisa Young | T565: =VLOOKUP(D565,Product_Dim!$A:$M,3,FALSE()) -> Sports | U565: =VLOOKUP(D565,Product_Dim!$A:$M,2,FALSE()) -> Soccer Training Cone Set | V565: =VLOOKUP(E565,Store_Dim!$A:$E,3,FALSE()) -> East | W565: =VLOOKUP(C565,Customer_Dim!$A:$N,13,FALSE()) -> Platinum | X565: =IF(F565>3,"High","Low") -> Low
A566: SALE1505 | B566: 45235 | C566: CUST1446 | D566: PROD59 | E566: STORE15 | F566: 1 | G566: 935.66 | H566: 0.26 | I566: PayPal | J566: 692.3884 | K566: =TEXT(B566,"dd-mm-yyyy") -> 05-11-2023 | L566: =TEXT(Sales_Fact!$B566,"mmm") -> Nov | M566: =IF(ISBLANK(F566),1,F566) -> 1 | N566: =ROUNDUP(IF(ISBLANK(G566),AVERAGE(C:C,G566,G:G),G566),2) -> 935.66 | O566: =M566*N566*(1-H566) -> 692.3884 | P566: =M566*N566 -> 935.66 | Q566: =(P566-O566)/P566 -> 0.26 | R566: =IF(Sales_Fact!$O566>1000,"High","Low") -> Low | S566: =VLOOKUP(C566,Customer_Dim!$A:$N,9,FALSE()) -> Shannon Turner | T566: =VLOOKUP(D566,Product_Dim!$A:$M,3,FALSE()) -> Beauty | U566: =VLOOKUP(D566,Product_Dim!$A:$M,2,FALSE()) -> Men's Hair Styling Gel | V566: =VLOOKUP(E566,Store_Dim!$A:$E,3,FALSE()) -> North | W566: =VLOOKUP(C566,Customer_Dim!$A:$N,13,FALSE()) -> Silver | X566: =IF(F566>3,"High","Low") -> Low
A567: SALE1506 | B567: 45864 | C567: CUST1469 | D567: PROD35 | E567: STORE8 | F567: 4 | G567: 480.75 | H567: 0.02 | I567: Credit Card | J567: 1884.54 | K567: =TEXT(B567,"dd-mm-yyyy") -> 26-07-2025 | L567: =TEXT(Sales_Fact!$B567,"mmm") -> Jul | M567: =IF(ISBLANK(F567),1,F567) -> 4 | N567: =ROUNDUP(IF(ISBLANK(G567),AVERAGE(C:C,G567,G:G),G567),2) -> 480.75 | O567: =M567*N567*(1-H567) -> 1884.54 | P567: =M567*N567 -> 1923 | Q567: =(P567-O567)/P567 -> 0.02 | R567: =IF(Sales_Fact!$O567>1000,"High","Low") -> High | S567: =VLOOKUP(C567,Customer_Dim!$A:$N,9,FALSE()) -> James Foster | T567: =VLOOKUP(D567,Product_Dim!$A:$M,3,FALSE()) -> Home | U567: =VLOOKUP(D567,Product_Dim!$A:$M,2,FALSE()) -> Bedroom Table Lamp | V567: =VLOOKUP(E567,Store_Dim!$A:$E,3,FALSE()) -> West | W567: =VLOOKUP(C567,Customer_Dim!$A:$N,13,FALSE()) -> Gold | X567: =IF(F567>3,"High","Low") -> High
A568: SALE1507 | B568: 45681 | C568: CUST1369 | D568: PROD81 | E568: STORE15 | F568: 2 | G568: 457.83 | H568: 0.01 | I568: COD | J568: 906.5034 | K568: =TEXT(B568,"dd-mm-yyyy") -> 24-01-2025 | L568: =TEXT(Sales_Fact!$B568,"mmm") -> Jan | M568: =IF(ISBLANK(F568),1,F568) -> 2 | N568: =ROUNDUP(IF(ISBLANK(G568),AVERAGE(C:C,G568,G:G),G568),2) -> 457.83 | O568: =M568*N568*(1-H568) -> 906.5034 | P568: =M568*N568 -> 915.66 | Q568: =(P568-O568)/P568 -> 0.01 | R568: =IF(Sales_Fact!$O568>1000,"High","Low") -> Low | S568: =VLOOKUP(C568,Customer_Dim!$A:$N,9,FALSE()) -> Gregory Allen | T568: =VLOOKUP(D568,Product_Dim!$A:$M,3,FALSE()) -> Sports | U568: =VLOOKUP(D568,Product_Dim!$A:$M,2,FALSE()) -> Badminton Racket Set | V568: =VLOOKUP(E568,Store_Dim!$A:$E,3,FALSE()) -> North | W568: =VLOOKUP(C568,Customer_Dim!$A:$N,13,FALSE()) -> Platinum | X568: =IF(F568>3,"High","Low") -> Low
A569: SALE1508 | B569: 45905 | C569: CUST1164 | D569: PROD48 | E569: STORE14 | F569: 1 | G569: 994.63 | H569: 0.28 | I569: Credit Card | J569: 716.1336 | K569: =TEXT(B569,"dd-mm-yyyy") -> 05-09-2025 | L569: =TEXT(Sales_Fact!$B569,"mmm") -> Sep | M569: =IF(ISBLANK(F569),1,F569) -> 1 | N569: =ROUNDUP(IF(ISBLANK(G569),AVERAGE(C:C,G569,G:G),G569),2) -> 994.63 | O569: =M569*N569*(1-H569) -> 716.1336 | P569: =M569*N569 -> 994.63 | Q569: =(P569-O569)/P569 -> 0.28 | R569: =IF(Sales_Fact!$O569>1000,"High","Low") -> Low | S569: =VLOOKUP(C569,Customer_Dim!$A:$N,9,FALSE()) -> Daniel Rivas | T569: =VLOOKUP(D569,Product_Dim!$A:$M,3,FALSE()) -> Electronics | U569: =VLOOKUP(D569,Product_Dim!$A:$M,2,FALSE()) -> Car Dashboard Phone Holder | V569: =VLOOKUP(E569,Store_Dim!$A:$E,3,FALSE()) -> South | W569: =VLOOKUP(C569,Customer_Dim!$A:$N,13,FALSE()) -> Silver | X569: =IF(F569>3,"High","Low") -> Low
A570: SALE1509 | B570: 45765 | C570: CUST1245 | D570: PROD90 | E570: STORE0 | F570: 3 | G570: 65.57 | H570: 0.3 | I570: COD | J570: 137.697 | K570: =TEXT(B570,"dd-mm-yyyy") -> 18-04-2025 | L570: =TEXT(Sales_Fact!$B570,"mmm") -> Apr | M570: =IF(ISBLANK(F570),1,F570) -> 3 | N570: =ROUNDUP(IF(ISBLANK(G570),AVERAGE(C:C,G570,G:G),G570),2) -> 65.57 | O570: =M570*N570*(1-H570) -> 137.697 | P570: =M570*N570 -> 196.71 | Q570: =(P570-O570)/P570 -> 0.3 | R570: =IF(Sales_Fact!$O570>1000,"High","Low") -> Low | S570: =VLOOKUP(C570,Customer_Dim!$A:$N,9,FALSE()) -> Laura Soto | T570: =VLOOKUP(D570,Product_Dim!$A:$M,3,FALSE()) -> Electronics | U570: =VLOOKUP(D570,Product_Dim!$A:$M,2,FALSE()) -> Gaming Mouse Pad XL | V570: =VLOOKUP(E570,Store_Dim!$A:$E,3,FALSE()) -> East | W570: =VLOOKUP(C570,Customer_Dim!$A:$N,13,FALSE()) -> Platinum | X570: =IF(F570>3,"High","Low") -> Low
A571: SALE151 | B571: 45594 | C571: CUST1022 | D571: PROD13 | E571: STORE8 | F571: 4 | G571: 535.4 | H571: 0.26 | I571: PayPal | J571: 1584.784 | K571: =TEXT(B571,"dd-mm-yyyy") -> 29-10-2024 | L571: =TEXT(Sales_Fact!$B571,"mmm") -> Oct | M571: =IF(ISBLANK(F571),1,F571) -> 4 | N571: =ROUNDUP(IF(ISBLANK(G571),AVERAGE(C:C,G571,G:G),G571),2) -> 535.4 | O571: =M571*N571*(1-H571) -> 1584.784 | P571: =M571*N571 -> 2141.6 | Q571: =(P571-O571)/P571 -> 0.26 | R571: =IF(Sales_Fact!$O571>1000,"High","Low") -> High | S571: =VLOOKUP(C571,Customer_Dim!$A:$N,9,FALSE()) -> Paul Fox | T571: =VLOOKUP(D571,Product_Dim!$A:$M,3,FALSE()) -> Electronics | U571: =VLOOKUP(D571,Product_Dim!$A:$M,2,FALSE()) -> USB-C Fast Charger | V571: =VLOOKUP(E571,Store_Dim!$A:$E,3,FALSE()) -> West | W571: =VLOOKUP(C571,Customer_Dim!$A:$N,13,FALSE()) -> Silver | X571: =IF(F571>3,"High","Low") -> High
... A1002: SALE1899 | B1002: 45525 | C1002: CUST1062 | D1002: PROD78 | E1002: STORE12 | F1002: 1 | G1002: 984.37 | H1002: 0 | I1002: PayPal | J1002: 984.37 | K1002: =TEXT(B1002,"dd-mm-yyyy") -> 21-08-2024 | L1002: =TEXT(Sales_Fact!$B1002,"mmm") -> Aug | M1002: =IF(ISBLANK(F1002),1,F1002) -> 1 | N1002: =ROUNDUP(IF(ISBLANK(G1002),AVERAGE(C:C,G1002,G:G),G1002),2) -> 984.37 | O1002: =M1002*N1002*(1-H1002) -> 984.37 | P1002: =M1002*N1002 -> 984.37 | Q1002: =(P1002-O1002)/P1002 -> 0 | R1002: =IF(Sales_Fact!$O1002>1000,"High","Low") -> Low | S1002: =VLOOKUP(C1002,Customer_Dim!$A:$N,9,FALSE()) -> James Bean | T1002: =VLOOKUP(D1002,Product_Dim!$A:$M,3,FALSE()) -> Home | U1002: =VLOOKUP(D1002,Product_Dim!$A:$M,2,FALSE()) -> Essential Oil Diffuser | V1002: =VLOOKUP(E1002,Store_Dim!$A:$E,3,FALSE()) -> North | W1002: =VLOOKUP(C1002,Customer_Dim!$A:$N,13,FALSE()) -> Bronze | X1002: =IF(F1002>3,"High","Low") -> Low
A1003: SALE19 | B1003: 45369 | C1003: CUST1239 | D1003: PROD60 | E1003: STORE13 | F1003: 4 | H1003: 0.04 | I1003: COD | J1003: 1782.4512 | K1003: =TEXT(B1003,"dd-mm-yyyy") -> 18-03-2024 | L1003: =TEXT(Sales_Fact!$B1003,"mmm") -> Mar | M1003: =IF(ISBLANK(F1003),1,F1003) -> 4 | N1003: =ROUNDUP(IF(ISBLANK(G1003),AVERAGE(C:C,G1003,G:G),G1003),2) -> 513.99 | O1003: =M1003*N1003*(1-H1003) -> 1973.7216 | P1003: =M1003*N1003 -> 2055.96 | Q1003: =(P1003-O1003)/P1003 -> 0.04 | R1003: =IF(Sales_Fact!$O1003>1000,"High","Low") -> High | S1003: =VLOOKUP(C1003,Customer_Dim!$A:$N,9,FALSE()) -> Maria Hill | T1003: =VLOOKUP(D1003,Product_Dim!$A:$M,3,FALSE()) -> Beauty | U1003: =VLOOKUP(D1003,Product_Dim!$A:$M,2,FALSE()) -> Luxury Perfume Spray | V1003: =VLOOKUP(E1003,Store_Dim!$A:$E,3,FALSE()) -> East | W1003: =VLOOKUP(C1003,Customer_Dim!$A:$N,13,FALSE()) -> Platinum | X1003: =IF(F1003>3,"High","Low") -> High
A1004: SALE190 | B1004: 45775 | C1004: CUST1334 | D1004: PROD71 | E1004: STORE9 | F1004: 3 | G1004: 444.55 | H1004: 0.14 | I1004: PayPal | J1004: 1146.939 | K1004: =TEXT(B1004,"dd-mm-yyyy") -> 28-04-2025 | L1004: =TEXT(Sales_Fact!$B1004,"mmm") -> Apr | M1004: =IF(ISBLANK(F1004),1,F1004) -> 3 | N1004: =ROUNDUP(IF(ISBLANK(G1004),AVERAGE(C:C,G1004,G:G),G1004),2) -> 444.55 | O1004: =M1004*N1004*(1-H1004) -> 1146.939 | P1004: =M1004*N1004 -> 1333.65 | Q1004: =(P1004-O1004)/P1004 -> 0.14 | R1004: =IF(Sales_Fact!$O1004>1000,"High","Low") -> High | S1004: =VLOOKUP(C1004,Customer_Dim!$A:$N,9,FALSE()) -> Mr. Christopher Sims | T1004: =VLOOKUP(D1004,Product_Dim!$A:$M,3,FALSE()) -> Beauty | U1004: =VLOOKUP(D1004,Product_Dim!$A:$M,2,FALSE()) -> Hair Repair Oil Treatment | V1004: =VLOOKUP(E1004,Store_Dim!$A:$E,3,FALSE()) -> South | W1004: =VLOOKUP(C1004,Customer_Dim!$A:$N,13,FALSE()) -> Silver | X1004: =IF(F1004>3,"High","Low") -> Low
A1005: SALE1900 | B1005: 45329 | C1005: CUST1292 | D1005: PROD1 | E1005: STORE12 | F1005: 2 | G1005: 237.59 | H1005: 0.12 | I1005: Credit Card | J1005: 418.1584 | K1005: =TEXT(B1005,"dd-mm-yyyy") -> 07-02-2024 | L1005: =TEXT(Sales_Fact!$B1005,"mmm") -> Feb | M1005: =IF(ISBLANK(F1005),1,F1005) -> 2 | N1005: =ROUNDUP(IF(ISBLANK(G1005),AVERAGE(C:C,G1005,G:G),G1005),2) -> 237.59 | O1005: =M1005*N1005*(1-H1005) -> 418.1584 | P1005: =M1005*N1005 -> 475.18 | Q1005: =(P1005-O1005)/P1005 -> 0.12 | R1005: =IF(Sales_Fact!$O1005>1000,"High","Low") -> Low | S1005: =VLOOKUP(C1005,Customer_Dim!$A:$N,9,FALSE()) -> Ricardo Jones | T1005: =VLOOKUP(D1005,Product_Dim!$A:$M,3,FALSE()) -> Clothing | U1005: =VLOOKUP(D1005,Product_Dim!$A:$M,2,FALSE()) -> Men's Graphic T-Shirt | V1005: =VLOOKUP(E1005,Store_Dim!$A:$E,3,FALSE()) -> North | W1005: =VLOOKUP(C1005,Customer_Dim!$A:$N,13,FALSE()) -> Silver | X1005: =IF(F1005>3,"High","Low") -> Low
A1006: SALE1901 | B1006: 45250 | C1006: CUST1431 | D1006: PROD25 | E1006: STORE8 | F1006: 1 | G1006: 52.06 | H1006: 0.27 | I1006: COD | J1006: 38.0038 | K1006: =TEXT(B1006,"dd-mm-yyyy") -> 20-11-2023 | L1006: =TEXT(Sales_Fact!$B1006,"mmm") -> Nov | M1006: =IF(ISBLANK(F1006),1,F1006) -> 1 | N1006: =ROUNDUP(IF(ISBLANK(G1006),AVERAGE(C:C,G1006,G:G),G1006),2) -> 52.06 | O1006: =M1006*N1006*(1-H1006) -> 38.0038 | P1006: =M1006*N1006 -> 52.06 | Q1006: =(P1006-O1006)/P1006 -> 0.27 | R1006: =IF(Sales_Fact!$O1006>1000,"High","Low") -> Low | S1006: =VLOOKUP(C1006,Customer_Dim!$A:$N,9,FALSE()) -> John Smith | T1006: =VLOOKUP(D1006,Product_Dim!$A:$M,3,FALSE()) -> Clothing | U1006: =VLOOKUP(D1006,Product_Dim!$A:$M,2,FALSE()) -> Women's Scarf Set | V1006: =VLOOKUP(E1006,Store_Dim!$A:$E,3,FALSE()) -> West | W1006: =VLOOKUP(C1006,Customer_Dim!$A:$N,13,FALSE()) -> Platinum | X1006: =IF(F1006>3,"High","Low") -> Low
A1007: SALE1902 | B1007: 45691 | C1007: CUST1455 | D1007: PROD3 | E1007: STORE1 | F1007: 2 | G1007: 594.63 | H1007: 0.12 | I1007: Credit Card | J1007: 1046.5488 | K1007: =TEXT(B1007,"dd-mm-yyyy") -> 03-02-2025 | L1007: =TEXT(Sales_Fact!$B1007,"mmm") -> Feb | M1007: =IF(ISBLANK(F1007),1,F1007) -> 2 | N1007: =ROUNDUP(IF(ISBLANK(G1007),AVERAGE(C:C,G1007,G:G),G1007),2) -> 594.63 | O1007: =M1007*N1007*(1-H1007) -> 1046.5488 | P1007: =M1007*N1007 -> 1189.26 | Q1007: =(P1007-O1007)/P1007 -> 0.12 | R1007: =IF(Sales_Fact!$O1007>1000,"High","Low") -> High | S1007: =VLOOKUP(C1007,Customer_Dim!$A:$N,9,FALSE()) -> Tyler Weber | T1007: =VLOOKUP(D1007,Product_Dim!$A:$M,3,FALSE()) -> Clothing | U1007: =VLOOKUP(D1007,Product_Dim!$A:$M,2,FALSE()) -> Men's Running Jacket | V1007: =VLOOKUP(E1007,Store_Dim!$A:$E,3,FALSE()) -> North | W1007: =VLOOKUP(C1007,Customer_Dim!$A:$N,13,FALSE()) -> Gold | X1007: =IF(F1007>3,"High","Low") -> Low
A1008: SALE1903 | B1008: 45644 | C1008: CUST1167 | D1008: PROD3 | E1008: STORE0 | F1008: 3 | G1008: 476.1 | H1008: 0.05 | I1008: COD | J1008: 1356.885 | K1008: =TEXT(B1008,"dd-mm-yyyy") -> 18-12-2024 | L1008: =TEXT(Sales_Fact!$B1008,"mmm") -> Dec | M1008: =IF(ISBLANK(F1008),1,F1008) -> 3 | N1008: =ROUNDUP(IF(ISBLANK(G1008),AVERAGE(C:C,G1008,G:G),G1008),2) -> 476.1 | O1008: =M1008*N1008*(1-H1008) -> 1356.885 | P1008: =M1008*N1008 -> 1428.3 | Q1008: =(P1008-O1008)/P1008 -> 0.05 | R1008: =IF(Sales_Fact!$O1008>1000,"High","Low") -> High | S1008: =VLOOKUP(C1008,Customer_Dim!$A:$N,9,FALSE()) -> Antonio Wade | T1008: =VLOOKUP(D1008,Product_Dim!$A:$M,3,FALSE()) -> Clothing | U1008: =VLOOKUP(D1008,Product_Dim!$A:$M,2,FALSE()) -> Men's Running Jacket | V1008: =VLOOKUP(E1008,Store_Dim!$A:$E,3,FALSE()) -> East | W1008: =VLOOKUP(C1008,Customer_Dim!$A:$N,13,FALSE()) -> Gold | X1008: =IF(F1008>3,"High","Low") -> Low
A1009: SALE1904 | B1009: 45514 | C1009: CUST1061 | D1009: PROD61 | E1009: STORE6 | F1009: 1 | G1009: 546.47 | H1009: 0.08 | I1009: COD | J1009: 502.7524 | K1009: =TEXT(B1009,"dd-mm-yyyy") -> 10-08-2024 | L1009: =TEXT(Sales_Fact!$B1009,"mmm") -> Aug | M1009: =IF(ISBLANK(F1009),1,F1009) -> 1 | N1009: =ROUNDUP(IF(ISBLANK(G1009),AVERAGE(C:C,G1009,G:G),G1009),2) -> 546.47 | O1009: =M1009*N1009*(1-H1009) -> 502.7524 | P1009: =M1009*N1009 -> 546.47 | Q1009: =(P1009-O1009)/P1009 -> 0.08 | R1009: =IF(Sales_Fact!$O1009>1000,"High","Low") -> Low | S1009: =VLOOKUP(C1009,Customer_Dim!$A:$N,9,FALSE()) -> Kristin Stein | T1009: =VLOOKUP(D1009,Product_Dim!$A:$M,3,FALSE()) -> Sports | U1009: =VLOOKUP(D1009,Product_Dim!$A:$M,2,FALSE()) -> Tennis Ball 3-Pack | V1009: =VLOOKUP(E1009,Store_Dim!$A:$E,3,FALSE()) -> East | W1009: =VLOOKUP(C1009,Customer_Dim!$A:$N,13,FALSE()) -> Silver | X1009: =IF(F1009>3,"High","Low") -> Low
A1010: SALE1905 | B1010: 45760 | C1010: CUST1176 | D1010: PROD75 | E1010: STORE12 | F1010: 1 | G1010: 979.49 | H1010: 0.19 | I1010: COD | J1010: 793.3869 | K1010: =TEXT(B1010,"dd-mm-yyyy") -> 13-04-2025 | L1010: =TEXT(Sales_Fact!$B1010,"mmm") -> Apr | M1010: =IF(ISBLANK(F1010),1,F1010) -> 1 | N1010: =ROUNDUP(IF(ISBLANK(G1010),AVERAGE(C:C,G1010,G:G),G1010),2) -> 979.49 | O1010: =M1010*N1010*(1-H1010) -> 793.3869 | P1010: =M1010*N1010 -> 979.49 | Q1010: =(P1010-O1010)/P1010 -> 0.19 | R1010: =IF(Sales_Fact!$O1010>1000,"High","Low") -> Low | S1010: =VLOOKUP(C1010,Customer_Dim!$A:$N,9,FALSE()) -> John Bradford | T1010: =VLOOKUP(D1010,Product_Dim!$A:$M,3,FALSE()) -> Clothing | U1010: =VLOOKUP(D1010,Product_Dim!$A:$M,2,FALSE()) -> Women's Ankle Boots | V1010: =VLOOKUP(E1010,Store_Dim!$A:$E,3,FALSE()) -> North | W1010: =VLOOKUP(C1010,Customer_Dim!$A:$N,13,FALSE()) -> Silver | X1010: =IF(F1010>3,"High","Low") -> Low
A1011: SALE1906 | B1011: 45289 | C1011: CUST1193 | D1011: PROD17 | E1011: STORE2 | F1011: 3 | G1011: 988.53 | H1011: 0.3 | I1011: COD | J1011: 2075.913 | K1011: =TEXT(B1011,"dd-mm-yyyy") -> 29-12-2023 | L1011: =TEXT(Sales_Fact!$B1011,"mmm") -> Dec | M1011: =IF(ISBLANK(F1011),1,F1011) -> 3 | N1011: =ROUNDUP(IF(ISBLANK(G1011),AVERAGE(C:C,G1011,G:G),G1011),2) -> 988.53 | O1011: =M1011*N1011*(1-H1011) -> 2075.913 | P1011: =M1011*N1011 -> 2965.59 | Q1011: =(P1011-O1011)/P1011 -> 0.3 | R1011: =IF(Sales_Fact!$O1011>1000,"High","Low") -> High | S1011: =VLOOKUP(C1011,Customer_Dim!$A:$N,9,FALSE()) -> David Roberts | T1011: =VLOOKUP(D1011,Product_Dim!$A:$M,3,FALSE()) -> Sports | U1011: =VLOOKUP(D1011,Product_Dim!$A:$M,2,FALSE()) -> Soccer Training Cone Set | V1011: =VLOOKUP(E1011,Store_Dim!$A:$E,3,FALSE()) -> South | W1011: =VLOOKUP(C1011,Customer_Dim!$A:$N,13,FALSE()) -> Gold | X1011: =IF(F1011>3,"High","Low") -> Low
A1012: SALE1907 | B1012: 45704 | C1012: CUST1255 | D1012: PROD76 | E1012: STORE3 | F1012: 4 | G1012: 849.29 | H1012: 0.26 | I1012: Credit Card | J1012: 2513.8984 | K1012: =TEXT(B1012,"dd-mm-yyyy") -> 16-02-2025 | L1012: =TEXT(Sales_Fact!$B1012,"mmm") -> Feb | M1012: =IF(ISBLANK(F1012),1,F1012) -> 4 | N1012: =ROUNDUP(IF(ISBLANK(G1012),AVERAGE(C:C,G1012,G:G),G1012),2) -> 849.29 | O1012: =M1012*N1012*(1-H1012) -> 2513.8984 | P1012: =M1012*N1012 -> 3397.16 | Q1012: =(P1012-O1012)/P1012 -> 0.26 | R1012: =IF(Sales_Fact!$O1012>1000,"High","Low") -> High | S1012: =VLOOKUP(C1012,Customer_Dim!$A:$N,9,FALSE()) -> Damon Perez | T1012: =VLOOKUP(D1012,Product_Dim!$A:$M,3,FALSE()) -> Electronics | U1012: =VLOOKUP(D1012,Product_Dim!$A:$M,2,FALSE()) -> Wireless Mouse | V1012: =VLOOKUP(E1012,Store_Dim!$A:$E,3,FALSE()) -> North | W1012: =VLOOKUP(C1012,Customer_Dim!$A:$N,13,FALSE()) -> Gold | X1012: =IF(F1012>3,"High","Low") -> High
A1013: SALE1908 | B1013: 45318 | C1013: CUST1343 | D1013: PROD95 | E1013: STORE14 | F1013: 2 | G1013: 452.29 | H1013: 0.01 | I1013: COD | J1013: 895.5342 | K1013: =TEXT(B1013,"dd-mm-yyyy") -> 27-01-2024 | L1013: =TEXT(Sales_Fact!$B1013,"mmm") -> Jan | M1013: =IF(ISBLANK(F1013),1,F1013) -> 2 | N1013: =ROUNDUP(IF(ISBLANK(G1013),AVERAGE(C:C,G1013,G:G),G1013),2) -> 452.29 | O1013: =M1013*N1013*(1-H1013) -> 895.5342 | P1013: =M1013*N1013 -> 904.58 | Q1013: =(P1013-O1013)/P1013 -> 0.01 | R1013: =IF(Sales_Fact!$O1013>1000,"High","Low") -> Low | S1013: =VLOOKUP(C1013,Customer_Dim!$A:$N,9,FALSE()) -> Ryan Moore | T1013: =VLOOKUP(D1013,Product_Dim!$A:$M,3,FALSE()) -> Sports | U1013: =VLOOKUP(D1013,Product_Dim!$A:$M,2,FALSE()) -> Sports Stopwatch Basic | V1013: =VLOOKUP(E1013,Store_Dim!$A:$E,3,FALSE()) -> South | W1013: =VLOOKUP(C1013,Customer_Dim!$A:$N,13,FALSE()) -> Bronze | X1013: =IF(F1013>3,"High","Low") -> Low
A1014: SALE1909 | B1014: 45495 | C1014: CUST1445 | D1014: PROD54 | E1014: STORE18 | F1014: 2 | G1014: 810.81 | H1014: 0.11 | I1014: COD | J1014: 1443.2418 | K1014: =TEXT(B1014,"dd-mm-yyyy") -> 22-07-2024 | L1014: =TEXT(Sales_Fact!$B1014,"mmm") -> Jul | M1014: =IF(ISBLANK(F1014),1,F1014) -> 2 | N1014: =ROUNDUP(IF(ISBLANK(G1014),AVERAGE(C:C,G1014,G:G),G1014),2) -> 810.81 | O1014: =M1014*N1014*(1-H1014) -> 1443.2418 | P1014: =M1014*N1014 -> 1621.62 | Q1014: =(P1014-O1014)/P1014 -> 0.11 | R1014: =IF(Sales_Fact!$O1014>1000,"High","Low") -> High | S1014: =VLOOKUP(C1014,Customer_Dim!$A:$N,9,FALSE()) -> Gene Lee | T1014: =VLOOKUP(D1014,Product_Dim!$A:$M,3,FALSE()) -> Sports | U1014: =VLOOKUP(D1014,Product_Dim!$A:$M,2,FALSE()) -> Sports Stopwatch Pro | V1014: =VLOOKUP(E1014,Store_Dim!$A:$E,3,FALSE()) -> East | W1014: =VLOOKUP(C1014,Customer_Dim!$A:$N,13,FALSE()) -> Platinum | X1014: =IF(F1014>3,"High","Low") -> Low
A1015: SALE191 | B1015: 45459 | C1015: CUST1138 | D1015: PROD46 | E1015: STORE18 | F1015: 1 | G1015: 804.9 | H1015: 0.03 | I1015: PayPal | J1015: 780.753 | K1015: =TEXT(B1015,"dd-mm-yyyy") -> 16-06-2024 | L1015: =TEXT(Sales_Fact!$B1015,"mmm") -> Jun | M1015: =IF(ISBLANK(F1015),1,F1015) -> 1 | N1015: =ROUNDUP(IF(ISBLANK(G1015),AVERAGE(C:C,G1015,G:G),G1015),2) -> 804.9 | O1015: =M1015*N1015*(1-H1015) -> 780.753 | P1015: =M1015*N1015 -> 804.9 | Q1015: =(P1015-O1015)/P1015 -> 0.03 | R1015: =IF(Sales_Fact!$O1015>1000,"High","Low") -> Low | S1015: =VLOOKUP(C1015,Customer_Dim!$A:$N,9,FALSE()) -> Sean Roth | T1015: =VLOOKUP(D1015,Product_Dim!$A:$M,3,FALSE()) -> Clothing | U1015: =VLOOKUP(D1015,Product_Dim!$A:$M,2,FALSE()) -> Men's Winter Jacket | V1015: =VLOOKUP(E1015,Store_Dim!$A:$E,3,FALSE()) -> East | W1015: =VLOOKUP(C1015,Customer_Dim!$A:$N,13,FALSE()) -> Gold | X1015: =IF(F1015>3,"High","Low") -> Low
... A1179: SALE258 | B1179: 45300 | C1179: CUST1136 | D1179: PROD35 | E1179: STORE17 | F1179: 1 | G1179: 222.94 | H1179: 0.19 | I1179: Credit Card | J1179: 180.5814 | K1179: =TEXT(B1179,"dd-mm-yyyy") -> 09-01-2024 | L1179: =TEXT(Sales_Fact!$B1179,"mmm") -> Jan | M1179: =IF(ISBLANK(F1179),1,F1179) -> 1 | N1179: =ROUNDUP(IF(ISBLANK(G1179),AVERAGE(C:C,G1179,G:G),G1179),2) -> 222.94 | O1179: =M1179*N1179*(1-H1179) -> 180.5814 | P1179: =M1179*N1179 -> 222.94 | Q1179: =(P1179-O1179)/P1179 -> 0.19 | R1179: =IF(Sales_Fact!$O1179>1000,"High","Low") -> Low | S1179: =VLOOKUP(C1179,Customer_Dim!$A:$N,9,FALSE()) -> Patrick Coleman | T1179: =VLOOKUP(D1179,Product_Dim!$A:$M,3,FALSE()) -> Home | U1179: =VLOOKUP(D1179,Product_Dim!$A:$M,2,FALSE()) -> Bedroom Table Lamp | V1179: =VLOOKUP(E1179,Store_Dim!$A:$E,3,FALSE()) -> North | W1179: =VLOOKUP(C1179,Customer_Dim!$A:$N,13,FALSE()) -> Silver | X1179: =IF(F1179>3,"High","Low") -> Low
A1180: SALE259 | B1180: 45773 | C1180: CUST1248 | D1180: PROD35 | E1180: STORE2 | F1180: 2 | G1180: 355.3 | I1180: PayPal | J1180: 589.798 | K1180: =TEXT(B1180,"dd-mm-yyyy") -> 26-04-2025 | L1180: =TEXT(Sales_Fact!$B1180,"mmm") -> Apr | M1180: =IF(ISBLANK(F1180),1,F1180) -> 2 | N1180: =ROUNDUP(IF(ISBLANK(G1180),AVERAGE(C:C,G1180,G:G),G1180),2) -> 355.3 | O1180: =M1180*N1180*(1-H1180) -> 710.6 | P1180: =M1180*N1180 -> 710.6 | Q1180: =(P1180-O1180)/P1180 -> 0 | R1180: =IF(Sales_Fact!$O1180>1000,"High","Low") -> Low | S1180: =VLOOKUP(C1180,Customer_Dim!$A:$N,9,FALSE()) -> Nicholas Webb | T1180: =VLOOKUP(D1180,Product_Dim!$A:$M,3,FALSE()) -> Home | U1180: =VLOOKUP(D1180,Product_Dim!$A:$M,2,FALSE()) -> Bedroom Table Lamp | V1180: =VLOOKUP(E1180,Store_Dim!$A:$E,3,FALSE()) -> South | W1180: =VLOOKUP(C1180,Customer_Dim!$A:$N,13,FALSE()) -> Gold | X1180: =IF(F1180>3,"High","Low") -> Low
A1181: SALE26 | B1181: 45294 | C1181: CUST1213 | D1181: PROD98 | E1181: STORE8 | F1181: 4 | G1181: 156.16 | I1181: Credit Card | J1181: 599.6544 | K1181: =TEXT(B1181,"dd-mm-yyyy") -> 03-01-2024 | L1181: =TEXT(Sales_Fact!$B1181,"mmm") -> Jan | M1181: =IF(ISBLANK(F1181),1,F1181) -> 4 | N1181: =ROUNDUP(IF(ISBLANK(G1181),AVERAGE(C:C,G1181,G:G),G1181),2) -> 156.16 | O1181: =M1181*N1181*(1-H1181) -> 624.64 | P1181: =M1181*N1181 -> 624.64 | Q1181: =(P1181-O1181)/P1181 -> 0 | R1181: =IF(Sales_Fact!$O1181>1000,"High","Low") -> Low | S1181: =VLOOKUP(C1181,Customer_Dim!$A:$N,9,FALSE()) -> Stuart Johnson | T1181: =VLOOKUP(D1181,Product_Dim!$A:$M,3,FALSE()) -> Electronics | U1181: =VLOOKUP(D1181,Product_Dim!$A:$M,2,FALSE()) -> Portable Bluetooth Speaker | V1181: =VLOOKUP(E1181,Store_Dim!$A:$E,3,FALSE()) -> West | W1181: =VLOOKUP(C1181,Customer_Dim!$A:$N,13,FALSE()) -> Platinum | X1181: =IF(F1181>3,"High","Low") -> High
A1182: SALE260 | B1182: 45497 | C1182: CUST1103 | D1182: PROD89 | E1182: STORE19 | F1182: 4 | G1182: 611.3 | H1182: 0.11 | I1182: PayPal | J1182: 2176.228 | K1182: =TEXT(B1182,"dd-mm-yyyy") -> 24-07-2024 | L1182: =TEXT(Sales_Fact!$B1182,"mmm") -> Jul | M1182: =IF(ISBLANK(F1182),1,F1182) -> 4 | N1182: =ROUNDUP(IF(ISBLANK(G1182),AVERAGE(C:C,G1182,G:G),G1182),2) -> 611.3 | O1182: =M1182*N1182*(1-H1182) -> 2176.228 | P1182: =M1182*N1182 -> 2445.2 | Q1182: =(P1182-O1182)/P1182 -> 0.11 | R1182: =IF(Sales_Fact!$O1182>1000,"High","Low") -> High | S1182: =VLOOKUP(C1182,Customer_Dim!$A:$N,9,FALSE()) -> Steven Stein | T1182: =VLOOKUP(D1182,Product_Dim!$A:$M,3,FALSE()) -> Beauty | U1182: =VLOOKUP(D1182,Product_Dim!$A:$M,2,FALSE()) -> Face Foundation Kit | V1182: =VLOOKUP(E1182,Store_Dim!$A:$E,3,FALSE()) -> East | W1182: =VLOOKUP(C1182,Customer_Dim!$A:$N,13,FALSE()) -> Bronze | X1182: =IF(F1182>3,"High","Low") -> High
A1183: SALE261 | B1183: 45742 | C1183: CUST1333 | D1183: PROD0 | E1183: STORE8 | F1183: 4 | G1183: 849.21 | H1183: 0.07 | I1183: Credit Card | J1183: 3159.0612 | K1183: =TEXT(B1183,"dd-mm-yyyy") -> 26-03-2025 | L1183: =TEXT(Sales_Fact!$B1183,"mmm") -> Mar | M1183: =IF(ISBLANK(F1183),1,F1183) -> 4 | N1183: =ROUNDUP(IF(ISBLANK(G1183),AVERAGE(C:C,G1183,G:G),G1183),2) -> 849.21 | O1183: =M1183*N1183*(1-H1183) -> 3159.0612 | P1183: =M1183*N1183 -> 3396.84 | Q1183: =(P1183-O1183)/P1183 -> 0.07 | R1183: =IF(Sales_Fact!$O1183>1000,"High","Low") -> High | S1183: =VLOOKUP(C1183,Customer_Dim!$A:$N,9,FALSE()) -> Teresa Johnson | T1183: =VLOOKUP(D1183,Product_Dim!$A:$M,3,FALSE()) -> Electronics | U1183: =VLOOKUP(D1183,Product_Dim!$A:$M,2,FALSE()) -> Brother Laser Printer | V1183: =VLOOKUP(E1183,Store_Dim!$A:$E,3,FALSE()) -> West | W1183: =VLOOKUP(C1183,Customer_Dim!$A:$N,13,FALSE()) -> Gold | X1183: =IF(F1183>3,"High","Low") -> High
A1184: SALE262 | B1184: 45713 | C1184: CUST1209 | D1184: PROD42 | E1184: STORE7 | F1184: 3 | G1184: 553.12 | H1184: 0.28 | I1184: COD | J1184: 1194.7392 | K1184: =TEXT(B1184,"dd-mm-yyyy") -> 25-02-2025 | L1184: =TEXT(Sales_Fact!$B1184,"mmm") -> Feb | M1184: =IF(ISBLANK(F1184),1,F1184) -> 3 | N1184: =ROUNDUP(IF(ISBLANK(G1184),AVERAGE(C:C,G1184,G:G),G1184),2) -> 553.12 | O1184: =M1184*N1184*(1-H1184) -> 1194.7392 | P1184: =M1184*N1184 -> 1659.36 | Q1184: =(P1184-O1184)/P1184 -> 0.28 | R1184: =IF(Sales_Fact!$O1184>1000,"High","Low") -> High | S1184: =VLOOKUP(C1184,Customer_Dim!$A:$N,9,FALSE()) -> Joan Johnson | T1184: =VLOOKUP(D1184,Product_Dim!$A:$M,3,FALSE()) -> Electronics | U1184: =VLOOKUP(D1184,Product_Dim!$A:$M,2,FALSE()) -> Smart Home WiFi Camera | V1184: =VLOOKUP(E1184,Store_Dim!$A:$E,3,FALSE()) -> South | W1184: =VLOOKUP(C1184,Customer_Dim!$A:$N,13,FALSE()) -> Platinum | X1184: =IF(F1184>3,"High","Low") -> Low
A1185: SALE263 | B1185: 45826 | C1185: CUST1282 | D1185: PROD91 | E1185: STORE9 | F1185: 2 | G1185: 903.08 | H1185: 0.18 | I1185: COD | J1185: 1481.0512 | K1185: =TEXT(B1185,"dd-mm-yyyy") -> 18-06-2025 | L1185: =TEXT(Sales_Fact!$B1185,"mmm") -> Jun | M1185: =IF(ISBLANK(F1185),1,F1185) -> 2 | N1185: =ROUNDUP(IF(ISBLANK(G1185),AVERAGE(C:C,G1185,G:G),G1185),2) -> 903.08 | O1185: =M1185*N1185*(1-H1185) -> 1481.0512 | P1185: =M1185*N1185 -> 1806.16 | Q1185: =(P1185-O1185)/P1185 -> 0.18 | R1185: =IF(Sales_Fact!$O1185>1000,"High","Low") -> High | S1185: =VLOOKUP(C1185,Customer_Dim!$A:$N,9,FALSE()) -> Kristi Lopez | T1185: =VLOOKUP(D1185,Product_Dim!$A:$M,3,FALSE()) -> Clothing | U1185: =VLOOKUP(D1185,Product_Dim!$A:$M,2,FALSE()) -> Women's High Heels | V1185: =VLOOKUP(E1185,Store_Dim!$A:$E,3,FALSE()) -> South | W1185: =VLOOKUP(C1185,Customer_Dim!$A:$N,13,FALSE()) -> Gold | X1185: =IF(F1185>3,"High","Low") -> Low
A1186: SALE264 | B1186: 45648 | C1186: CUST1478 | D1186: PROD16 | E1186: STORE11 | F1186: 4 | G1186: 640.23 | H1186: 0.06 | I1186: COD | J1186: 2407.2648 | K1186: =TEXT(B1186,"dd-mm-yyyy") -> 22-12-2024 | L1186: =TEXT(Sales_Fact!$B1186,"mmm") -> Dec | M1186: =IF(ISBLANK(F1186),1,F1186) -> 4 | N1186: =ROUNDUP(IF(ISBLANK(G1186),AVERAGE(C:C,G1186,G:G),G1186),2) -> 640.23 | O1186: =M1186*N1186*(1-H1186) -> 2407.2648 | P1186: =M1186*N1186 -> 2560.92 | Q1186: =(P1186-O1186)/P1186 -> 0.06 | R1186: =IF(Sales_Fact!$O1186>1000,"High","Low") -> High | S1186: =VLOOKUP(C1186,Customer_Dim!$A:$N,9,FALSE()) -> Earl Smith Dds | T1186: =VLOOKUP(D1186,Product_Dim!$A:$M,3,FALSE()) -> Beauty | U1186: =VLOOKUP(D1186,Product_Dim!$A:$M,2,FALSE()) -> Beard Grooming Kit | V1186: =VLOOKUP(E1186,Store_Dim!$A:$E,3,FALSE()) -> South | W1186: =VLOOKUP(C1186,Customer_Dim!$A:$N,13,FALSE()) -> Gold | X1186: =IF(F1186>3,"High","Low") -> High
A1187: SALE265 | B1187: 45836 | C1187: CUST1141 | D1187: PROD21 | E1187: STORE6 | F1187: 1 | G1187: 518 | H1187: 0.25 | I1187: Credit Card | J1187: 388.5 | K1187: =TEXT(B1187,"dd-mm-yyyy") -> 28-06-2025 | L1187: =TEXT(Sales_Fact!$B1187,"mmm") -> Jun | M1187: =IF(ISBLANK(F1187),1,F1187) -> 1 | N1187: =ROUNDUP(IF(ISBLANK(G1187),AVERAGE(C:C,G1187,G:G),G1187),2) -> 518 | O1187: =M1187*N1187*(1-H1187) -> 388.5 | P1187: =M1187*N1187 -> 518 | Q1187: =(P1187-O1187)/P1187 -> 0.25 | R1187: =IF(Sales_Fact!$O1187>1000,"High","Low") -> Low | S1187: =VLOOKUP(C1187,Customer_Dim!$A:$N,9,FALSE()) -> Cristian Wright | T1187: =VLOOKUP(D1187,Product_Dim!$A:$M,3,FALSE()) -> Home | U1187: =VLOOKUP(D1187,Product_Dim!$A:$M,2,FALSE()) -> Multi-Purpose Storage Box | V1187: =VLOOKUP(E1187,Store_Dim!$A:$E,3,FALSE()) -> East | W1187: =VLOOKUP(C1187,Customer_Dim!$A:$N,13,FALSE()) -> Bronze | X1187: =IF(F1187>3,"High","Low") -> Low
A1188: SALE266 | B1188: 45437 | C1188: CUST1433 | D1188: PROD64 | E1188: STORE4 | F1188: 4 | G1188: 779.25 | H1188: 0.25 | I1188: Credit Card | J1188: 2337.75 | K1188: =TEXT(B1188,"dd-mm-yyyy") -> 25-05-2024 | L1188: =TEXT(Sales_Fact!$B1188,"mmm") -> May | M1188: =IF(ISBLANK(F1188),1,F1188) -> 4 | N1188: =ROUNDUP(IF(ISBLANK(G1188),AVERAGE(C:C,G1188,G:G),G1188),2) -> 779.25 | O1188: =M1188*N1188*(1-H1188) -> 2337.75 | P1188: =M1188*N1188 -> 3117 | Q1188: =(P1188-O1188)/P1188 -> 0.25 | R1188: =IF(Sales_Fact!$O1188>1000,"High","Low") -> High | S1188: =VLOOKUP(C1188,Customer_Dim!$A:$N,9,FALSE()) -> Thomas Moore | T1188: =VLOOKUP(D1188,Product_Dim!$A:$M,3,FALSE()) -> Beauty | U1188: =VLOOKUP(D1188,Product_Dim!$A:$M,2,FALSE()) -> Matte Lipstick Set | V1188: =VLOOKUP(E1188,Store_Dim!$A:$E,3,FALSE()) -> South | W1188: =VLOOKUP(C1188,Customer_Dim!$A:$N,13,FALSE()) -> Silver | X1188: =IF(F1188>3,"High","Low") -> High
A1189: SALE267 | B1189: 45807 | C1189: CUST1118 | D1189: PROD83 | E1189: STORE7 | F1189: 2 | G1189: 467.75 | H1189: 0.26 | I1189: Credit Card | J1189: 692.27 | K1189: =TEXT(B1189,"dd-mm-yyyy") -> 30-05-2025 | L1189: =TEXT(Sales_Fact!$B1189,"mmm") -> May | M1189: =IF(ISBLANK(F1189),1,F1189) -> 2 | N1189: =ROUNDUP(IF(ISBLANK(G1189),AVERAGE(C:C,G1189,G:G),G1189),2) -> 467.75 | O1189: =M1189*N1189*(1-H1189) -> 692.27 | P1189: =M1189*N1189 -> 935.5 | Q1189: =(P1189-O1189)/P1189 -> 0.26 | R1189: =IF(Sales_Fact!$O1189>1000,"High","Low") -> Low | S1189: =VLOOKUP(C1189,Customer_Dim!$A:$N,9,FALSE()) -> Earl Allen | T1189: =VLOOKUP(D1189,Product_Dim!$A:$M,3,FALSE()) -> Beauty | U1189: =VLOOKUP(D1189,Product_Dim!$A:$M,2,FALSE()) -> Hydrating Face Cleanser | V1189: =VLOOKUP(E1189,Store_Dim!$A:$E,3,FALSE()) -> South | W1189: =VLOOKUP(C1189,Customer_Dim!$A:$N,13,FALSE()) -> Platinum | X1189: =IF(F1189>3,"High","Low") -> Low
A1190: SALE268 | B1190: 45555 | C1190: CUST1406 | D1190: PROD90 | E1190: STORE18 | F1190: 3 | H1190: 0.06 | I1190: Credit Card | J1190: 315.2478 | K1190: =TEXT(B1190,"dd-mm-yyyy") -> 20-09-2024 | L1190: =TEXT(Sales_Fact!$B1190,"mmm") -> Sep | M1190: =IF(ISBLANK(F1190),1,F1190) -> 3 | N1190: =ROUNDUP(IF(ISBLANK(G1190),AVERAGE(C:C,G1190,G:G),G1190),2) -> 513.99 | O1190: =M1190*N1190*(1-H1190) -> 1449.4518 | P1190: =M1190*N1190 -> 1541.97 | Q1190: =(P1190-O1190)/P1190 -> 0.06 | R1190: =IF(Sales_Fact!$O1190>1000,"High","Low") -> High | S1190: =VLOOKUP(C1190,Customer_Dim!$A:$N,9,FALSE()) -> David Lozano | T1190: =VLOOKUP(D1190,Product_Dim!$A:$M,3,FALSE()) -> Electronics | U1190: =VLOOKUP(D1190,Product_Dim!$A:$M,2,FALSE()) -> Gaming Mouse Pad XL | V1190: =VLOOKUP(E1190,Store_Dim!$A:$E,3,FALSE()) -> East | W1190: =VLOOKUP(C1190,Customer_Dim!$A:$N,13,FALSE()) -> Gold | X1190: =IF(F1190>3,"High","Low") -> Low
A1191: SALE269 | B1191: 45803 | C1191: CUST1219 | D1191: PROD37 | E1191: STORE0 | F1191: 4 | G1191: 747.01 | H1191: 0.13 | I1191: PayPal | J1191: 2599.5948 | K1191: =TEXT(B1191,"dd-mm-yyyy") -> 26-05-2025 | L1191: =TEXT(Sales_Fact!$B1191,"mmm") -> May | M1191: =IF(ISBLANK(F1191),1,F1191) -> 4 | N1191: =ROUNDUP(IF(ISBLANK(G1191),AVERAGE(C:C,G1191,G:G),G1191),2) -> 747.01 | O1191: =M1191*N1191*(1-H1191) -> 2599.5948 | P1191: =M1191*N1191 -> 2988.04 | Q1191: =(P1191-O1191)/P1191 -> 0.13 | R1191: =IF(Sales_Fact!$O1191>1000,"High","Low") -> High | S1191: =VLOOKUP(C1191,Customer_Dim!$A:$N,9,FALSE()) -> Jordan Wells | T1191: =VLOOKUP(D1191,Product_Dim!$A:$M,3,FALSE()) -> Clothing | U1191: =VLOOKUP(D1191,Product_Dim!$A:$M,2,FALSE()) -> Men's Casual Sneakers | V1191: =VLOOKUP(E1191,Store_Dim!$A:$E,3,FALSE()) -> East | W1191: =VLOOKUP(C1191,Customer_Dim!$A:$N,13,FALSE()) -> Gold | X1191: =IF(F1191>3,"High","Low") -> High
A1192: SALE27 | B1192: 45710 | C1192: CUST1200 | D1192: PROD77 | E1192: STORE8 | F1192: 3 | G1192: 815.49 | H1192: 0.17 | I1192: Credit Card | J1192: 2030.5701 | K1192: =TEXT(B1192,"dd-mm-yyyy") -> 22-02-2025 | L1192: =TEXT(Sales_Fact!$B1192,"mmm") -> Feb | M1192: =IF(ISBLANK(F1192),1,F1192) -> 3 | N1192: =ROUNDUP(IF(ISBLANK(G1192),AVERAGE(C:C,G1192,G:G),G1192),2) -> 815.49 | O1192: =M1192*N1192*(1-H1192) -> 2030.5701 | P1192: =M1192*N1192 -> 2446.47 | Q1192: =(P1192-O1192)/P1192 -> 0.17 | R1192: =IF(Sales_Fact!$O1192>1000,"High","Low") -> High | S1192: =VLOOKUP(C1192,Customer_Dim!$A:$N,9,FALSE()) -> Anna Perez | T1192: =VLOOKUP(D1192,Product_Dim!$A:$M,3,FALSE()) -> Electronics | U1192: =VLOOKUP(D1192,Product_Dim!$A:$M,2,FALSE()) -> WiFi Mesh Router | V1192: =VLOOKUP(E1192,Store_Dim!$A:$E,3,FALSE()) -> West | W1192: =VLOOKUP(C1192,Customer_Dim!$A:$N,13,FALSE()) -> Platinum | X1192: =IF(F1192>3,"High","Low") -> Low
A1193: SALE270 | B1193: 45735 | C1193: CUST1101 | D1193: PROD89 | E1193: STORE12 | F1193: 4 | G1193: 461.83 | H1193: 0.28 | I1193: PayPal | J1193: 1330.0704 | K1193: =TEXT(B1193,"dd-mm-yyyy") -> 19-03-2025 | L1193: =TEXT(Sales_Fact!$B1193,"mmm") -> Mar | M1193: =IF(ISBLANK(F1193),1,F1193) -> 4 | N1193: =ROUNDUP(IF(ISBLANK(G1193),AVERAGE(C:C,G1193,G:G),G1193),2) -> 461.83 | O1193: =M1193*N1193*(1-H1193) -> 1330.0704 | P1193: =M1193*N1193 -> 1847.32 | Q1193: =(P1193-O1193)/P1193 -> 0.28 | R1193: =IF(Sales_Fact!$O1193>1000,"High","Low") -> High | S1193: =VLOOKUP(C1193,Customer_Dim!$A:$N,9,FALSE()) -> Colleen Maynard | T1193: =VLOOKUP(D1193,Product_Dim!$A:$M,3,FALSE()) -> Beauty | U1193: =VLOOKUP(D1193,Product_Dim!$A:$M,2,FALSE()) -> Face Foundation Kit | V1193: =VLOOKUP(E1193,Store_Dim!$A:$E,3,FALSE()) -> North | W1193: =VLOOKUP(C1193,Customer_Dim!$A:$N,13,FALSE()) -> Gold | X1193: =IF(F1193>3,"High","Low") -> High
A1194: SALE271 | B1194: 45750 | C1194: CUST1134 | D1194: PROD70 | E1194: STORE8 | F1194: 2 | G1194: 105.15 | H1194: 0.06 | I1194: Credit Card | J1194: 197.682 | K1194: =TEXT(B1194,"dd-mm-yyyy") -> 03-04-2025 | L1194: =TEXT(Sales_Fact!$B1194,"mmm") -> Apr | M1194: =IF(ISBLANK(F1194),1,F1194) -> 2 | N1194: =ROUNDUP(IF(ISBLANK(G1194),AVERAGE(C:C,G1194,G:G),G1194),2) -> 105.15 | O1194: =M1194*N1194*(1-H1194) -> 197.682 | P1194: =M1194*N1194 -> 210.3 | Q1194: =(P1194-O1194)/P1194 -> 0.06 | R1194: =IF(Sales_Fact!$O1194>1000,"High","Low") -> Low | S1194: =VLOOKUP(C1194,Customer_Dim!$A:$N,9,FALSE()) -> Morgan Bowen | T1194: =VLOOKUP(D1194,Product_Dim!$A:$M,3,FALSE()) -> Home | U1194: =VLOOKUP(D1194,Product_Dim!$A:$M,2,FALSE()) -> Kitchen Storage Rack | V1194: =VLOOKUP(E1194,Store_Dim!$A:$E,3,FALSE()) -> West | W1194: =VLOOKUP(C1194,Customer_Dim!$A:$N,13,FALSE()) -> Gold | X1194: =IF(F1194>3,"High","Low") -> Low
A1195: SALE272 | B1195: 45693 | C1195: CUST1033 | D1195: PROD23 | E1195: STORE3 | F1195: 3 | G1195: 610.24 | H1195: 0.17 | I1195: COD | J1195: 1519.4976 | K1195: =TEXT(B1195,"dd-mm-yyyy") -> 05-02-2025 | L1195: =TEXT(Sales_Fact!$B1195,"mmm") -> Feb | M1195: =IF(ISBLANK(F1195),1,F1195) -> 3 | N1195: =ROUNDUP(IF(ISBLANK(G1195),AVERAGE(C:C,G1195,G:G),G1195),2) -> 610.24 | O1195: =M1195*N1195*(1-H1195) -> 1519.4976 | P1195: =M1195*N1195 -> 1830.72 | Q1195: =(P1195-O1195)/P1195 -> 0.17 | R1195: =IF(Sales_Fact!$O1195>1000,"High","Low") -> High | S1195: =VLOOKUP(C1195,Customer_Dim!$A:$N,9,FALSE()) -> Robert Jones Dds | T1195: =VLOOKUP(D1195,Product_Dim!$A:$M,3,FALSE()) -> Clothing | U1195: =VLOOKUP(D1195,Product_Dim!$A:$M,2,FALSE()) -> Men's Formal Shirt | V1195: =VLOOKUP(E1195,Store_Dim!$A:$E,3,FALSE()) -> North | W1195: =VLOOKUP(C1195,Customer_Dim!$A:$N,13,FALSE()) -> Platinum | X1195: =IF(F1195>3,"High","Low") -> Low
A1196: SALE273 | B1196: 45667 | C1196: CUST1312 | D1196: PROD74 | E1196: STORE8 | F1196: 1 | G1196: 872.12 | H1196: 0.07 | I1196: PayPal | J1196: 811.0716 | K1196: =TEXT(B1196,"dd-mm-yyyy") -> 10-01-2025 | L1196: =TEXT(Sales_Fact!$B1196,"mmm") -> Jan | M1196: =IF(ISBLANK(F1196),1,F1196) -> 1 | N1196: =ROUNDUP(IF(ISBLANK(G1196),AVERAGE(C:C,G1196,G:G),G1196),2) -> 872.12 | O1196: =M1196*N1196*(1-H1196) -> 811.0716 | P1196: =M1196*N1196 -> 872.12 | Q1196: =(P1196-O1196)/P1196 -> 0.07 | R1196: =IF(Sales_Fact!$O1196>1000,"High","Low") -> Low | S1196: =VLOOKUP(C1196,Customer_Dim!$A:$N,9,FALSE()) -> Jason Mullins | T1196: =VLOOKUP(D1196,Product_Dim!$A:$M,3,FALSE()) -> Electronics | U1196: =VLOOKUP(D1196,Product_Dim!$A:$M,2,FALSE()) -> Bluetooth Car Audio System | V1196: =VLOOKUP(E1196,Store_Dim!$A:$E,3,FALSE()) -> West | W1196: =VLOOKUP(C1196,Customer_Dim!$A:$N,13,FALSE()) -> Silver | X1196: =IF(F1196>3,"High","Low") -> Low
A1197: SALE274 | B1197: 45316 | C1197: CUST1433 | D1197: PROD10 | E1197: STORE1 | F1197: 1 | G1197: 406.79 | H1197: 0.03 | I1197: COD | J1197: 394.5863 | K1197: =TEXT(B1197,"dd-mm-yyyy") -> 25-01-2024 | L1197: =TEXT(Sales_Fact!$B1197,"mmm") -> Jan | M1197: =IF(ISBLANK(F1197),1,F1197) -> 1 | N1197: =ROUNDUP(IF(ISBLANK(G1197),AVERAGE(C:C,G1197,G:G),G1197),2) -> 406.79 | O1197: =M1197*N1197*(1-H1197) -> 394.5863 | P1197: =M1197*N1197 -> 406.79 | Q1197: =(P1197-O1197)/P1197 -> 0.03 | R1197: =IF(Sales_Fact!$O1197>1000,"High","Low") -> Low | S1197: =VLOOKUP(C1197,Customer_Dim!$A:$N,9,FALSE()) -> Thomas Moore | T1197: =VLOOKUP(D1197,Product_Dim!$A:$M,3,FALSE()) -> Home | U1197: =VLOOKUP(D1197,Product_Dim!$A:$M,2,FALSE()) -> Ceramic Kitchen Bowl Set | V1197: =VLOOKUP(E1197,Store_Dim!$A:$E,3,FALSE()) -> North | W1197: =VLOOKUP(C1197,Customer_Dim!$A:$N,13,FALSE()) -> Silver | X1197: =IF(F1197>3,"High","Low") -> Low
A1198: SALE275 | B1198: 45932 | C1198: CUST1372 | D1198: PROD54 | E1198: STORE14 | F1198: 1 | G1198: 606.01 | H1198: 0.04 | I1198: PayPal | J1198: 581.7696 | K1198: =TEXT(B1198,"dd-mm-yyyy") -> 02-10-2025 | L1198: =TEXT(Sales_Fact!$B1198,"mmm") -> Oct | M1198: =IF(ISBLANK(F1198),1,F1198) -> 1 | N1198: =ROUNDUP(IF(ISBLANK(G1198),AVERAGE(C:C,G1198,G:G),G1198),2) -> 606.01 | O1198: =M1198*N1198*(1-H1198) -> 581.7696 | P1198: =M1198*N1198 -> 606.01 | Q1198: =(P1198-O1198)/P1198 -> 0.04 | R1198: =IF(Sales_Fact!$O1198>1000,"High","Low") -> Low | S1198: =VLOOKUP(C1198,Customer_Dim!$A:$N,9,FALSE()) -> Jacqueline Anthony | T1198: =VLOOKUP(D1198,Product_Dim!$A:$M,3,FALSE()) -> Sports | U1198: =VLOOKUP(D1198,Product_Dim!$A:$M,2,FALSE()) -> Sports Stopwatch Pro | V1198: =VLOOKUP(E1198,Store_Dim!$A:$E,3,FALSE()) -> South | W1198: =VLOOKUP(C1198,Customer_Dim!$A:$N,13,FALSE()) -> Bronze | X1198: =IF(F1198>3,"High","Low") -> Low
A1199: SALE276 | B1199: 45483 | C1199: CUST1349 | D1199: PROD17 | E1199: STORE5 | F1199: 4 | G1199: 322.58 | H1199: 0.06 | I1199: Credit Card | J1199: 1212.9008 | K1199: =TEXT(B1199,"dd-mm-yyyy") -> 10-07-2024 | L1199: =TEXT(Sales_Fact!$B1199,"mmm") -> Jul | M1199: =IF(ISBLANK(F1199),1,F1199) -> 4 | N1199: =ROUNDUP(IF(ISBLANK(G1199),AVERAGE(C:C,G1199,G:G),G1199),2) -> 322.58 | O1199: =M1199*N1199*(1-H1199) -> 1212.9008 | P1199: =M1199*N1199 -> 1290.32 | Q1199: =(P1199-O1199)/P1199 -> 0.06 | R1199: =IF(Sales_Fact!$O1199>1000,"High","Low") -> High | S1199: =VLOOKUP(C1199,Customer_Dim!$A:$N,9,FALSE()) -> Heather Valenzuela | T1199: =VLOOKUP(D1199,Product_Dim!$A:$M,3,FALSE()) -> Sports | U1199: =VLOOKUP(D1199,Product_Dim!$A:$M,2,FALSE()) -> Soccer Training Cone Set | V1199: =VLOOKUP(E1199,Store_Dim!$A:$E,3,FALSE()) -> North | W1199: =VLOOKUP(C1199,Customer_Dim!$A:$N,13,FALSE()) -> Bronze | X1199: =IF(F1199>3,"High","Low") -> High
A1200: SALE277 | B1200: 45661 | C1200: CUST1484 | D1200: PROD77 | E1200: STORE18 | F1200: 4 | G1200: 463.17 | H1200: 0.06 | I1200: PayPal | J1200: 1741.5192 | K1200: =TEXT(B1200,"dd-mm-yyyy") -> 04-01-2025 | L1200: =TEXT(Sales_Fact!$B1200,"mmm") -> Jan | M1200: =IF(ISBLANK(F1200),1,F1200) -> 4 | N1200: =ROUNDUP(IF(ISBLANK(G1200),AVERAGE(C:C,G1200,G:G),G1200),2) -> 463.17 | O1200: =M1200*N1200*(1-H1200) -> 1741.5192 | P1200: =M1200*N1200 -> 1852.68 | Q1200: =(P1200-O1200)/P1200 -> 0.06 | R1200: =IF(Sales_Fact!$O1200>1000,"High","Low") -> High | S1200: =VLOOKUP(C1200,Customer_Dim!$A:$N,9,FALSE()) -> Jessica Castro | T1200: =VLOOKUP(D1200,Product_Dim!$A:$M,3,FALSE()) -> Electronics | U1200: =VLOOKUP(D1200,Product_Dim!$A:$M,2,FALSE()) -> WiFi Mesh Router | V1200: =VLOOKUP(E1200,Store_Dim!$A:$E,3,FALSE()) -> East | W1200: =VLOOKUP(C1200,Customer_Dim!$A:$N,13,FALSE()) -> Bronze | X1200: =IF(F1200>3,"High","Low") -> High
A1201: SALE278 | B1201: 45798 | C1201: CUST1316 | D1201: PROD25 | E1201: STORE7 | F1201: 4 | G1201: 285.82 | H1201: 0.18 | I1201: PayPal | J1201: 937.4896 | K1201: =TEXT(B1201,"dd-mm-yyyy") -> 21-05-2025 | L1201: =TEXT(Sales_Fact!$B1201,"mmm") -> May | M1201: =IF(ISBLANK(F1201),1,F1201) -> 4 | N1201: =ROUNDUP(IF(ISBLANK(G1201),AVERAGE(C:C,G1201,G:G),G1201),2) -> 285.82 | O1201: =M1201*N1201*(1-H1201) -> 937.4896 | P1201: =M1201*N1201 -> 1143.28 | Q1201: =(P1201-O1201)/P1201 -> 0.18 | R1201: =IF(Sales_Fact!$O1201>1000,"High","Low") -> Low | S1201: =VLOOKUP(C1201,Customer_Dim!$A:$N,9,FALSE()) -> Robert House | T1201: =VLOOKUP(D1201,Product_Dim!$A:$M,3,FALSE()) -> Clothing | U1201: =VLOOKUP(D1201,Product_Dim!$A:$M,2,FALSE()) -> Women's Scarf Set | V1201: =VLOOKUP(E1201,Store_Dim!$A:$E,3,FALSE()) -> South | W1201: =VLOOKUP(C1201,Customer_Dim!$A:$N,13,FALSE()) -> Gold | X1201: =IF(F1201>3,"High","Low") -> High
A1202: SALE279 | B1202: 45868 | C1202: CUST1326 | D1202: PROD37 | E1202: STORE11 | F1202: 3 | G1202: 995.38 | H1202: 0.1 | I1202: PayPal | J1202: 2687.526 | K1202: =TEXT(B1202,"dd-mm-yyyy") -> 30-07-2025 | L1202: =TEXT(Sales_Fact!$B1202,"mmm") -> Jul | M1202: =IF(ISBLANK(F1202),1,F1202) -> 3 | N1202: =ROUNDUP(IF(ISBLANK(G1202),AVERAGE(C:C,G1202,G:G),G1202),2) -> 995.38 | O1202: =M1202*N1202*(1-H1202) -> 2687.526 | P1202: =M1202*N1202 -> 2986.14 | Q1202: =(P1202-O1202)/P1202 -> 0.1 | R1202: =IF(Sales_Fact!$O1202>1000,"High","Low") -> High | S1202: =VLOOKUP(C1202,Customer_Dim!$A:$N,9,FALSE()) -> Robert King | T1202: =VLOOKUP(D1202,Product_Dim!$A:$M,3,FALSE()) -> Clothing | U1202: =VLOOKUP(D1202,Product_Dim!$A:$M,2,FALSE()) -> Men's Casual Sneakers | V1202: =VLOOKUP(E1202,Store_Dim!$A:$E,3,FALSE()) -> South | W1202: =VLOOKUP(C1202,Customer_Dim!$A:$N,13,FALSE()) -> Gold | X1202: =IF(F1202>3,"High","Low") -> Low
... A1213: SALE289 | B1213: 45438 | C1213: CUST1263 | D1213: PROD65 | E1213: STORE7 | F1213: 1 | G1213: 203.61 | H1213: 0.24 | I1213: COD | J1213: 154.7436 | K1213: =TEXT(B1213,"dd-mm-yyyy") -> 26-05-2024 | L1213: =TEXT(Sales_Fact!$B1213,"mmm") -> May | M1213: =IF(ISBLANK(F1213),1,F1213) -> 1 | N1213: =ROUNDUP(IF(ISBLANK(G1213),AVERAGE(C:C,G1213,G:G),G1213),2) -> 203.61 | O1213: =M1213*N1213*(1-H1213) -> 154.7436 | P1213: =M1213*N1213 -> 203.61 | Q1213: =(P1213-O1213)/P1213 -> 0.24 | R1213: =IF(Sales_Fact!$O1213>1000,"High","Low") -> Low | S1213: =VLOOKUP(C1213,Customer_Dim!$A:$N,9,FALSE()) -> Crystal Davis | T1213: =VLOOKUP(D1213,Product_Dim!$A:$M,3,FALSE()) -> Sports | U1213: =VLOOKUP(D1213,Product_Dim!$A:$M,2,FALSE()) -> Adjustable Dumbbells 20kg | V1213: =VLOOKUP(E1213,Store_Dim!$A:$E,3,FALSE()) -> South | W1213: =VLOOKUP(C1213,Customer_Dim!$A:$N,13,FALSE()) -> Bronze | X1213: =IF(F1213>3,"High","Low") -> Low
A1214: SALE29 | B1214: 45302 | C1214: CUST1348 | D1214: PROD99 | E1214: STORE3 | G1214: 451.67 | H1214: 0.15 | I1214: Credit Card | J1214: 1535.678 | K1214: =TEXT(B1214,"dd-mm-yyyy") -> 11-01-2024 | L1214: =TEXT(Sales_Fact!$B1214,"mmm") -> Jan | M1214: =IF(ISBLANK(F1214),1,F1214) -> 1 | N1214: =ROUNDUP(IF(ISBLANK(G1214),AVERAGE(C:C,G1214,G:G),G1214),2) -> 451.67 | O1214: =M1214*N1214*(1-H1214) -> 383.9195 | P1214: =M1214*N1214 -> 451.67 | Q1214: =(P1214-O1214)/P1214 -> 0.15 | R1214: =IF(Sales_Fact!$O1214>1000,"High","Low") -> Low | S1214: =VLOOKUP(C1214,Customer_Dim!$A:$N,9,FALSE()) -> Sherry Cabrera | T1214: =VLOOKUP(D1214,Product_Dim!$A:$M,3,FALSE()) -> Home | U1214: =VLOOKUP(D1214,Product_Dim!$A:$M,2,FALSE()) -> Stainless Steel Cookware Set | V1214: =VLOOKUP(E1214,Store_Dim!$A:$E,3,FALSE()) -> North | W1214: =VLOOKUP(C1214,Customer_Dim!$A:$N,13,FALSE()) -> Silver | X1214: =IF(F1214>3,"High","Low") -> Low
A1215: SALE290 | B1215: 45856 | C1215: CUST1417 | D1215: PROD97 | E1215: STORE15 | F1215: 4 | G1215: 493.8 | H1215: 0.24 | I1215: COD | J1215: 1501.152 | K1215: =TEXT(B1215,"dd-mm-yyyy") -> 18-07-2025 | L1215: =TEXT(Sales_Fact!$B1215,"mmm") -> Jul | M1215: =IF(ISBLANK(F1215),1,F1215) -> 4 | N1215: =ROUNDUP(IF(ISBLANK(G1215),AVERAGE(C:C,G1215,G:G),G1215),2) -> 493.8 | O1215: =M1215*N1215*(1-H1215) -> 1501.152 | P1215: =M1215*N1215 -> 1975.2 | Q1215: =(P1215-O1215)/P1215 -> 0.24 | R1215: =IF(Sales_Fact!$O1215>1000,"High","Low") -> High | S1215: =VLOOKUP(C1215,Customer_Dim!$A:$N,9,FALSE()) -> Karen King | T1215: =VLOOKUP(D1215,Product_Dim!$A:$M,3,FALSE()) -> Sports | U1215: =VLOOKUP(D1215,Product_Dim!$A:$M,2,FALSE()) -> Cricket Bat | V1215: =VLOOKUP(E1215,Store_Dim!$A:$E,3,FALSE()) -> North | W1215: =VLOOKUP(C1215,Customer_Dim!$A:$N,13,FALSE()) -> Bronze | X1215: =IF(F1215>3,"High","Low") -> High
A1216: SALE291 | B1216: 45485 | C1216: CUST1017 | D1216: PROD41 | E1216: STORE17 | F1216: 1 | G1216: 640.55 | H1216: 0.25 | I1216: Credit Card | J1216: 480.4125 | K1216: =TEXT(B1216,"dd-mm-yyyy") -> 12-07-2024 | L1216: =TEXT(Sales_Fact!$B1216,"mmm") -> Jul | M1216: =IF(ISBLANK(F1216),1,F1216) -> 1 | N1216: =ROUNDUP(IF(ISBLANK(G1216),AVERAGE(C:C,G1216,G:G),G1216),2) -> 640.55 | O1216: =M1216*N1216*(1-H1216) -> 480.4125 | P1216: =M1216*N1216 -> 640.55 | Q1216: =(P1216-O1216)/P1216 -> 0.25 | R1216: =IF(Sales_Fact!$O1216>1000,"High","Low") -> Low | S1216: =VLOOKUP(C1216,Customer_Dim!$A:$N,9,FALSE()) -> Adam Cruz | T1216: =VLOOKUP(D1216,Product_Dim!$A:$M,3,FALSE()) -> Sports | U1216: =VLOOKUP(D1216,Product_Dim!$A:$M,2,FALSE()) -> Yoga Exercise Mat | V1216: =VLOOKUP(E1216,Store_Dim!$A:$E,3,FALSE()) -> North | W1216: =VLOOKUP(C1216,Customer_Dim!$A:$N,13,FALSE()) -> Platinum | X1216: =IF(F1216>3,"High","Low") -> Low
A1217: SALE292 | B1217: 45545 | C1217: CUST1119 | D1217: PROD74 | E1217: STORE4 | F1217: 1 | G1217: 702.53 | H1217: 0.3 | I1217: Credit Card | J1217: 491.771 | K1217: =TEXT(B1217,"dd-mm-yyyy") -> 10-09-2024 | L1217: =TEXT(Sales_Fact!$B1217,"mmm") -> Sep | M1217: =IF(ISBLANK(F1217),1,F1217) -> 1 | N1217: =ROUNDUP(IF(ISBLANK(G1217),AVERAGE(C:C,G1217,G:G),G1217),2) -> 702.53 | O1217: =M1217*N1217*(1-H1217) -> 491.771 | P1217: =M1217*N1217 -> 702.53 | Q1217: =(P1217-O1217)/P1217 -> 0.3 | R1217: =IF(Sales_Fact!$O1217>1000,"High","Low") -> Low | S1217: =VLOOKUP(C1217,Customer_Dim!$A:$N,9,FALSE()) -> Michael Jones | T1217: =VLOOKUP(D1217,Product_Dim!$A:$M,3,FALSE()) -> Electronics | U1217: =VLOOKUP(D1217,Product_Dim!$A:$M,2,FALSE()) -> Bluetooth Car Audio System | V1217: =VLOOKUP(E1217,Store_Dim!$A:$E,3,FALSE()) -> South | W1217: =VLOOKUP(C1217,Customer_Dim!$A:$N,13,FALSE()) -> Bronze | X1217: =IF(F1217>3,"High","Low") -> Low
A1218: SALE293 | B1218: 45826 | C1218: CUST1224 | D1218: PROD39 | E1218: STORE8 | F1218: 4 | G1218: 139.94 | H1218: 0.24 | I1218: Credit Card | J1218: 425.4176 | K1218: =TEXT(B1218,"dd-mm-yyyy") -> 18-06-2025 | L1218: =TEXT(Sales_Fact!$B1218,"mmm") -> Jun | M1218: =IF(ISBLANK(F1218),1,F1218) -> 4 | N1218: =ROUNDUP(IF(ISBLANK(G1218),AVERAGE(C:C,G1218,G:G),G1218),2) -> 139.94 | O1218: =M1218*N1218*(1-H1218) -> 425.4176 | P1218: =M1218*N1218 -> 559.76 | Q1218: =(P1218-O1218)/P1218 -> 0.24 | R1218: =IF(Sales_Fact!$O1218>1000,"High","Low") -> Low | S1218: =VLOOKUP(C1218,Customer_Dim!$A:$N,9,FALSE()) -> Anthony Morgan | T1218: =VLOOKUP(D1218,Product_Dim!$A:$M,3,FALSE()) -> Electronics | U1218: =VLOOKUP(D1218,Product_Dim!$A:$M,2,FALSE()) -> Portable Power Bank | V1218: =VLOOKUP(E1218,Store_Dim!$A:$E,3,FALSE()) -> West | W1218: =VLOOKUP(C1218,Customer_Dim!$A:$N,13,FALSE()) -> Silver | X1218: =IF(F1218>3,"High","Low") -> High
A1219: SALE294 | B1219: 45654 | C1219: CUST1277 | D1219: PROD19 | E1219: STORE8 | F1219: 2 | G1219: 230.85 | H1219: 0.18 | I1219: Credit Card | J1219: 378.594 | K1219: =TEXT(B1219,"dd-mm-yyyy") -> 28-12-2024 | L1219: =TEXT(Sales_Fact!$B1219,"mmm") -> Dec | M1219: =IF(ISBLANK(F1219),1,F1219) -> 2 | N1219: =ROUNDUP(IF(ISBLANK(G1219),AVERAGE(C:C,G1219,G:G),G1219),2) -> 230.85 | O1219: =M1219*N1219*(1-H1219) -> 378.594 | P1219: =M1219*N1219 -> 461.7 | Q1219: =(P1219-O1219)/P1219 -> 0.18 | R1219: =IF(Sales_Fact!$O1219>1000,"High","Low") -> Low | S1219: =VLOOKUP(C1219,Customer_Dim!$A:$N,9,FALSE()) -> Jeffrey Gomez | T1219: =VLOOKUP(D1219,Product_Dim!$A:$M,3,FALSE()) -> Sports | U1219: =VLOOKUP(D1219,Product_Dim!$A:$M,2,FALSE()) -> Knee Support Brace | V1219: =VLOOKUP(E1219,Store_Dim!$A:$E,3,FALSE()) -> West | W1219: =VLOOKUP(C1219,Customer_Dim!$A:$N,13,FALSE()) -> Platinum | X1219: =IF(F1219>3,"High","Low") -> Low
A1220: SALE295 | B1220: 45556 | C1220: CUST1211 | D1220: PROD85 | E1220: STORE17 | F1220: 4 | G1220: 626.35 | H1220: 0.25 | I1220: COD | J1220: 1879.05 | K1220: =TEXT(B1220,"dd-mm-yyyy") -> 21-09-2024 | L1220: =TEXT(Sales_Fact!$B1220,"mmm") -> Sep | M1220: =IF(ISBLANK(F1220),1,F1220) -> 4 | N1220: =ROUNDUP(IF(ISBLANK(G1220),AVERAGE(C:C,G1220,G:G),G1220),2) -> 626.35 | O1220: =M1220*N1220*(1-H1220) -> 1879.05 | P1220: =M1220*N1220 -> 2505.4 | Q1220: =(P1220-O1220)/P1220 -> 0.25 | R1220: =IF(Sales_Fact!$O1220>1000,"High","Low") -> High | S1220: =VLOOKUP(C1220,Customer_Dim!$A:$N,9,FALSE()) -> Rodney Huffman | T1220: =VLOOKUP(D1220,Product_Dim!$A:$M,3,FALSE()) -> Clothing | U1220: =VLOOKUP(D1220,Product_Dim!$A:$M,2,FALSE()) -> Women's Beanie Hat | V1220: =VLOOKUP(E1220,Store_Dim!$A:$E,3,FALSE()) -> North | W1220: =VLOOKUP(C1220,Customer_Dim!$A:$N,13,FALSE()) -> Silver | X1220: =IF(F1220>3,"High","Low") -> High
A1221: SALE296 | B1221: 45434 | C1221: CUST1082 | D1221: PROD41 | E1221: STORE14 | F1221: 4 | G1221: 108.55 | H1221: 0.18 | I1221: PayPal | J1221: 356.044 | K1221: =TEXT(B1221,"dd-mm-yyyy") -> 22-05-2024 | L1221: =TEXT(Sales_Fact!$B1221,"mmm") -> May | M1221: =IF(ISBLANK(F1221),1,F1221) -> 4 | N1221: =ROUNDUP(IF(ISBLANK(G1221),AVERAGE(C:C,G1221,G:G),G1221),2) -> 108.55 | O1221: =M1221*N1221*(1-H1221) -> 356.044 | P1221: =M1221*N1221 -> 434.2 | Q1221: =(P1221-O1221)/P1221 -> 0.18 | R1221: =IF(Sales_Fact!$O1221>1000,"High","Low") -> Low | S1221: =VLOOKUP(C1221,Customer_Dim!$A:$N,9,FALSE()) -> George Rosario | T1221: =VLOOKUP(D1221,Product_Dim!$A:$M,3,FALSE()) -> Sports | U1221: =VLOOKUP(D1221,Product_Dim!$A:$M,2,FALSE()) -> Yoga Exercise Mat | V1221: =VLOOKUP(E1221,Store_Dim!$A:$E,3,FALSE()) -> South | W1221: =VLOOKUP(C1221,Customer_Dim!$A:$N,13,FALSE()) -> Bronze | X1221: =IF(F1221>3,"High","Low") -> High
A1222: SALE297 | B1222: 45871 | C1222: CUST1191 | D1222: PROD17 | E1222: STORE1 | F1222: 4 | G1222: 353.67 | H1222: 0.03 | I1222: COD | J1222: 1372.2396 | K1222: =TEXT(B1222,"dd-mm-yyyy") -> 02-08-2025 | L1222: =TEXT(Sales_Fact!$B1222,"mmm") -> Aug | M1222: =IF(ISBLANK(F1222),1,F1222) -> 4 | N1222: =ROUNDUP(IF(ISBLANK(G1222),AVERAGE(C:C,G1222,G:G),G1222),2) -> 353.67 | O1222: =M1222*N1222*(1-H1222) -> 1372.2396 | P1222: =M1222*N1222 -> 1414.68 | Q1222: =(P1222-O1222)/P1222 -> 0.03 | R1222: =IF(Sales_Fact!$O1222>1000,"High","Low") -> High | S1222: =VLOOKUP(C1222,Customer_Dim!$A:$N,9,FALSE()) -> Todd Poole | T1222: =VLOOKUP(D1222,Product_Dim!$A:$M,3,FALSE()) -> Sports | U1222: =VLOOKUP(D1222,Product_Dim!$A:$M,2,FALSE()) -> Soccer Training Cone Set | V1222: =VLOOKUP(E1222,Store_Dim!$A:$E,3,FALSE()) -> North | W1222: =VLOOKUP(C1222,Customer_Dim!$A:$N,13,FALSE()) -> Bronze | X1222: =IF(F1222>3,"High","Low") -> High
A1223: SALE298 | B1223: 45583 | C1223: CUST1065 | D1223: PROD90 | E1223: STORE1 | F1223: 4 | G1223: 61.98 | H1223: 0.16 | I1223: Credit Card | J1223: 208.2528 | K1223: =TEXT(B1223,"dd-mm-yyyy") -> 18-10-2024 | L1223: =TEXT(Sales_Fact!$B1223,"mmm") -> Oct | M1223: =IF(ISBLANK(F1223),1,F1223) -> 4 | N1223: =ROUNDUP(IF(ISBLANK(G1223),AVERAGE(C:C,G1223,G:G),G1223),2) -> 61.98 | O1223: =M1223*N1223*(1-H1223) -> 208.2528 | P1223: =M1223*N1223 -> 247.92 | Q1223: =(P1223-O1223)/P1223 -> 0.16 | R1223: =IF(Sales_Fact!$O1223>1000,"High","Low") -> Low | S1223: =VLOOKUP(C1223,Customer_Dim!$A:$N,9,FALSE()) -> Michael Thomas | T1223: =VLOOKUP(D1223,Product_Dim!$A:$M,3,FALSE()) -> Electronics | U1223: =VLOOKUP(D1223,Product_Dim!$A:$M,2,FALSE()) -> Gaming Mouse Pad XL | V1223: =VLOOKUP(E1223,Store_Dim!$A:$E,3,FALSE()) -> North | W1223: =VLOOKUP(C1223,Customer_Dim!$A:$N,13,FALSE()) -> Silver | X1223: =IF(F1223>3,"High","Low") -> High
A1224: SALE299 | B1224: 45348 | C1224: CUST1216 | D1224: PROD22 | E1224: STORE19 | F1224: 2 | G1224: 873.1 | H1224: 0.12 | I1224: PayPal | J1224: 1536.656 | K1224: =TEXT(B1224,"dd-mm-yyyy") -> 26-02-2024 | L1224: =TEXT(Sales_Fact!$B1224,"mmm") -> Feb | M1224: =IF(ISBLANK(F1224),1,F1224) -> 2 | N1224: =ROUNDUP(IF(ISBLANK(G1224),AVERAGE(C:C,G1224,G:G),G1224),2) -> 873.1 | O1224: =M1224*N1224*(1-H1224) -> 1536.656 | P1224: =M1224*N1224 -> 1746.2 | Q1224: =(P1224-O1224)/P1224 -> 0.12 | R1224: =IF(Sales_Fact!$O1224>1000,"High","Low") -> High | S1224: =VLOOKUP(C1224,Customer_Dim!$A:$N,9,FALSE()) -> Kathryn Garcia | T1224: =VLOOKUP(D1224,Product_Dim!$A:$M,3,FALSE()) -> Sports | U1224: =VLOOKUP(D1224,Product_Dim!$A:$M,2,FALSE()) -> Carbon Fiber Tennis Racket | V1224: =VLOOKUP(E1224,Store_Dim!$A:$E,3,FALSE()) -> East | W1224: =VLOOKUP(C1224,Customer_Dim!$A:$N,13,FALSE()) -> Platinum | X1224: =IF(F1224>3,"High","Low") -> Low
A1225: SALE3 | B1225: 45259 | C1225: CUST1346 | D1225: PROD90 | E1225: STORE8 | F1225: 1 | G1225: 921.51 | H1225: 0.16 | I1225: COD | J1225: 774.0684 | K1225: =TEXT(B1225,"dd-mm-yyyy") -> 29-11-2023 | L1225: =TEXT(Sales_Fact!$B1225,"mmm") -> Nov | M1225: =IF(ISBLANK(F1225),1,F1225) -> 1 | N1225: =ROUNDUP(IF(ISBLANK(G1225),AVERAGE(C:C,G1225,G:G),G1225),2) -> 921.51 | O1225: =M1225*N1225*(1-H1225) -> 774.0684 | P1225: =M1225*N1225 -> 921.51 | Q1225: =(P1225-O1225)/P1225 -> 0.16 | R1225: =IF(Sales_Fact!$O1225>1000,"High","Low") -> Low | S1225: =VLOOKUP(C1225,Customer_Dim!$A:$N,9,FALSE()) -> John Jordan | T1225: =VLOOKUP(D1225,Product_Dim!$A:$M,3,FALSE()) -> Electronics | U1225: =VLOOKUP(D1225,Product_Dim!$A:$M,2,FALSE()) -> Gaming Mouse Pad XL | V1225: =VLOOKUP(E1225,Store_Dim!$A:$E,3,FALSE()) -> West | W1225: =VLOOKUP(C1225,Customer_Dim!$A:$N,13,FALSE()) -> Platinum | X1225: =IF(F1225>3,"High","Low") -> Low
A1226: SALE30 | B1226: 45217 | C1226: CUST1028 | D1226: PROD5 | E1226: STORE19 | F1226: 1 | G1226: 429.38 | H1226: 0.13 | I1226: PayPal | J1226: 373.5606 | K1226: =TEXT(B1226,"dd-mm-yyyy") -> 18-10-2023 | L1226: =TEXT(Sales_Fact!$B1226,"mmm") -> Oct | M1226: =IF(ISBLANK(F1226),1,F1226) -> 1 | N1226: =ROUNDUP(IF(ISBLANK(G1226),AVERAGE(C:C,G1226,G:G),G1226),2) -> 429.38 | O1226: =M1226*N1226*(1-H1226) -> 373.5606 | P1226: =M1226*N1226 -> 429.38 | Q1226: =(P1226-O1226)/P1226 -> 0.13 | R1226: =IF(Sales_Fact!$O1226>1000,"High","Low") -> Low | S1226: =VLOOKUP(C1226,Customer_Dim!$A:$N,9,FALSE()) -> Joshua Ryan | T1226: =VLOOKUP(D1226,Product_Dim!$A:$M,3,FALSE()) -> Clothing | U1226: =VLOOKUP(D1226,Product_Dim!$A:$M,2,FALSE()) -> Men's Leather Belt | V1226: =VLOOKUP(E1226,Store_Dim!$A:$E,3,FALSE()) -> East | W1226: =VLOOKUP(C1226,Customer_Dim!$A:$N,13,FALSE()) -> Platinum | X1226: =IF(F1226>3,"High","Low") -> Low
... A1269: SALE339 | B1269: 45303 | C1269: CUST1222 | D1269: PROD46 | E1269: STORE6 | F1269: 4 | G1269: 344.12 | H1269: 0.25 | I1269: PayPal | J1269: 1032.36 | K1269: =TEXT(B1269,"dd-mm-yyyy") -> 12-01-2024 | L1269: =TEXT(Sales_Fact!$B1269,"mmm") -> Jan | M1269: =IF(ISBLANK(F1269),1,F1269) -> 4 | N1269: =ROUNDUP(IF(ISBLANK(G1269),AVERAGE(C:C,G1269,G:G),G1269),2) -> 344.12 | O1269: =M1269*N1269*(1-H1269) -> 1032.36 | P1269: =M1269*N1269 -> 1376.48 | Q1269: =(P1269-O1269)/P1269 -> 0.25 | R1269: =IF(Sales_Fact!$O1269>1000,"High","Low") -> High | S1269: =VLOOKUP(C1269,Customer_Dim!$A:$N,9,FALSE()) -> Alejandro Doyle | T1269: =VLOOKUP(D1269,Product_Dim!$A:$M,3,FALSE()) -> Clothing | U1269: =VLOOKUP(D1269,Product_Dim!$A:$M,2,FALSE()) -> Men's Winter Jacket | V1269: =VLOOKUP(E1269,Store_Dim!$A:$E,3,FALSE()) -> East | W1269: =VLOOKUP(C1269,Customer_Dim!$A:$N,13,FALSE()) -> Platinum | X1269: =IF(F1269>3,"High","Low") -> High
A1270: SALE34 | B1270: 45215 | C1270: CUST1344 | D1270: PROD79 | E1270: STORE1 | G1270: 873.22 | H1270: 0.18 | I1270: Credit Card | J1270: 2148.1212 | K1270: =TEXT(B1270,"dd-mm-yyyy") -> 16-10-2023 | L1270: =TEXT(Sales_Fact!$B1270,"mmm") -> Oct | M1270: =IF(ISBLANK(F1270),1,F1270) -> 1 | N1270: =ROUNDUP(IF(ISBLANK(G1270),AVERAGE(C:C,G1270,G:G),G1270),2) -> 873.22 | O1270: =M1270*N1270*(1-H1270) -> 716.0404 | P1270: =M1270*N1270 -> 873.22 | Q1270: =(P1270-O1270)/P1270 -> 0.18 | R1270: =IF(Sales_Fact!$O1270>1000,"High","Low") -> Low | S1270: =VLOOKUP(C1270,Customer_Dim!$A:$N,9,FALSE()) -> Evelyn Brown | T1270: =VLOOKUP(D1270,Product_Dim!$A:$M,3,FALSE()) -> Home | U1270: =VLOOKUP(D1270,Product_Dim!$A:$M,2,FALSE()) -> Decorative Lamp Shade | V1270: =VLOOKUP(E1270,Store_Dim!$A:$E,3,FALSE()) -> North | W1270: =VLOOKUP(C1270,Customer_Dim!$A:$N,13,FALSE()) -> Gold | X1270: =IF(F1270>3,"High","Low") -> Low
A1271: SALE340 | B1271: 45218 | C1271: CUST1047 | D1271: PROD17 | E1271: STORE19 | F1271: 3 | G1271: 997.95 | H1271: 0.09 | I1271: COD | J1271: 2724.4035 | K1271: =TEXT(B1271,"dd-mm-yyyy") -> 19-10-2023 | L1271: =TEXT(Sales_Fact!$B1271,"mmm") -> Oct | M1271: =IF(ISBLANK(F1271),1,F1271) -> 3 | N1271: =ROUNDUP(IF(ISBLANK(G1271),AVERAGE(C:C,G1271,G:G),G1271),2) -> 997.95 | O1271: =M1271*N1271*(1-H1271) -> 2724.4035 | P1271: =M1271*N1271 -> 2993.85 | Q1271: =(P1271-O1271)/P1271 -> 0.09 | R1271: =IF(Sales_Fact!$O1271>1000,"High","Low") -> High | S1271: =VLOOKUP(C1271,Customer_Dim!$A:$N,9,FALSE()) -> Gina Knight | T1271: =VLOOKUP(D1271,Product_Dim!$A:$M,3,FALSE()) -> Sports | U1271: =VLOOKUP(D1271,Product_Dim!$A:$M,2,FALSE()) -> Soccer Training Cone Set | V1271: =VLOOKUP(E1271,Store_Dim!$A:$E,3,FALSE()) -> East | W1271: =VLOOKUP(C1271,Customer_Dim!$A:$N,13,FALSE()) -> Silver | X1271: =IF(F1271>3,"High","Low") -> Low
A1272: SALE341 | B1272: 45727 | C1272: CUST1150 | D1272: PROD11 | E1272: STORE15 | F1272: 3 | G1272: 121.64 | H1272: 0.07 | I1272: PayPal | J1272: 339.3756 | K1272: =TEXT(B1272,"dd-mm-yyyy") -> 11-03-2025 | L1272: =TEXT(Sales_Fact!$B1272,"mmm") -> Mar | M1272: =IF(ISBLANK(F1272),1,F1272) -> 3 | N1272: =ROUNDUP(IF(ISBLANK(G1272),AVERAGE(C:C,G1272,G:G),G1272),2) -> 121.64 | O1272: =M1272*N1272*(1-H1272) -> 339.3756 | P1272: =M1272*N1272 -> 364.92 | Q1272: =(P1272-O1272)/P1272 -> 0.07 | R1272: =IF(Sales_Fact!$O1272>1000,"High","Low") -> Low | S1272: =VLOOKUP(C1272,Customer_Dim!$A:$N,9,FALSE()) -> Stephanie Conway | T1272: =VLOOKUP(D1272,Product_Dim!$A:$M,3,FALSE()) -> Electronics | U1272: =VLOOKUP(D1272,Product_Dim!$A:$M,2,FALSE()) -> HD Smart TV Stick | V1272: =VLOOKUP(E1272,Store_Dim!$A:$E,3,FALSE()) -> North | W1272: =VLOOKUP(C1272,Customer_Dim!$A:$N,13,FALSE()) -> Gold | X1272: =IF(F1272>3,"High","Low") -> Low
A1273: SALE342 | B1273: 45557 | C1273: CUST1221 | D1273: PROD68 | E1273: STORE10 | F1273: 2 | G1273: 692.72 | H1273: 0.13 | I1273: PayPal | J1273: 1205.3328 | K1273: =TEXT(B1273,"dd-mm-yyyy") -> 22-09-2024 | L1273: =TEXT(Sales_Fact!$B1273,"mmm") -> Sep | M1273: =IF(ISBLANK(F1273),1,F1273) -> 2 | N1273: =ROUNDUP(IF(ISBLANK(G1273),AVERAGE(C:C,G1273,G:G),G1273),2) -> 692.72 | O1273: =M1273*N1273*(1-H1273) -> 1205.3328 | P1273: =M1273*N1273 -> 1385.44 | Q1273: =(P1273-O1273)/P1273 -> 0.13 | R1273: =IF(Sales_Fact!$O1273>1000,"High","Low") -> High | S1273: =VLOOKUP(C1273,Customer_Dim!$A:$N,9,FALSE()) -> Lisa Young | T1273: =VLOOKUP(D1273,Product_Dim!$A:$M,3,FALSE()) -> Home | U1273: =VLOOKUP(D1273,Product_Dim!$A:$M,2,FALSE()) -> Wooden Nightstand | V1273: =VLOOKUP(E1273,Store_Dim!$A:$E,3,FALSE()) -> East | W1273: =VLOOKUP(C1273,Customer_Dim!$A:$N,13,FALSE()) -> Platinum | X1273: =IF(F1273>3,"High","Low") -> Low
A1274: SALE343 | B1274: 45623 | C1274: CUST1027 | D1274: PROD24 | E1274: STORE19 | F1274: 3 | G1274: 794.59 | H1274: 0.03 | I1274: PayPal | J1274: 2312.2569 | K1274: =TEXT(B1274,"dd-mm-yyyy") -> 27-11-2024 | L1274: =TEXT(Sales_Fact!$B1274,"mmm") -> Nov | M1274: =IF(ISBLANK(F1274),1,F1274) -> 3 | N1274: =ROUNDUP(IF(ISBLANK(G1274),AVERAGE(C:C,G1274,G:G),G1274),2) -> 794.59 | O1274: =M1274*N1274*(1-H1274) -> 2312.2569 | P1274: =M1274*N1274 -> 2383.77 | Q1274: =(P1274-O1274)/P1274 -> 0.03 | R1274: =IF(Sales_Fact!$O1274>1000,"High","Low") -> High | S1274: =VLOOKUP(C1274,Customer_Dim!$A:$N,9,FALSE()) -> Leslie Johnson | T1274: =VLOOKUP(D1274,Product_Dim!$A:$M,3,FALSE()) -> Sports | U1274: =VLOOKUP(D1274,Product_Dim!$A:$M,2,FALSE()) -> Foldable Camping Chair | V1274: =VLOOKUP(E1274,Store_Dim!$A:$E,3,FALSE()) -> East | W1274: =VLOOKUP(C1274,Customer_Dim!$A:$N,13,FALSE()) -> Standard | X1274: =IF(F1274>3,"High","Low") -> Low
A1275: SALE344 | B1275: 45224 | C1275: CUST1014 | D1275: PROD26 | E1275: STORE9 | F1275: 1 | G1275: 907.95 | H1275: 0.1 | I1275: PayPal | J1275: 817.155 | K1275: =TEXT(B1275,"dd-mm-yyyy") -> 25-10-2023 | L1275: =TEXT(Sales_Fact!$B1275,"mmm") -> Oct | M1275: =IF(ISBLANK(F1275),1,F1275) -> 1 | N1275: =ROUNDUP(IF(ISBLANK(G1275),AVERAGE(C:C,G1275,G:G),G1275),2) -> 907.95 | O1275: =M1275*N1275*(1-H1275) -> 817.155 | P1275: =M1275*N1275 -> 907.95 | Q1275: =(P1275-O1275)/P1275 -> 0.1 | R1275: =IF(Sales_Fact!$O1275>1000,"High","Low") -> Low | S1275: =VLOOKUP(C1275,Customer_Dim!$A:$N,9,FALSE()) -> Ashley Cohen | T1275: =VLOOKUP(D1275,Product_Dim!$A:$M,3,FALSE()) -> Electronics | U1275: =VLOOKUP(D1275,Product_Dim!$A:$M,2,FALSE()) -> Wireless Bluetooth Speaker | V1275: =VLOOKUP(E1275,Store_Dim!$A:$E,3,FALSE()) -> South | W1275: =VLOOKUP(C1275,Customer_Dim!$A:$N,13,FALSE()) -> Silver | X1275: =IF(F1275>3,"High","Low") -> Low
A1276: SALE345 | B1276: 45940 | C1276: CUST1287 | D1276: PROD50 | E1276: STORE0 | F1276: 2 | G1276: 660.81 | H1276: 0.18 | I1276: Credit Card | J1276: 1083.7284 | K1276: =TEXT(B1276,"dd-mm-yyyy") -> 10-10-2025 | L1276: =TEXT(Sales_Fact!$B1276,"mmm") -> Oct | M1276: =IF(ISBLANK(F1276),1,F1276) -> 2 | N1276: =ROUNDUP(IF(ISBLANK(G1276),AVERAGE(C:C,G1276,G:G),G1276),2) -> 660.81 | O1276: =M1276*N1276*(1-H1276) -> 1083.7284 | P1276: =M1276*N1276 -> 1321.62 | Q1276: =(P1276-O1276)/P1276 -> 0.18 | R1276: =IF(Sales_Fact!$O1276>1000,"High","Low") -> High | S1276: =VLOOKUP(C1276,Customer_Dim!$A:$N,9,FALSE()) -> Cynthia Roberts | T1276: =VLOOKUP(D1276,Product_Dim!$A:$M,3,FALSE()) -> Sports | U1276: =VLOOKUP(D1276,Product_Dim!$A:$M,2,FALSE()) -> Boxing Hand Wraps | V1276: =VLOOKUP(E1276,Store_Dim!$A:$E,3,FALSE()) -> East | W1276: =VLOOKUP(C1276,Customer_Dim!$A:$N,13,FALSE()) -> Gold | X1276: =IF(F1276>3,"High","Low") -> Low
A1277: SALE346 | B1277: 45915 | C1277: CUST1061 | D1277: PROD51 | E1277: STORE8 | F1277: 3 | G1277: 564.94 | H1277: 0.22 | I1277: COD | J1277: 1321.9596 | K1277: =TEXT(B1277,"dd-mm-yyyy") -> 15-09-2025 | L1277: =TEXT(Sales_Fact!$B1277,"mmm") -> Sep | M1277: =IF(ISBLANK(F1277),1,F1277) -> 3 | N1277: =ROUNDUP(IF(ISBLANK(G1277),AVERAGE(C:C,G1277,G:G),G1277),2) -> 564.94 | O1277: =M1277*N1277*(1-H1277) -> 1321.9596 | P1277: =M1277*N1277 -> 1694.82 | Q1277: =(P1277-O1277)/P1277 -> 0.22 | R1277: =IF(Sales_Fact!$O1277>1000,"High","Low") -> High | S1277: =VLOOKUP(C1277,Customer_Dim!$A:$N,9,FALSE()) -> Kristin Stein | T1277: =VLOOKUP(D1277,Product_Dim!$A:$M,3,FALSE()) -> Electronics | U1277: =VLOOKUP(D1277,Product_Dim!$A:$M,2,FALSE()) -> HDMI Cable – 2m | V1277: =VLOOKUP(E1277,Store_Dim!$A:$E,3,FALSE()) -> West | W1277: =VLOOKUP(C1277,Customer_Dim!$A:$N,13,FALSE()) -> Silver | X1277: =IF(F1277>3,"High","Low") -> Low
A1278: SALE347 | B1278: 45541 | C1278: CUST1054 | D1278: PROD15 | E1278: STORE15 | F1278: 2 | G1278: 280.37 | H1278: 0.22 | I1278: COD | J1278: 437.3772 | K1278: =TEXT(B1278,"dd-mm-yyyy") -> 06-09-2024 | L1278: =TEXT(Sales_Fact!$B1278,"mmm") -> Sep | M1278: =IF(ISBLANK(F1278),1,F1278) -> 2 | N1278: =ROUNDUP(IF(ISBLANK(G1278),AVERAGE(C:C,G1278,G:G),G1278),2) -> 280.37 | O1278: =M1278*N1278*(1-H1278) -> 437.3772 | P1278: =M1278*N1278 -> 560.74 | Q1278: =(P1278-O1278)/P1278 -> 0.22 | R1278: =IF(Sales_Fact!$O1278>1000,"High","Low") -> Low | S1278: =VLOOKUP(C1278,Customer_Dim!$A:$N,9,FALSE()) -> Katherine Dorsey | T1278: =VLOOKUP(D1278,Product_Dim!$A:$M,3,FALSE()) -> Electronics | U1278: =VLOOKUP(D1278,Product_Dim!$A:$M,2,FALSE()) -> 4K Home Projector | V1278: =VLOOKUP(E1278,Store_Dim!$A:$E,3,FALSE()) -> North | W1278: =VLOOKUP(C1278,Customer_Dim!$A:$N,13,FALSE()) -> Platinum | X1278: =IF(F1278>3,"High","Low") -> Low
A1279: SALE348 | B1279: 45489 | C1279: CUST1372 | D1279: PROD50 | E1279: STORE3 | F1279: 2 | G1279: 85.23 | H1279: 0.13 | I1279: Credit Card | J1279: 148.3002 | K1279: =TEXT(B1279,"dd-mm-yyyy") -> 16-07-2024 | L1279: =TEXT(Sales_Fact!$B1279,"mmm") -> Jul | M1279: =IF(ISBLANK(F1279),1,F1279) -> 2 | N1279: =ROUNDUP(IF(ISBLANK(G1279),AVERAGE(C:C,G1279,G:G),G1279),2) -> 85.23 | O1279: =M1279*N1279*(1-H1279) -> 148.3002 | P1279: =M1279*N1279 -> 170.46 | Q1279: =(P1279-O1279)/P1279 -> 0.13 | R1279: =IF(Sales_Fact!$O1279>1000,"High","Low") -> Low | S1279: =VLOOKUP(C1279,Customer_Dim!$A:$N,9,FALSE()) -> Jacqueline Anthony | T1279: =VLOOKUP(D1279,Product_Dim!$A:$M,3,FALSE()) -> Sports | U1279: =VLOOKUP(D1279,Product_Dim!$A:$M,2,FALSE()) -> Boxing Hand Wraps | V1279: =VLOOKUP(E1279,Store_Dim!$A:$E,3,FALSE()) -> North | W1279: =VLOOKUP(C1279,Customer_Dim!$A:$N,13,FALSE()) -> Bronze | X1279: =IF(F1279>3,"High","Low") -> Low
A1280: SALE349 | B1280: 45748 | C1280: CUST1312 | D1280: PROD27 | E1280: STORE13 | F1280: 2 | G1280: 563.3 | H1280: 0.26 | I1280: Credit Card | J1280: 833.684 | K1280: =TEXT(B1280,"dd-mm-yyyy") -> 01-04-2025 | L1280: =TEXT(Sales_Fact!$B1280,"mmm") -> Apr | M1280: =IF(ISBLANK(F1280),1,F1280) -> 2 | N1280: =ROUNDUP(IF(ISBLANK(G1280),AVERAGE(C:C,G1280,G:G),G1280),2) -> 563.3 | O1280: =M1280*N1280*(1-H1280) -> 833.684 | P1280: =M1280*N1280 -> 1126.6 | Q1280: =(P1280-O1280)/P1280 -> 0.26 | R1280: =IF(Sales_Fact!$O1280>1000,"High","Low") -> Low | S1280: =VLOOKUP(C1280,Customer_Dim!$A:$N,9,FALSE()) -> Jason Mullins | T1280: =VLOOKUP(D1280,Product_Dim!$A:$M,3,FALSE()) -> Home | U1280: =VLOOKUP(D1280,Product_Dim!$A:$M,2,FALSE()) -> Decorative Floor Vase | V1280: =VLOOKUP(E1280,Store_Dim!$A:$E,3,FALSE()) -> East | W1280: =VLOOKUP(C1280,Customer_Dim!$A:$N,13,FALSE()) -> Silver | X1280: =IF(F1280>3,"High","Low") -> Low
A1281: SALE35 | B1281: 45878 | C1281: CUST1218 | D1281: PROD16 | E1281: STORE3 | F1281: 4 | G1281: 109.36 | H1281: 0.19 | I1281: COD | J1281: 354.3264 | K1281: =TEXT(B1281,"dd-mm-yyyy") -> 09-08-2025 | L1281: =TEXT(Sales_Fact!$B1281,"mmm") -> Aug | M1281: =IF(ISBLANK(F1281),1,F1281) -> 4 | N1281: =ROUNDUP(IF(ISBLANK(G1281),AVERAGE(C:C,G1281,G:G),G1281),2) -> 109.36 | O1281: =M1281*N1281*(1-H1281) -> 354.3264 | P1281: =M1281*N1281 -> 437.44 | Q1281: =(P1281-O1281)/P1281 -> 0.19 | R1281: =IF(Sales_Fact!$O1281>1000,"High","Low") -> Low | S1281: =VLOOKUP(C1281,Customer_Dim!$A:$N,9,FALSE()) -> Julia Jackson | T1281: =VLOOKUP(D1281,Product_Dim!$A:$M,3,FALSE()) -> Beauty | U1281: =VLOOKUP(D1281,Product_Dim!$A:$M,2,FALSE()) -> Beard Grooming Kit | V1281: =VLOOKUP(E1281,Store_Dim!$A:$E,3,FALSE()) -> North | W1281: =VLOOKUP(C1281,Customer_Dim!$A:$N,13,FALSE()) -> Platinum | X1281: =IF(F1281>3,"High","Low") -> High
A1282: SALE350 | B1282: 45309 | C1282: CUST1033 | D1282: PROD80 | E1282: STORE18 | F1282: 2 | G1282: 827.81 | H1282: 0.04 | I1282: PayPal | J1282: 1589.3952 | K1282: =TEXT(B1282,"dd-mm-yyyy") -> 18-01-2024 | L1282: =TEXT(Sales_Fact!$B1282,"mmm") -> Jan | M1282: =IF(ISBLANK(F1282),1,F1282) -> 2 | N1282: =ROUNDUP(IF(ISBLANK(G1282),AVERAGE(C:C,G1282,G:G),G1282),2) -> 827.81 | O1282: =M1282*N1282*(1-H1282) -> 1589.3952 | P1282: =M1282*N1282 -> 1655.62 | Q1282: =(P1282-O1282)/P1282 -> 0.04 | R1282: =IF(Sales_Fact!$O1282>1000,"High","Low") -> High | S1282: =VLOOKUP(C1282,Customer_Dim!$A:$N,9,FALSE()) -> Robert Jones Dds | T1282: =VLOOKUP(D1282,Product_Dim!$A:$M,3,FALSE()) -> Home | U1282: =VLOOKUP(D1282,Product_Dim!$A:$M,2,FALSE()) -> Wall-Mounted Spice Rack | V1282: =VLOOKUP(E1282,Store_Dim!$A:$E,3,FALSE()) -> East | W1282: =VLOOKUP(C1282,Customer_Dim!$A:$N,13,FALSE()) -> Platinum | X1282: =IF(F1282>3,"High","Low") -> Low
... A1369: SALE429 | B1369: 45731 | C1369: CUST1183 | D1369: PROD7 | E1369: STORE4 | F1369: 4 | G1369: 149.83 | H1369: 0.02 | I1369: Credit Card | J1369: 587.3336 | K1369: =TEXT(B1369,"dd-mm-yyyy") -> 15-03-2025 | L1369: =TEXT(Sales_Fact!$B1369,"mmm") -> Mar | M1369: =IF(ISBLANK(F1369),1,F1369) -> 4 | N1369: =ROUNDUP(IF(ISBLANK(G1369),AVERAGE(C:C,G1369,G:G),G1369),2) -> 149.83 | O1369: =M1369*N1369*(1-H1369) -> 587.3336 | P1369: =M1369*N1369 -> 599.32 | Q1369: =(P1369-O1369)/P1369 -> 0.02 | R1369: =IF(Sales_Fact!$O1369>1000,"High","Low") -> Low | S1369: =VLOOKUP(C1369,Customer_Dim!$A:$N,9,FALSE()) -> Mario Jacobs | T1369: =VLOOKUP(D1369,Product_Dim!$A:$M,3,FALSE()) -> Home | U1369: =VLOOKUP(D1369,Product_Dim!$A:$M,2,FALSE()) -> LED Table Lamp | V1369: =VLOOKUP(E1369,Store_Dim!$A:$E,3,FALSE()) -> South | W1369: =VLOOKUP(C1369,Customer_Dim!$A:$N,13,FALSE()) -> Platinum | X1369: =IF(F1369>3,"High","Low") -> High
A1370: SALE43 | B1370: 45677 | C1370: CUST1084 | D1370: PROD33 | E1370: STORE17 | G1370: 863.11 | H1370: 0.28 | I1370: PayPal | J1370: 1864.3176 | K1370: =TEXT(B1370,"dd-mm-yyyy") -> 20-01-2025 | L1370: =TEXT(Sales_Fact!$B1370,"mmm") -> Jan | M1370: =IF(ISBLANK(F1370),1,F1370) -> 1 | N1370: =ROUNDUP(IF(ISBLANK(G1370),AVERAGE(C:C,G1370,G:G),G1370),2) -> 863.11 | O1370: =M1370*N1370*(1-H1370) -> 621.4392 | P1370: =M1370*N1370 -> 863.11 | Q1370: =(P1370-O1370)/P1370 -> 0.28 | R1370: =IF(Sales_Fact!$O1370>1000,"High","Low") -> Low | S1370: =VLOOKUP(C1370,Customer_Dim!$A:$N,9,FALSE()) -> Christy Hoffman | T1370: =VLOOKUP(D1370,Product_Dim!$A:$M,3,FALSE()) -> Home | U1370: =VLOOKUP(D1370,Product_Dim!$A:$M,2,FALSE()) -> Modern Wall Clock | V1370: =VLOOKUP(E1370,Store_Dim!$A:$E,3,FALSE()) -> North | W1370: =VLOOKUP(C1370,Customer_Dim!$A:$N,13,FALSE()) -> Platinum | X1370: =IF(F1370>3,"High","Low") -> Low
A1371: SALE430 | B1371: 45445 | C1371: CUST1001 | D1371: PROD51 | E1371: STORE14 | F1371: 3 | G1371: 287.71 | H1371: 0.03 | I1371: COD | J1371: 837.2361 | K1371: =TEXT(B1371,"dd-mm-yyyy") -> 02-06-2024 | L1371: =TEXT(Sales_Fact!$B1371,"mmm") -> Jun | M1371: =IF(ISBLANK(F1371),1,F1371) -> 3 | N1371: =ROUNDUP(IF(ISBLANK(G1371),AVERAGE(C:C,G1371,G:G),G1371),2) -> 287.71 | O1371: =M1371*N1371*(1-H1371) -> 837.2361 | P1371: =M1371*N1371 -> 863.13 | Q1371: =(P1371-O1371)/P1371 -> 0.03 | R1371: =IF(Sales_Fact!$O1371>1000,"High","Low") -> Low | S1371: =VLOOKUP(C1371,Customer_Dim!$A:$N,9,FALSE()) -> Eugene Nelson | T1371: =VLOOKUP(D1371,Product_Dim!$A:$M,3,FALSE()) -> Electronics | U1371: =VLOOKUP(D1371,Product_Dim!$A:$M,2,FALSE()) -> HDMI Cable – 2m | V1371: =VLOOKUP(E1371,Store_Dim!$A:$E,3,FALSE()) -> South | W1371: =VLOOKUP(C1371,Customer_Dim!$A:$N,13,FALSE()) -> Platinum | X1371: =IF(F1371>3,"High","Low") -> Low
A1372: SALE431 | B1372: 45860 | C1372: CUST1094 | D1372: PROD67 | E1372: STORE6 | F1372: 2 | G1372: 849.8 | H1372: 0.06 | I1372: COD | J1372: 1597.624 | K1372: =TEXT(B1372,"dd-mm-yyyy") -> 22-07-2025 | L1372: =TEXT(Sales_Fact!$B1372,"mmm") -> Jul | M1372: =IF(ISBLANK(F1372),1,F1372) -> 2 | N1372: =ROUNDUP(IF(ISBLANK(G1372),AVERAGE(C:C,G1372,G:G),G1372),2) -> 849.8 | O1372: =M1372*N1372*(1-H1372) -> 1597.624 | P1372: =M1372*N1372 -> 1699.6 | Q1372: =(P1372-O1372)/P1372 -> 0.06 | R1372: =IF(Sales_Fact!$O1372>1000,"High","Low") -> High | S1372: =VLOOKUP(C1372,Customer_Dim!$A:$N,9,FALSE()) -> David Patterson | T1372: =VLOOKUP(D1372,Product_Dim!$A:$M,3,FALSE()) -> Electronics | U1372: =VLOOKUP(D1372,Product_Dim!$A:$M,2,FALSE()) -> Smart LED Light Strip | V1372: =VLOOKUP(E1372,Store_Dim!$A:$E,3,FALSE()) -> East | W1372: =VLOOKUP(C1372,Customer_Dim!$A:$N,13,FALSE()) -> Gold | X1372: =IF(F1372>3,"High","Low") -> Low
A1373: SALE432 | B1373: 45725 | C1373: CUST1016 | D1373: PROD41 | E1373: STORE3 | F1373: 3 | G1373: 482.58 | H1373: 0.28 | I1373: PayPal | J1373: 1042.3728 | K1373: =TEXT(B1373,"dd-mm-yyyy") -> 09-03-2025 | L1373: =TEXT(Sales_Fact!$B1373,"mmm") -> Mar | M1373: =IF(ISBLANK(F1373),1,F1373) -> 3 | N1373: =ROUNDUP(IF(ISBLANK(G1373),AVERAGE(C:C,G1373,G:G),G1373),2) -> 482.58 | O1373: =M1373*N1373*(1-H1373) -> 1042.3728 | P1373: =M1373*N1373 -> 1447.74 | Q1373: =(P1373-O1373)/P1373 -> 0.28 | R1373: =IF(Sales_Fact!$O1373>1000,"High","Low") -> High | S1373: =VLOOKUP(C1373,Customer_Dim!$A:$N,9,FALSE()) -> John Scott | T1373: =VLOOKUP(D1373,Product_Dim!$A:$M,3,FALSE()) -> Sports | U1373: =VLOOKUP(D1373,Product_Dim!$A:$M,2,FALSE()) -> Yoga Exercise Mat | V1373: =VLOOKUP(E1373,Store_Dim!$A:$E,3,FALSE()) -> North | W1373: =VLOOKUP(C1373,Customer_Dim!$A:$N,13,FALSE()) -> Bronze | X1373: =IF(F1373>3,"High","Low") -> Low
A1374: SALE433 | B1374: 45699 | C1374: CUST1114 | D1374: PROD59 | E1374: STORE2 | F1374: 2 | G1374: 64.7 | H1374: 0 | I1374: Credit Card | J1374: 129.4 | K1374: =TEXT(B1374,"dd-mm-yyyy") -> 11-02-2025 | L1374: =TEXT(Sales_Fact!$B1374,"mmm") -> Feb | M1374: =IF(ISBLANK(F1374),1,F1374) -> 2 | N1374: =ROUNDUP(IF(ISBLANK(G1374),AVERAGE(C:C,G1374,G:G),G1374),2) -> 64.7 | O1374: =M1374*N1374*(1-H1374) -> 129.4 | P1374: =M1374*N1374 -> 129.4 | Q1374: =(P1374-O1374)/P1374 -> 0 | R1374: =IF(Sales_Fact!$O1374>1000,"High","Low") -> Low | S1374: =VLOOKUP(C1374,Customer_Dim!$A:$N,9,FALSE()) -> Ryan Hernandez | T1374: =VLOOKUP(D1374,Product_Dim!$A:$M,3,FALSE()) -> Beauty | U1374: =VLOOKUP(D1374,Product_Dim!$A:$M,2,FALSE()) -> Men's Hair Styling Gel | V1374: =VLOOKUP(E1374,Store_Dim!$A:$E,3,FALSE()) -> South | W1374: =VLOOKUP(C1374,Customer_Dim!$A:$N,13,FALSE()) -> Bronze | X1374: =IF(F1374>3,"High","Low") -> Low
A1375: SALE434 | B1375: 45266 | C1375: CUST1148 | D1375: PROD5 | E1375: STORE5 | F1375: 3 | G1375: 589.83 | H1375: 0.26 | I1375: Credit Card | J1375: 1309.4226 | K1375: =TEXT(B1375,"dd-mm-yyyy") -> 06-12-2023 | L1375: =TEXT(Sales_Fact!$B1375,"mmm") -> Dec | M1375: =IF(ISBLANK(F1375),1,F1375) -> 3 | N1375: =ROUNDUP(IF(ISBLANK(G1375),AVERAGE(C:C,G1375,G:G),G1375),2) -> 589.83 | O1375: =M1375*N1375*(1-H1375) -> 1309.4226 | P1375: =M1375*N1375 -> 1769.49 | Q1375: =(P1375-O1375)/P1375 -> 0.26 | R1375: =IF(Sales_Fact!$O1375>1000,"High","Low") -> High | S1375: =VLOOKUP(C1375,Customer_Dim!$A:$N,9,FALSE()) -> Theresa Campbell | T1375: =VLOOKUP(D1375,Product_Dim!$A:$M,3,FALSE()) -> Clothing | U1375: =VLOOKUP(D1375,Product_Dim!$A:$M,2,FALSE()) -> Men's Leather Belt | V1375: =VLOOKUP(E1375,Store_Dim!$A:$E,3,FALSE()) -> North | W1375: =VLOOKUP(C1375,Customer_Dim!$A:$N,13,FALSE()) -> Bronze | X1375: =IF(F1375>3,"High","Low") -> Low
...

Sheet Toolpak
C3: TOTAL AMOUNT
C5: Mean | D5: 1085.48
C6: Standard Error | D6: 18.3149
C7: Median | D7: 866.7
C8: Mode | D8: =#N/A -> #N/A
C9: Standard Deviation | D9: 819.0674
C10: Sample Variance | D10: 670871.91
C11: Kurtosis | D11: 0.06322
C12: Skewness | D12: 0.88616
C13: Range | D13: 3889.7838
C14: Minimum | D14: 18.46
C15: Maximum | D15: 3908.2428
C16: Sum | D16: 2170969.8
C17: Count | D17: 2000

Sheet Pivot and Visualizations 
A3: store region | B3: Sum of Total_Amount | C3: Count of Product Name
A4: East | B4: 619851.21 | C4: 590
A5: North | B5: 645166.75 | C5: 596
A6: South | B6: 635213.1 | C6: 581
A7: West | B7: 270676.41 | C7: 233
A8: Grand Total | B8: 2170907.5 | C8: 2000
A11: Product Category | B11: Sum of Total_Amount
A12: Beauty | B12: 321362.09
A13: Clothing | B13: 377055.37
A14: Electronics | B14: 504311.35
A15: Home | B15: 427295.8
A16: Sports | B16: 540882.84
A17: Grand Total | B17: 2170907.5
A20: Count of Sales Perfomance | B20: Product Category
A21: Month | B21: Beauty | C21: Clothing | D21: Electronics | E21: Home | F21: Sports | G21: Grand Total
A22: Jan | B22: 28 | C22: 25 | D22: 43 | E22: 30 | F22: 38 | G22: 164
A23: Feb | B23: 20 | C23: 28 | D23: 31 | E23: 36 | F23: 44 | G23: 159
A24: Mar | B24: 27 | C24: 23 | D24: 42 | E24: 34 | F24: 57 | G24: 183
A25: Apr | B25: 28 | C25: 34 | D25: 27 | E25: 38 | F25: 34 | G25: 161
A26: May | B26: 25 | C26: 22 | D26: 43 | E26: 30 | F26: 38 | G26: 158
A27: Jun | B27: 29 | C27: 19 | D27: 42 | E27: 33 | F27: 32 | G27: 155
A28: Jul | B28: 37 | C28: 27 | D28: 39 | E28: 36 | F28: 45 | G28: 184
A29: Aug | B29: 21 | C29: 32 | D29: 40 | E29: 34 | F29: 44 | G29: 171
A30: Sep | B30: 13 | C30: 36 | D30: 42 | E30: 33 | F30: 41 | G30: 165
A31: Oct | B31: 24 | C31: 23 | D31: 41 | E31: 34 | F31: 45 | G31: 167
A32: Nov | B32: 29 | C32: 28 | D32: 33 | E32: 40 | F32: 36 | G32: 166
A33: Dec | B33: 23 | C33: 37 | D33: 31 | E33: 32 | F33: 44 | G33: 167
A34: Grand Total | B34: 304 | C34: 334 | D34: 454 | E34: 410 | F34: 498 | G34: 2000
A37: Loyalty Check | B37: Count of Customer_ID
A38: Bronze | B38: 487
A39: Gold | B39: 469
A40: Platinum | B40: 606
A41: Silver | B41: 422
A42: Standard | B42: 16
A43: Grand Total | B43: 2000
A45: Monthly Revenue Trend
A46: Month | B46: Total Revenue
A47: 45200 | B47: =SUMIFS(Sales_Fact!$O$2:$O$2001,Sales_Fact!$B$2:$B$2001,">="&A47,Sales_Fact!$B$2:$B$2001,"<"&EDATE(A47,1)) -> 43700.663
A48: 45231 | B48: =SUMIFS(Sales_Fact!$O$2:$O$2001,Sales_Fact!$B$2:$B$2001,">="&A48,Sales_Fact!$B$2:$B$2001,"<"&EDATE(A48,1)) -> 84402.869
A49: 45261 | B49: =SUMIFS(Sales_Fact!$O$2:$O$2001,Sales_Fact!$B$2:$B$2001,">="&A49,Sales_Fact!$B$2:$B$2001,"<"&EDATE(A49,1)) -> 94277.112
A50: 45292 | B50: =SUMIFS(Sales_Fact!$O$2:$O$2001,Sales_Fact!$B$2:$B$2001,">="&A50,Sales_Fact!$B$2:$B$2001,"<"&EDATE(A50,1)) -> 81336.269
A51: 45323 | B51: =SUMIFS(Sales_Fact!$O$2:$O$2001,Sales_Fact!$B$2:$B$2001,">="&A51,Sales_Fact!$B$2:$B$2001,"<"&EDATE(A51,1)) -> 83018.279
A52: 45352 | B52: =SUMIFS(Sales_Fact!$O$2:$O$2001,Sales_Fact!$B$2:$B$2001,">="&A52,Sales_Fact!$B$2:$B$2001,"<"&EDATE(A52,1)) -> 103306.93
A53: 45383 | B53: =SUMIFS(Sales_Fact!$O$2:$O$2001,Sales_Fact!$B$2:$B$2001,">="&A53,Sales_Fact!$B$2:$B$2001,"<"&EDATE(A53,1)) -> 90470.731
A54: 45413 | B54: =SUMIFS(Sales_Fact!$O$2:$O$2001,Sales_Fact!$B$2:$B$2001,">="&A54,Sales_Fact!$B$2:$B$2001,"<"&EDATE(A54,1)) -> 57825.221
A55: 45444 | B55: =SUMIFS(Sales_Fact!$O$2:$O$2001,Sales_Fact!$B$2:$B$2001,">="&A55,Sales_Fact!$B$2:$B$2001,"<"&EDATE(A55,1)) -> 97004.005
A56: 45474 | B56: =SUMIFS(Sales_Fact!$O$2:$O$2001,Sales_Fact!$B$2:$B$2001,">="&A56,Sales_Fact!$B$2:$B$2001,"<"&EDATE(A56,1)) -> 93582.269
A57: 45505 | B57: =SUMIFS(Sales_Fact!$O$2:$O$2001,Sales_Fact!$B$2:$B$2001,">="&A57,Sales_Fact!$B$2:$B$2001,"<"&EDATE(A57,1)) -> 92326.516
A58: 45536 | B58: =SUMIFS(Sales_Fact!$O$2:$O$2001,Sales_Fact!$B$2:$B$2001,">="&A58,Sales_Fact!$B$2:$B$2001,"<"&EDATE(A58,1)) -> 100811.46
... A71: 45931 | B71: =SUMIFS(Sales_Fact!$O$2:$O$2001,Sales_Fact!$B$2:$B$2001,">="&A71,Sales_Fact!$B$2:$B$2001,"<"&EDATE(A71,1)) -> 38467.816
A74: Top 10 Products by Revenue
A75: Product | B75: Revenue
A76: =INDEX(Helper_Data!$A$2:$A$101,MATCH(B76,Helper_Data!$B$2:$B$101,0)) -> Portable Power Bank | B76: =LARGE(Helper_Data!$B$2:$B$101,1) -> 41852.503
A77: =INDEX(Helper_Data!$A$2:$A$101,MATCH(B77,Helper_Data!$B$2:$B$101,0)) -> Shin Guards – Adult | B77: =LARGE(Helper_Data!$B$2:$B$101,2) -> 38281.015
A78: =INDEX(Helper_Data!$A$2:$A$101,MATCH(B78,Helper_Data!$B$2:$B$101,0)) -> Men's Casual Sneakers | B78: =LARGE(Helper_Data!$B$2:$B$101,3) -> 35489.62
A79: =INDEX(Helper_Data!$A$2:$A$101,MATCH(B79,Helper_Data!$B$2:$B$101,0)) -> Gaming Mechanical Keyboard | B79: =LARGE(Helper_Data!$B$2:$B$101,4) -> 34699.833
A80: =INDEX(Helper_Data!$A$2:$A$101,MATCH(B80,Helper_Data!$B$2:$B$101,0)) -> Women's High Heels | B80: =LARGE(Helper_Data!$B$2:$B$101,5) -> 33993.659
A81: =INDEX(Helper_Data!$A$2:$A$101,MATCH(B81,Helper_Data!$B$2:$B$101,0)) -> Wireless Mouse | B81: =LARGE(Helper_Data!$B$2:$B$101,6) -> 32792.731
A82: =INDEX(Helper_Data!$A$2:$A$101,MATCH(B82,Helper_Data!$B$2:$B$101,0)) -> Basketball | B82: =LARGE(Helper_Data!$B$2:$B$101,7) -> 31070.456
A83: =INDEX(Helper_Data!$A$2:$A$101,MATCH(B83,Helper_Data!$B$2:$B$101,0)) -> Men's Hair Styling Gel | B83: =LARGE(Helper_Data!$B$2:$B$101,8) -> 30236.698
A84: =INDEX(Helper_Data!$A$2:$A$101,MATCH(B84,Helper_Data!$B$2:$B$101,0)) -> Face Foundation Kit | B84: =LARGE(Helper_Data!$B$2:$B$101,9) -> 29293.838
A85: =INDEX(Helper_Data!$A$2:$A$101,MATCH(B85,Helper_Data!$B$2:$B$101,0)) -> 4K Home Projector | B85: =LARGE(Helper_Data!$B$2:$B$101,10) -> 28666.993
A88: Revenue by Payment Type
A89: Payment Type | B89: Revenue
A90: Credit Card | B90: =SUMIF(Sales_Fact!$I$2:$I$2001,A90,Sales_Fact!$O$2:$O$2001) -> 714811.97
A91: PayPal | B91: =SUMIF(Sales_Fact!$I$2:$I$2001,A91,Sales_Fact!$O$2:$O$2001) -> 755180.13
A92: COD | B92: =SUMIF(Sales_Fact!$I$2:$I$2001,A92,Sales_Fact!$O$2:$O$2001) -> 700977.71
A93: Grand Total | B93: =SUM(B90:B92) -> 2170969.8
A96: Sales Performance by Region
A97: Region | B97: High | C97: Low
A98: East | B98: =COUNTIFS(Sales_Fact!$V$2:$V$2001,A98,Sales_Fact!$R$2:$R$2001,"High") -> 263 | C98: =COUNTIFS(Sales_Fact!$V$2:$V$2001,A98,Sales_Fact!$R$2:$R$2001,"Low") -> 327
A99: North | B99: =COUNTIFS(Sales_Fact!$V$2:$V$2001,A99,Sales_Fact!$R$2:$R$2001,"High") -> 263 | C99: =COUNTIFS(Sales_Fact!$V$2:$V$2001,A99,Sales_Fact!$R$2:$R$2001,"Low") -> 333
A100: South | B100: =COUNTIFS(Sales_Fact!$V$2:$V$2001,A100,Sales_Fact!$R$2:$R$2001,"High") -> 254 | C100: =COUNTIFS(Sales_Fact!$V$2:$V$2001,A100,Sales_Fact!$R$2:$R$2001,"Low") -> 327
A101: West | B101: =COUNTIFS(Sales_Fact!$V$2:$V$2001,A101,Sales_Fact!$R$2:$R$2001,"High") -> 112 | C101: =COUNTIFS(Sales_Fact!$V$2:$V$2001,A101,Sales_Fact!$R$2:$R$2001,"Low") -> 121
A104: Average Order Value by Loyalty Tier
A105: Loyalty Tier | B105: Avg Order Value
A106: Platinum | B106: =AVERAGEIFS(Sales_Fact!$O$2:$O$2001,Sales_Fact!$W$2:$W$2001,A106) -> 1079.6102
A107: Gold | B107: =AVERAGEIFS(Sales_Fact!$O$2:$O$2001,Sales_Fact!$W$2:$W$2001,A107) -> 1103.2942
A108: Silver | B108: =AVERAGEIFS(Sales_Fact!$O$2:$O$2001,Sales_Fact!$W$2:$W$2001,A108) -> 1085.5199
A109: Bronze | B109: =AVERAGEIFS(Sales_Fact!$O$2:$O$2001,Sales_Fact!$W$2:$W$2001,A109) -> 1075.3168
A110: Standard | B110: =AVERAGEIFS(Sales_Fact!$O$2:$O$2001,Sales_Fact!$W$2:$W$2001,A110) -> 1094.521

Sheet Insights
B2: KEY INSIGHTS
B5: 1. Sales Performance
B7: Looking at the Category-wise sales.
B9: The Sports Category contributes the largest share of total sales.
B11: Total revenue in the Sports category is $540,882.82.
B12: ….....................................................................................................................................................
B14: 2. Region-wise Sales
B16: Looking at the Region-wise sales.
B18: The North Region has the highest sales record of $451,616.750.
B20: The West Region has the lowest sales record when compared to other regions with $270,676.406.
B22: …........................................................................................................................................................
B24: 3. Loyalty Level with Payment Method
... B164: Descriptive Statistical Pivot Table Chat Visualistaion Dash Baord creation

Sheet Helper_Data
A1: Product Name | B1: Revenue
A2: Cricket Bat | B2: =SUMIF(Sales_Fact!$U$2:$U$2001,A2,Sales_Fact!$O$2:$O$2001) -> 24566.339
A3: Bluetooth Car Audio System | B3: =SUMIF(Sales_Fact!$U$2:$U$2001,A3,Sales_Fact!$O$2:$O$2001) -> 21716.854
A4: Foldable Camping Chair | B4: =SUMIF(Sales_Fact!$U$2:$U$2001,A4,Sales_Fact!$O$2:$O$2001) -> 21414.866
A5: Modern Wall Clock | B5: =SUMIF(Sales_Fact!$U$2:$U$2001,A5,Sales_Fact!$O$2:$O$2001) -> 24127.17
A6: Men's Hair Styling Gel | B6: =SUMIF(Sales_Fact!$U$2:$U$2001,A6,Sales_Fact!$O$2:$O$2001) -> 30236.698
A7: Men's Sports Shorts | B7: =SUMIF(Sales_Fact!$U$2:$U$2001,A7,Sales_Fact!$O$2:$O$2001) -> 22117.246
A8: Shin Guards – Adult | B8: =SUMIF(Sales_Fact!$U$2:$U$2001,A8,Sales_Fact!$O$2:$O$2001) -> 38281.015
A9: Brother Laser Printer | B9: =SUMIF(Sales_Fact!$U$2:$U$2001,A9,Sales_Fact!$O$2:$O$2001) -> 17024.962
A10: Sports Stopwatch Pro | B10: =SUMIF(Sales_Fact!$U$2:$U$2001,A10,Sales_Fact!$O$2:$O$2001) -> 27344.748
A11: Men's Formal Shirt | B11: =SUMIF(Sales_Fact!$U$2:$U$2001,A11,Sales_Fact!$O$2:$O$2001) -> 12949.499
A12: Women's Ankle Boots | B12: =SUMIF(Sales_Fact!$U$2:$U$2001,A12,Sales_Fact!$O$2:$O$2001) -> 23180.13
A13: Organic Sunscreen Lotion | B13: =SUMIF(Sales_Fact!$U$2:$U$2001,A13,Sales_Fact!$O$2:$O$2001) -> 22597.402
... A101: Smart LED Light Strip | B101: =SUMIF(Sales_Fact!$U$2:$U$2001,A101,Sales_Fact!$O$2:$O$2001) -> 27348.156
